Workbook

Sheet 00_LEIA_ME
B2: NEXA | FP&A INTEGRADO
B6: Projeto | C6: Projeto autoral demonstrativo de Gustavo Xavier. Empresa, operações e resultados integralmente fictícios.
B7: Negócio | C7: Distribuidora B2B de equipamentos tecnológicos: três famílias de produtos, três regiões e dois canais de venda.
B8: Período | C8: 24 meses realizados: jan/2024 a dez/2025. Orçamento dos dois anos. Forecast 2025 com corte em jun/2025 e três cenários para 2026.
B9: Comece aqui | C9: Abra 01_PAINEL. Selecione cenário e ano. DRE, BP, DFC e indicadores mensais acompanham essa seleção.
B10: Planejamento | C10: Premissas em azul na aba 08_PREMISSAS. Forecast 6+6 usa jan–jun realizados e premissas de jul–dez. Os cenários 2026 partem do BP de dez/2025 realizado.
B11: Integração | C11: Receita e CMV → resultado. Clientes, estoque e fornecedores → capital de giro. Capex e depreciação → imobilizado. Lucro → PL. Fluxos → caixa.
B12: Auditoria | C12: 07_CHECKS compara ativo/passivo/PL, DFC direto/indireto e os valores realizados com o diário de partidas dobradas. Tolerância: R$ 0,01.
B13: Base histórica | C13: Vendas, despesas e diário são snapshots fictícios. Alterações no histórico exigem regenerar as bases e o diário com o script; mudanças de planejamento recalculam por fórmulas.
B14: Convenções | C14: DRE: despesas positivas subtraídas nos subtotais. DFC: entradas positivas e saídas negativas. MoM/YoY sem base disponível ficam vazios, nunca zero.
B15: Simplificações | C15: Tributos são premissas pedagógicas; sem créditos tributários, diferidos ou enquadramento fiscal. Juros pagos classificados em operação. Dividendos em financiamento. Receita reconhecida na entrega.
B16: Saldos | C16: Saldo inicial em 31/12/2023 explícito. BP e DFC de orçamento seguem trilha própria; a diferença de dezembro/2024 orçado x realizado é preservada.
B17: Tecnologias | C17: Excel 2021+ sem VBA e sem funções exclusivas do Microsoft 365. CSV UTF-8 e medidas DAX para desenvolver o relatório em Power BI.
B18: Uso comercial | C18: Apresentar como Projeto Autoral. Não atribuir os resultados simulados a clientes ou à experiência profissional anterior.

Sheet 09_VENDAS
A1: Data | B1: ProdutoID | C1: Produto | D1: Regiao | E1: Canal | F1: Quantidade | G1: PrecoUnitario | H1: CustoUnitario | I1: ReceitaBruta | J1: CMV
A2: 45292 | B2: P01 | C2: Estações de trabalho | D2: Sudeste | E2: Venda direta | F2: 83 | G2: 2646.8 | H2: 1820 | I2: 219684.4 | J2: 151060
A3: 45292 | B3: P01 | C3: Estações de trabalho | D3: Sudeste | E3: Parceiros | F3: 46 | G3: 2496 | H3: 1820 | I3: 114816 | J3: 83720
A4: 45292 | B4: P01 | C4: Estações de trabalho | D4: Sul | E4: Venda direta | F4: 37 | G4: 2646.8 | H4: 1820 | I4: 97931.6 | J4: 67340
A5: 45292 | B5: P01 | C5: Estações de trabalho | D5: Sul | E5: Parceiros | F5: 20 | G5: 2496 | H5: 1820 | I5: 49920 | J5: 36400
A6: 45292 | B6: P01 | C6: Estações de trabalho | D6: Nordeste | E6: Venda direta | F6: 26 | G6: 2646.8 | H6: 1820 | I6: 68816.8 | J6: 47320
A7: 45292 | B7: P01 | C7: Estações de trabalho | D7: Nordeste | E7: Parceiros | F7: 15 | G7: 2496 | H7: 1820 | I7: 37440 | J7: 27300
A8: 45292 | B8: P02 | C8: Equipamentos de rede | D8: Sudeste | E8: Venda direta | F8: 60 | G8: 1679.7 | H8: 990 | I8: 100782 | J8: 59400
A9: 45292 | B9: P02 | C9: Equipamentos de rede | D9: Sudeste | E9: Parceiros | F9: 32 | G9: 1584 | H9: 990 | I9: 50688 | J9: 31680
A10: 45292 | B10: P02 | C10: Equipamentos de rede | D10: Sul | E10: Venda direta | F10: 27 | G10: 1679.7 | H10: 990 | I10: 45351.9 | J10: 26730
A11: 45292 | B11: P02 | C11: Equipamentos de rede | D11: Sul | E11: Parceiros | F11: 13 | G11: 1584 | H11: 990 | I11: 20592 | J11: 12870
A12: 45292 | B12: P02 | C12: Equipamentos de rede | D12: Nordeste | E12: Venda direta | F12: 20 | G12: 1679.7 | H12: 990 | I12: 33594 | J12: 19800
A13: 45292 | B13: P02 | C13: Equipamentos de rede | D13: Nordeste | E13: Parceiros | F13: 10 | G13: 1584 | H13: 990 | I13: 15840 | J13: 9900
... A433: 45992 | B433: P03 | C433: Periféricos profissionais | D433: Nordeste | E433: Parceiros | F433: 11 | G433: 682.18 | H433: 399.76 | I433: 7503.98 | J433: 4397.36

Sheet 10_DESPESAS
A1: Data | B1: CentroCusto | C1: Conta | D1: Valor
A2: 45292 | B2: Pessoal | C2: Pessoal | D2: 95000
A3: 45292 | B3: Comercial | C3: Comissões | D3: 33483.76
A4: 45292 | B4: Administrativo | C4: Aluguel e serviços | D4: 32000
A5: 45292 | B5: Tecnologia | C5: Software e infraestrutura | D5: 18000
A6: 45292 | B6: Operações | C6: Logística | D6: 20462.3
A7: 45323 | B7: Pessoal | C7: Pessoal | D7: 95000
A8: 45323 | B8: Comercial | C8: Comissões | D8: 35030.03
A9: 45323 | B9: Administrativo | C9: Aluguel e serviços | D9: 32000
A10: 45323 | B10: Tecnologia | C10: Software e infraestrutura | D10: 18000
A11: 45323 | B11: Operações | C11: Logística | D11: 21407.24
A12: 45352 | B12: Pessoal | C12: Pessoal | D12: 95000
A13: 45352 | B13: Comercial | C13: Comissões | D13: 41009.46
... A123: 45992 | B123: Operações | C123: Logística | D123: 37292.73

Sheet 08_PREMISSAS
A1: Data | B1: Cenario | C1: Quantidade | D1: TicketMedio | E1: CMVPercentual | F1: TaxaComercial | G1: TaxaLogistica | H1: ReceitaBruta | I1: CMV | J1: Pessoal | K1: Comercial | L1: Administrativo | M1: Tecnologia | N1: Logistica | O1: DSO | P1: DIO | Q1: DPO | R1: TaxaVenda | S1: TaxaIR | T1: TaxaJuros | U1: TaxaDep | V1: Capex | W1: Captacao | X1: Amortizacao | Y1: Dividendos
A2: 45292 | B2: Realizado | C2: 499 | D2: 1863.9366 | E2: 0.66156016 | F2: 0.036000002 | G2: 0.022000004 | H2: 930104.38 | I2: 615320 | J2: 95000 | K2: 33483.76 | L2: 32000 | M2: 18000 | N2: 20462.3 | O2: 40 | P2: 46 | Q2: 35 | R2: 0.085 | S2: 0.34 | T2: 0.012 | U2: 0.01 | V2: 18000 | W2: 0 | X2: 18000 | Y2: 0
A3: 45323 | B3: Realizado | C3: 523 | D3: 1860.5286 | E3: 0.66091744 | F3: 0.035999997 | G3: 0.021999997 | H3: 973056.48 | I3: 643110 | J3: 95000 | K3: 35030.03 | L3: 32000 | M3: 18000 | N3: 21407.24 | O3: 40 | P3: 46 | Q3: 35 | R3: 0.085 | S3: 0.34 | T3: 0.012 | U3: 0.01 | V3: 18000 | W3: 0 | X3: 18000 | Y3: 0
A4: 45352 | B4: Realizado | C4: 612 | D4: 1861.3587 | E4: 0.66086905 | F4: 0.036000004 | G4: 0.021999997 | H4: 1139151.5 | I4: 752830 | J4: 95000 | K4: 41009.46 | L4: 32000 | M4: 18000 | N4: 25061.33 | O4: 40 | P4: 46 | Q4: 35 | R4: 0.085 | S4: 0.34 | T4: 0.012 | U4: 0.01 | V4: 90000 | W4: 0 | X4: 18000 | Y4: 0
A5: 45383 | B5: Realizado | C5: 611 | D5: 1865.4973 | E5: 0.66145597 | F5: 0.036 | G5: 0.022000004 | H5: 1139818.9 | I5: 753940 | J5: 95000 | K5: 41033.48 | L5: 32000 | M5: 18000 | N5: 25076.02 | O5: 40 | P5: 46 | Q5: 35 | R5: 0.085 | S5: 0.34 | T5: 0.012 | U5: 0.01 | V5: 18000 | W5: 0 | X5: 18000 | Y5: 0
A6: 45413 | B6: Realizado | C6: 635 | D6: 1867.7797 | E6: 0.66205183 | F6: 0.035999998 | G6: 0.021999999 | H6: 1186040.1 | I6: 785220 | J6: 95000 | K6: 42697.44 | L6: 32000 | M6: 18000 | N6: 26092.88 | O6: 40 | P6: 46 | Q6: 35 | R6: 0.085 | S6: 0.34 | T6: 0.012 | U6: 0.01 | V6: 18000 | W6: 0 | X6: 18000 | Y6: 0
A7: 45444 | B7: Realizado | C7: 654 | D7: 1877.9673 | E7: 0.66190052 | F7: 0.035999999 | G7: 0.021999997 | H7: 1228190.6 | I7: 812940 | J7: 95000 | K7: 44214.86 | L7: 32000 | M7: 18000 | N7: 27020.19 | O7: 40 | P7: 46 | Q7: 35 | R7: 0.085 | S7: 0.34 | T7: 0.012 | U7: 0.01 | V7: 90000 | W7: 0 | X7: 18000 | Y7: 0
A8: 45474 | B8: Realizado | C8: 578 | D8: 1875.1816 | E8: 0.66267169 | F8: 0.036000001 | G8: 0.022000001 | H8: 1083855 | I8: 718240 | J8: 98800 | K8: 39018.78 | L8: 32000 | M8: 18000 | N8: 23844.81 | O8: 40 | P8: 46 | Q8: 35 | R8: 0.085 | S8: 0.34 | T8: 0.012 | U8: 0.01 | V8: 18000 | W8: 0 | X8: 18000 | Y8: 0
A9: 45505 | B9: Realizado | C9: 629 | D9: 1865.5681 | E9: 0.66160047 | F9: 0.035999996 | G9: 0.021999999 | H9: 1173442.3 | I9: 776350 | J9: 98800 | K9: 42243.92 | L9: 32000 | M9: 18000 | N9: 25815.73 | O9: 40 | P9: 46 | Q9: 35 | R9: 0.085 | S9: 0.34 | T9: 0.012 | U9: 0.01 | V9: 18000 | W9: 0 | X9: 18000 | Y9: 0
A10: 45536 | B10: Realizado | C10: 654 | D10: 1863.8934 | E10: 0.66081139 | F10: 0.036000004 | G10: 0.022000002 | H10: 1218986.3 | I10: 805520 | J10: 98800 | K10: 43883.51 | L10: 32000 | M10: 18000 | N10: 26817.7 | O10: 40 | P10: 46 | Q10: 35 | R10: 0.085 | S10: 0.34 | T10: 0.012 | U10: 0.01 | V10: 90000 | W10: 0 | X10: 18000 | Y10: 0
A11: 45566 | B11: Realizado | C11: 707 | D11: 1890.3489 | E11: 0.66251063 | F11: 0.036 | G11: 0.022000003 | H11: 1336476.7 | I11: 885430 | J11: 98800 | K11: 48113.16 | L11: 32000 | M11: 18000 | N11: 29402.49 | O11: 40 | P11: 46 | Q11: 35 | R11: 0.085 | S11: 0.34 | T11: 0.012 | U11: 0.01 | V11: 18000 | W11: 0 | X11: 18000 | Y11: 0
A12: 45597 | B12: Realizado | C12: 800 | D12: 1880.5154 | E12: 0.66223866 | F12: 0.035999998 | G12: 0.021999999 | H12: 1504412.3 | I12: 996280 | J12: 98800 | K12: 54158.84 | L12: 32000 | M12: 18000 | N12: 33097.07 | O12: 40 | P12: 46 | Q12: 35 | R12: 0.085 | S12: 0.34 | T12: 0.012 | U12: 0.01 | V12: 18000 | W12: 0 | X12: 18000 | Y12: 0
A13: 45627 | B13: Realizado | C13: 735 | D13: 1879.8906 | E13: 0.66231239 | F13: 0.035999996 | G13: 0.021999999 | H13: 1381719.6 | I13: 915130 | J13: 98800 | K13: 49741.9 | L13: 32000 | M13: 18000 | N13: 30397.83 | O13: 40 | P13: 46 | Q13: 35 | R13: 0.085 | S13: 0.34 | T13: 0.012 | U13: 0.01 | V13: 90000 | W13: 0 | X13: 18000 | Y13: 0
... A97: 46357 | B97: Adverso 2026 | C97: 897 | D97: 1776.3842 | E97: 0.701 | F97: 0.035 | G97: 0.023 | H97: 1593416.6 | I97: 1116985.1 | J97: 125000 | K97: 55769.58 | L97: 37000 | M97: 24000 | N97: 36648.58 | O97: 65 | P97: 68 | Q97: 30 | R97: 0.085 | S97: 0.34 | T97: 0.012 | U97: 0.01 | V97: 120000 | W97: 0 | X97: 18000 | Y97: 0

Sheet 11_SALDO_INICIAL
A1: Conta | B1: Saldo
A2: CaixaFinal | B2: 3000000
A3: Clientes | B3: 900000
A4: Estoque | B4: 700000
A5: Fornecedores | B5: 550000
A6: SalariosPagar | B6: 40000
A7: TributosVendaPagar | B7: 80000
A8: IRPagar | B8: 50000
A9: ImobilizadoBruto | B9: 1500000
A10: DepAcumulada | B10: 300000
A11: Divida | B11: 800000
A12: Capital | B12: 3900000
A13: LucrosAcumulados | B13: 380000

Sheet 12_MODELO
A1: Data | B1: Cenario | C1: ReceitaBruta | D1: Deducoes | E1: ReceitaLiquida | F1: CMV | G1: LucroBruto | H1: Pessoal | I1: Comercial | J1: Administrativo | K1: Tecnologia | L1: Logistica | M1: Opex | N1: EBITDA | O1: Depreciacao | P1: EBIT | Q1: Juros | R1: LAIR | S1: IRSimulado | T1: LucroLiquido | U1: Clientes | V1: Estoque | W1: Compras | X1: Fornecedores | Y1: SalariosPagar | Z1: TributosVendaPagar | AA1: IRPagar | AB1: Capex | AC1: ImobilizadoBruto | AD1: DepAcumulada | AE1: Captacao | AF1: Amortizacao | AG1: Divida | AH1: Dividendos | AI1: Capital | AJ1: LucrosAcumulados | AK1: Recebimentos | AL1: PagFornecedores | AM1: PagOpex | AN1: PagTributosVenda | AO1: PagIR | AP1: FCO_Direto | AQ1: FCO_Indireto | AR1: FCI | AS1: FCF | AT1: VariacaoCaixa | AU1: CaixaInicial | AV1: CaixaFinal | AW1: Ativo | AX1: Passivo | AY1: PL | AZ1: CheckBP | BA1: CheckDFC | BB1: DSO | BC1: DIO | BD1: DPO | BE1: TaxaVenda | BF1: TaxaIR | BG1: TaxaJuros | BH1: TaxaDep | BI1: MargemEBITDA | BJ1: MargemLiquida | BK1: FC_Livre | BL1: NCG | BM1: DividaLiquida | BN1: CheckDiario | BO1: AtivoCirculante | BP1: AtivoNaoCirculante | BQ1: DividaCP | BR1: DividaLP | BS1: PassivoCirculante | BT1: PassivoNaoCirculante | BU1: LiquidezCorrente
A2: 45292 | B2: Realizado | C2: =SUMIFS('09_VENDAS'!I$2:I$433,'09_VENDAS'!A$2:A$433,'12_MODELO'!A2) -> 930104.38 | D2: ='12_MODELO'!C2*'12_MODELO'!BE2 -> 79058.872 | E2: ='12_MODELO'!C2-'12_MODELO'!D2 -> 851045.51 | F2: =SUMIFS('09_VENDAS'!J$2:J$433,'09_VENDAS'!A$2:A$433,'12_MODELO'!A2) -> 615320 | G2: ='12_MODELO'!E2-'12_MODELO'!F2 -> 235725.51 | H2: =SUMIFS('10_DESPESAS'!D$2:D$123,'10_DESPESAS'!A$2:A$123,'12_MODELO'!A2,'10_DESPESAS'!B$2:B$123,"Pessoal") -> 95000 | I2: =SUMIFS('10_DESPESAS'!D$2:D$123,'10_DESPESAS'!A$2:A$123,'12_MODELO'!A2,'10_DESPESAS'!B$2:B$123,"Comercial") -> 33483.76 | J2: =SUMIFS('10_DESPESAS'!D$2:D$123,'10_DESPESAS'!A$2:A$123,'12_MODELO'!A2,'10_DESPESAS'!B$2:B$123,"Administrativo") -> 32000 | K2: =SUMIFS('10_DESPESAS'!D$2:D$123,'10_DESPESAS'!A$2:A$123,'12_MODELO'!A2,'10_DESPESAS'!B$2:B$123,"Tecnologia") -> 18000 | L2: =SUMIFS('10_DESPESAS'!D$2:D$123,'10_DESPESAS'!A$2:A$123,'12_MODELO'!A2,'10_DESPESAS'!B$2:B$123,"Operações") -> 20462.3 | M2: =SUM('12_MODELO'!H2:'12_MODELO'!L2) -> 198946.06 | N2: ='12_MODELO'!G2-'12_MODELO'!M2 -> 36779.448 | O2: =MIN('11_SALDO_INICIAL'!B9*'12_MODELO'!BH2,'11_SALDO_INICIAL'!B9-'11_SALDO_INICIAL'!B10+'12_MODELO'!AB2) -> 15000 | P2: ='12_MODELO'!N2-'12_MODELO'!O2 -> 21779.448 | Q2: ='11_SALDO_INICIAL'!B11*'12_MODELO'!BG2 -> 9600 | R2: ='12_MODELO'!P2-'12_MODELO'!Q2 -> 12179.448 | S2: =MAX(0,'12_MODELO'!R2)*'12_MODELO'!BF2 -> 4141.0122 | T2: ='12_MODELO'!R2-'12_MODELO'!S2 -> 8038.4355 | U2: ='12_MODELO'!C2*'12_MODELO'!BB2/30 -> 1240139.2 | V2: ='12_MODELO'!F2*'12_MODELO'!BC2/30 -> 943490.67 | W2: ='12_MODELO'!F2+'12_MODELO'!V2-'11_SALDO_INICIAL'!B4 -> 858810.67 | X2: ='12_MODELO'!F2*'12_MODELO'!BD2/30 -> 717873.33 | Y2: ='12_MODELO'!H2*20% -> 19000 | Z2: ='12_MODELO'!D2 -> 79058.872 | AA2: ='12_MODELO'!S2 -> 4141.0122 | AB2: ='08_PREMISSAS'!V2 -> 18000 | AC2: ='11_SALDO_INICIAL'!B9+'12_MODELO'!AB2 -> 1518000 | AD2: ='11_SALDO_INICIAL'!B10+'12_MODELO'!O2 -> 315000 | AE2: ='08_PREMISSAS'!W2 -> 0 | AF2: ='08_PREMISSAS'!X2 -> 18000 | AG2: ='11_SALDO_INICIAL'!B11+'12_MODELO'!AE2-'12_MODELO'!AF2 -> 782000 | AH2: ='08_PREMISSAS'!Y2 -> 0 | AI2: ='11_SALDO_INICIAL'!B12 -> 3900000 | AJ2: ='11_SALDO_INICIAL'!B13+'12_MODELO'!T2-'12_MODELO'!AH2 -> 388038.44 | AK2: ='11_SALDO_INICIAL'!B3+'12_MODELO'!C2-'12_MODELO'!U2 -> 589965.21 | AL2: ='11_SALDO_INICIAL'!B5+'12_MODELO'!W2-'12_MODELO'!X2 -> 690937.33 | AM2: ='12_MODELO'!M2+'11_SALDO_INICIAL'!B6-'12_MODELO'!Y2 -> 219946.06 | AN2: ='11_SALDO_INICIAL'!B7+'12_MODELO'!D2-'12_MODELO'!Z2 -> 80000 | AO2: ='11_SALDO_INICIAL'!B8+'12_MODELO'!S2-'12_MODELO'!AA2 -> 50000 | AP2: ='12_MODELO'!AK2-'12_MODELO'!AL2-'12_MODELO'!AM2-'12_MODELO'!AN2-'12_MODELO'!Q2-'12_MODELO'!AO2 -> -460518.19 | AQ2: ='12_MODELO'!T2+'12_MODELO'!O2-('12_MODELO'!U2-'11_SALDO_INICIAL'!B3)-('12_MODELO'!V2-'11_SALDO_INICIAL'!B4)+('12_MODELO'!X2-'11_SALDO_INICIAL'!B5)+('12_MODELO'!Y2-'11_SALDO_INICIAL'!B6)+('12_MODELO'!Z2-'11_SALDO_INICIAL'!B7)+('12_MODELO'!AA2-'11_SALDO_INICIAL'!B8) -> -460518.19 | AR2: =-'12_MODELO'!AB2 -> -18000 | AS2: ='12_MODELO'!AE2-'12_MODELO'!AF2-'12_MODELO'!AH2 -> -18000 | AT2: ='12_MODELO'!AQ2+'12_MODELO'!AR2+'12_MODELO'!AS2 -> -496518.19 | AU2: ='11_SALDO_INICIAL'!B2 -> 3000000 | AV2: ='12_MODELO'!AU2+'12_MODELO'!AT2 -> 2503481.8 | AW2: ='12_MODELO'!AV2+'12_MODELO'!U2+'12_MODELO'!V2+'12_MODELO'!AC2-'12_MODELO'!AD2 -> 5890111.7 | AX2: ='12_MODELO'!X2+'12_MODELO'!Y2+'12_MODELO'!Z2+'12_MODELO'!AA2+'12_MODELO'!AG2 -> 1602073.2 | AY2: ='12_MODELO'!AI2+'12_MODELO'!AJ2 -> 4288038.4 | AZ2: ='12_MODELO'!AW2-'12_MODELO'!AX2-'12_MODELO'!AY2 -> 0 | BA2: ='12_MODELO'!AP2-'12_MODELO'!AQ2 -> 0 | BB2: ='08_PREMISSAS'!O2 -> 40 | BC2: ='08_PREMISSAS'!P2 -> 46 | BD2: ='08_PREMISSAS'!Q2 -> 35 | BE2: ='08_PREMISSAS'!R2 -> 0.085 | BF2: ='08_PREMISSAS'!S2 -> 0.34 | BG2: ='08_PREMISSAS'!T2 -> 0.012 | BH2: ='08_PREMISSAS'!U2 -> 0.01 | BI2: =IFERROR('12_MODELO'!N2/'12_MODELO'!E2,0) -> 0.043216781 | BJ2: =IFERROR('12_MODELO'!T2/'12_MODELO'!E2,0) -> 0.009445365 | BK2: ='12_MODELO'!AQ2+'12_MODELO'!AR2 -> -478518.19 | BL2: ='12_MODELO'!U2+'12_MODELO'!V2-'12_MODELO'!X2-'12_MODELO'!Y2-'12_MODELO'!Z2-'12_MODELO'!AA2 -> 1363556.6 | BM2: ='12_MODELO'!AG2-'12_MODELO'!AV2 -> -1721481.8 | BN2: =MAX(ABS('15_CONCILIACAO'!F2),ABS('15_CONCILIACAO'!F3),ABS('15_CONCILIACAO'!F4),ABS('15_CONCILIACAO'!F5),ABS('15_CONCILIACAO'!F6),ABS('15_CONCILIACAO'!F7),ABS('15_CONCILIACAO'!F8),ABS('15_CONCILIACAO'!F9),ABS('15_CONCILIACAO'!F10),ABS('15_CONCILIACAO'!F11),ABS('15_CONCILIACAO'!F12),ABS('15_CONCILIACAO'!F13)) -> 4.6566129e-10 | BO2: ='12_MODELO'!AV2+'12_MODELO'!U2+'12_MODELO'!V2 -> 4687111.7 | BP2: ='12_MODELO'!AC2-'12_MODELO'!AD2 -> 1203000 | BQ2: =MIN('12_MODELO'!AG2,'12_MODELO'!AF2*12) -> 216000 | BR2: ='12_MODELO'!AG2-'12_MODELO'!BQ2 -> 566000 | BS2: ='12_MODELO'!AX2-'12_MODELO'!BR2 -> 1036073.2 | BT2: ='12_MODELO'!BR2 -> 566000 | BU2: =IFERROR('12_MODELO'!BO2/'12_MODELO'!BS2,0) -> 4.5239193
A3: 45323 | B3: Realizado | C3: =SUMIFS('09_VENDAS'!I$2:I$433,'09_VENDAS'!A$2:A$433,'12_MODELO'!A3) -> 973056.48 | D3: ='12_MODELO'!C3*'12_MODELO'!BE3 -> 82709.801 | E3: ='12_MODELO'!C3-'12_MODELO'!D3 -> 890346.68 | F3: =SUMIFS('09_VENDAS'!J$2:J$433,'09_VENDAS'!A$2:A$433,'12_MODELO'!A3) -> 643110 | G3: ='12_MODELO'!E3-'12_MODELO'!F3 -> 247236.68 | H3: =SUMIFS('10_DESPESAS'!D$2:D$123,'10_DESPESAS'!A$2:A$123,'12_MODELO'!A3,'10_DESPESAS'!B$2:B$123,"Pessoal") -> 95000 | I3: =SUMIFS('10_DESPESAS'!D$2:D$123,'10_DESPESAS'!A$2:A$123,'12_MODELO'!A3,'10_DESPESAS'!B$2:B$123,"Comercial") -> 35030.03 | J3: =SUMIFS('10_DESPESAS'!D$2:D$123,'10_DESPESAS'!A$2:A$123,'12_MODELO'!A3,'10_DESPESAS'!B$2:B$123,"Administrativo") -> 32000 | K3: =SUMIFS('10_DESPESAS'!D$2:D$123,'10_DESPESAS'!A$2:A$123,'12_MODELO'!A3,'10_DESPESAS'!B$2:B$123,"Tecnologia") -> 18000 | L3: =SUMIFS('10_DESPESAS'!D$2:D$123,'10_DESPESAS'!A$2:A$123,'12_MODELO'!A3,'10_DESPESAS'!B$2:B$123,"Operações") -> 21407.24 | M3: =SUM('12_MODELO'!H3:'12_MODELO'!L3) -> 201437.27 | N3: ='12_MODELO'!G3-'12_MODELO'!M3 -> 45799.409 | O3: =MIN('12_MODELO'!AC2*'12_MODELO'!BH3,'12_MODELO'!AC2-'12_MODELO'!AD2+'12_MODELO'!AB3) -> 15180 | P3: ='12_MODELO'!N3-'12_MODELO'!O3 -> 30619.409 | Q3: ='12_MODELO'!AG2*'12_MODELO'!BG3 -> 9384 | R3: ='12_MODELO'!P3-'12_MODELO'!Q3 -> 21235.409 | S3: =MAX(0,'12_MODELO'!R3)*'12_MODELO'!BF3 -> 7220.0391 | T3: ='12_MODELO'!R3-'12_MODELO'!S3 -> 14015.37 | U3: ='12_MODELO'!C3*'12_MODELO'!BB3/30 -> 1297408.6 | V3: ='12_MODELO'!F3*'12_MODELO'!BC3/30 -> 986102 | W3: ='12_MODELO'!F3+'12_MODELO'!V3-'12_MODELO'!V2 -> 685721.33 | X3: ='12_MODELO'!F3*'12_MODELO'!BD3/30 -> 750295 | Y3: ='12_MODELO'!H3*20% -> 19000 | Z3: ='12_MODELO'!D3 -> 82709.801 | AA3: ='12_MODELO'!S3 -> 7220.0391 | AB3: ='08_PREMISSAS'!V3 -> 18000 | AC3: ='12_MODELO'!AC2+'12_MODELO'!AB3 -> 1536000 | AD3: ='12_MODELO'!AD2+'12_MODELO'!O3 -> 330180 | AE3: ='08_PREMISSAS'!W3 -> 0 | AF3: ='08_PREMISSAS'!X3 -> 18000 | AG3: ='12_MODELO'!AG2+'12_MODELO'!AE3-'12_MODELO'!AF3 -> 764000 | AH3: ='08_PREMISSAS'!Y3 -> 0 | AI3: ='12_MODELO'!AI2 -> 3900000 | AJ3: ='12_MODELO'!AJ2+'12_MODELO'!T3-'12_MODELO'!AH3 -> 402053.81 | AK3: ='12_MODELO'!U2+'12_MODELO'!C3-'12_MODELO'!U3 -> 915787.01 | AL3: ='12_MODELO'!X2+'12_MODELO'!W3-'12_MODELO'!X3 -> 653299.67 | AM3: ='12_MODELO'!M3+'12_MODELO'!Y2-'12_MODELO'!Y3 -> 201437.27 | AN3: ='12_MODELO'!Z2+'12_MODELO'!D3-'12_MODELO'!Z3 -> 79058.872 | AO3: ='12_MODELO'!AA2+'12_MODELO'!S3-'12_MODELO'!AA3 -> 4141.0122 | AP3: ='12_MODELO'!AK3-'12_MODELO'!AL3-'12_MODELO'!AM3-'12_MODELO'!AN3-'12_MODELO'!Q3-'12_MODELO'!AO3 -> -31533.808 | AQ3: ='12_MODELO'!T3+'12_MODELO'!O3-('12_MODELO'!U3-'12_MODELO'!U2)-('12_MODELO'!V3-'12_MODELO'!V2)+('12_MODELO'!X3-'12_MODELO'!X2)+('12_MODELO'!Y3-'12_MODELO'!Y2)+('12_MODELO'!Z3-'12_MODELO'!Z2)+('12_MODELO'!AA3-'12_MODELO'!AA2) -> -31533.808 | AR3: =-'12_MODELO'!AB3 -> -18000 | AS3: ='12_MODELO'!AE3-'12_MODELO'!AF3-'12_MODELO'!AH3 -> -18000 | AT3: ='12_MODELO'!AQ3+'12_MODELO'!AR3+'12_MODELO'!AS3 -> -67533.808 | AU3: ='12_MODELO'!AV2 -> 2503481.8 | AV3: ='12_MODELO'!AU3+'12_MODELO'!AT3 -> 2435948 | AW3: ='12_MODELO'!AV3+'12_MODELO'!U3+'12_MODELO'!V3+'12_MODELO'!AC3-'12_MODELO'!AD3 -> 5925278.6 | AX3: ='12_MODELO'!X3+'12_MODELO'!Y3+'12_MODELO'!Z3+'12_MODELO'!AA3+'12_MODELO'!AG3 -> 1623224.8 | AY3: ='12_MODELO'!AI3+'12_MODELO'!AJ3 -> 4302053.8 | AZ3: ='12_MODELO'!AW3-'12_MODELO'!AX3-'12_MODELO'!AY3 -> 0 | BA3: ='12_MODELO'!AP3-'12_MODELO'!AQ3 -> -5.0931703e-11 | BB3: ='08_PREMISSAS'!O3 -> 40 | BC3: ='08_PREMISSAS'!P3 -> 46 | BD3: ='08_PREMISSAS'!Q3 -> 35 | BE3: ='08_PREMISSAS'!R3 -> 0.085 | BF3: ='08_PREMISSAS'!S3 -> 0.34 | BG3: ='08_PREMISSAS'!T3 -> 0.012 | BH3: ='08_PREMISSAS'!U3 -> 0.01 | BI3: =IFERROR('12_MODELO'!N3/'12_MODELO'!E3,0) -> 0.051439973 | BJ3: =IFERROR('12_MODELO'!T3/'12_MODELO'!E3,0) -> 0.015741475 | BK3: ='12_MODELO'!AQ3+'12_MODELO'!AR3 -> -49533.808 | BL3: ='12_MODELO'!U3+'12_MODELO'!V3-'12_MODELO'!X3-'12_MODELO'!Y3-'12_MODELO'!Z3-'12_MODELO'!AA3 -> 1424285.8 | BM3: ='12_MODELO'!AG3-'12_MODELO'!AV3 -> -1671948 | BN3: =MAX(ABS('15_CONCILIACAO'!F14),ABS('15_CONCILIACAO'!F15),ABS('15_CONCILIACAO'!F16),ABS('15_CONCILIACAO'!F17),ABS('15_CONCILIACAO'!F18),ABS('15_CONCILIACAO'!F19),ABS('15_CONCILIACAO'!F20),ABS('15_CONCILIACAO'!F21),ABS('15_CONCILIACAO'!F22),ABS('15_CONCILIACAO'!F23),ABS('15_CONCILIACAO'!F24),ABS('15_CONCILIACAO'!F25)) -> 9.3132257e-10 | BO3: ='12_MODELO'!AV3+'12_MODELO'!U3+'12_MODELO'!V3 -> 4719458.6 | BP3: ='12_MODELO'!AC3-'12_MODELO'!AD3 -> 1205820 | BQ3: =MIN('12_MODELO'!AG3,'12_MODELO'!AF3*12) -> 216000 | BR3: ='12_MODELO'!AG3-'12_MODELO'!BQ3 -> 548000 | BS3: ='12_MODELO'!AX3-'12_MODELO'!BR3 -> 1075224.8 | BT3: ='12_MODELO'!BR3 -> 548000 | BU3: =IFERROR('12_MODELO'!BO3/'12_MODELO'!BS3,0) -> 4.3892761
A4: 45352 | B4: Realizado | C4: =SUMIFS('09_VENDAS'!I$2:I$433,'09_VENDAS'!A$2:A$433,'12_MODELO'!A4) -> 1139151.5 | D4: ='12_MODELO'!C4*'12_MODELO'!BE4 -> 96827.881 | E4: ='12_MODELO'!C4-'12_MODELO'!D4 -> 1042323.7 | F4: =SUMIFS('09_VENDAS'!J$2:J$433,'09_VENDAS'!A$2:A$433,'12_MODELO'!A4) -> 752830 | G4: ='12_MODELO'!E4-'12_MODELO'!F4 -> 289493.66 | H4: =SUMIFS('10_DESPESAS'!D$2:D$123,'10_DESPESAS'!A$2:A$123,'12_MODELO'!A4,'10_DESPESAS'!B$2:B$123,"Pessoal") -> 95000 | I4: =SUMIFS('10_DESPESAS'!D$2:D$123,'10_DESPESAS'!A$2:A$123,'12_MODELO'!A4,'10_DESPESAS'!B$2:B$123,"Comercial") -> 41009.46 | J4: =SUMIFS('10_DESPESAS'!D$2:D$123,'10_DESPESAS'!A$2:A$123,'12_MODELO'!A4,'10_DESPESAS'!B$2:B$123,"Administrativo") -> 32000 | K4: =SUMIFS('10_DESPESAS'!D$2:D$123,'10_DESPESAS'!A$2:A$123,'12_MODELO'!A4,'10_DESPESAS'!B$2:B$123,"Tecnologia") -> 18000 | L4: =SUMIFS('10_DESPESAS'!D$2:D$123,'10_DESPESAS'!A$2:A$123,'12_MODELO'!A4,'10_DESPESAS'!B$2:B$123,"Operações") -> 25061.33 | M4: =SUM('12_MODELO'!H4:'12_MODELO'!L4) -> 211070.79 | N4: ='12_MODELO'!G4-'12_MODELO'!M4 -> 78422.869 | O4: =MIN('12_MODELO'!AC3*'12_MODELO'!BH4,'12_MODELO'!AC3-'12_MODELO'!AD3+'12_MODELO'!AB4) -> 15360 | P4: ='12_MODELO'!N4-'12_MODELO'!O4 -> 63062.869 | Q4: ='12_MODELO'!AG3*'12_MODELO'!BG4 -> 9168 | R4: ='12_MODELO'!P4-'12_MODELO'!Q4 -> 53894.869 | S4: =MAX(0,'12_MODELO'!R4)*'12_MODELO'!BF4 -> 18324.255 | T4: ='12_MODELO'!R4-'12_MODELO'!S4 -> 35570.614 | U4: ='12_MODELO'!C4*'12_MODELO'!BB4/30 -> 1518868.7 | V4: ='12_MODELO'!F4*'12_MODELO'!BC4/30 -> 1154339.3 | W4: ='12_MODELO'!F4+'12_MODELO'!V4-'12_MODELO'!V3 -> 921067.33 | X4: ='12_MODELO'!F4*'12_MODELO'!BD4/30 -> 878301.67 | Y4: ='12_MODELO'!H4*20% -> 19000 | Z4: ='12_MODELO'!D4 -> 96827.881 | AA4: ='12_MODELO'!S4 -> 18324.255 | AB4: ='08_PREMISSAS'!V4 -> 90000 | AC4: ='12_MODELO'!AC3+'12_MODELO'!AB4 -> 1626000 | AD4: ='12_MODELO'!AD3+'12_MODELO'!O4 -> 345540 | AE4: ='08_PREMISSAS'!W4 -> 0 | AF4: ='08_PREMISSAS'!X4 -> 18000 | AG4: ='12_MODELO'!AG3+'12_MODELO'!AE4-'12_MODELO'!AF4 -> 746000 | AH4: ='08_PREMISSAS'!Y4 -> 0 | AI4: ='12_MODELO'!AI3 -> 3900000 | AJ4: ='12_MODELO'!AJ3+'12_MODELO'!T4-'12_MODELO'!AH4 -> 437624.42 | AK4: ='12_MODELO'!U3+'12_MODELO'!C4-'12_MODELO'!U4 -> 917691.46 | AL4: ='12_MODELO'!X3+'12_MODELO'!W4-'12_MODELO'!X4 -> 793060.67 | AM4: ='12_MODELO'!M4+'12_MODELO'!Y3-'12_MODELO'!Y4 -> 211070.79 | AN4: ='12_MODELO'!Z3+'12_MODELO'!D4-'12_MODELO'!Z4 -> 82709.801 | AO4: ='12_MODELO'!AA3+'12_MODELO'!S4-'12_MODELO'!AA4 -> 7220.0391 | AP4: ='12_MODELO'!AK4-'12_MODELO'!AL4-'12_MODELO'!AM4-'12_MODELO'!AN4-'12_MODELO'!Q4-'12_MODELO'!AO4 -> -185537.84 | AQ4: ='12_MODELO'!T4+'12_MODELO'!O4-('12_MODELO'!U4-'12_MODELO'!U3)-('12_MODELO'!V4-'12_MODELO'!V3)+('12_MODELO'!X4-'12_MODELO'!X3)+('12_MODELO'!Y4-'12_MODELO'!Y3)+('12_MODELO'!Z4-'12_MODELO'!Z3)+('12_MODELO'!AA4-'12_MODELO'!AA3) -> -185537.84 | AR4: =-'12_MODELO'!AB4 -> -90000 | AS4: ='12_MODELO'!AE4-'12_MODELO'!AF4-'12_MODELO'!AH4 -> -18000 | AT4: ='12_MODELO'!AQ4+'12_MODELO'!AR4+'12_MODELO'!AS4 -> -293537.84 | AU4: ='12_MODELO'!AV3 -> 2435948 | AV4: ='12_MODELO'!AU4+'12_MODELO'!AT4 -> 2142410.2 | AW4: ='12_MODELO'!AV4+'12_MODELO'!U4+'12_MODELO'!V4+'12_MODELO'!AC4-'12_MODELO'!AD4 -> 6096078.2 | AX4: ='12_MODELO'!X4+'12_MODELO'!Y4+'12_MODELO'!Z4+'12_MODELO'!AA4+'12_MODELO'!AG4 -> 1758453.8 | AY4: ='12_MODELO'!AI4+'12_MODELO'!AJ4 -> 4337624.4 | AZ4: ='12_MODELO'!AW4-'12_MODELO'!AX4-'12_MODELO'!AY4 -> 0 | BA4: ='12_MODELO'!AP4-'12_MODELO'!AQ4 -> -2.910383e-11 | BB4: ='08_PREMISSAS'!O4 -> 40 | BC4: ='08_PREMISSAS'!P4 -> 46 | BD4: ='08_PREMISSAS'!Q4 -> 35 | BE4: ='08_PREMISSAS'!R4 -> 0.085 | BF4: ='08_PREMISSAS'!S4 -> 0.34 | BG4: ='08_PREMISSAS'!T4 -> 0.012 | BH4: ='08_PREMISSAS'!U4 -> 0.01 | BI4: =IFERROR('12_MODELO'!N4/'12_MODELO'!E4,0) -> 0.0752385 | BJ4: =IFERROR('12_MODELO'!T4/'12_MODELO'!E4,0) -> 0.034126265 | BK4: ='12_MODELO'!AQ4+'12_MODELO'!AR4 -> -275537.84 | BL4: ='12_MODELO'!U4+'12_MODELO'!V4-'12_MODELO'!X4-'12_MODELO'!Y4-'12_MODELO'!Z4-'12_MODELO'!AA4 -> 1660754.3 | BM4: ='12_MODELO'!AG4-'12_MODELO'!AV4 -> -1396410.2 | BN4: =MAX(ABS('15_CONCILIACAO'!F26),ABS('15_CONCILIACAO'!F27),ABS('15_CONCILIACAO'!F28),ABS('15_CONCILIACAO'!F29),ABS('15_CONCILIACAO'!F30),ABS('15_CONCILIACAO'!F31),ABS('15_CONCILIACAO'!F32),ABS('15_CONCILIACAO'!F33),ABS('15_CONCILIACAO'!F34),ABS('15_CONCILIACAO'!F35),ABS('15_CONCILIACAO'!F36),ABS('15_CONCILIACAO'!F37)) -> 1.3969839e-09 | BO4: ='12_MODELO'!AV4+'12_MODELO'!U4+'12_MODELO'!V4 -> 4815618.2 | BP4: ='12_MODELO'!AC4-'12_MODELO'!AD4 -> 1280460 | BQ4: =MIN('12_MODELO'!AG4,'12_MODELO'!AF4*12) -> 216000 | BR4: ='12_MODELO'!AG4-'12_MODELO'!BQ4 -> 530000 | BS4: ='12_MODELO'!AX4-'12_MODELO'!BR4 -> 1228453.8 | BT4: ='12_MODELO'!BR4 -> 530000 | BU4: =IFERROR('12_MODELO'!BO4/'12_MODELO'!BS4,0) -> 3.9200646
A5: 45383 | B5: Realizado | C5: =SUMIFS('09_VENDAS'!I$2:I$433,'09_VENDAS'!A$2:A$433,'12_MODELO'!A5) -> 1139818.9 | D5: ='12_MODELO'!C5*'12_MODELO'!BE5 -> 96884.605 | E5: ='12_MODELO'!C5-'12_MODELO'!D5 -> 1042934.3 | F5: =SUMIFS('09_VENDAS'!J$2:J$433,'09_VENDAS'!A$2:A$433,'12_MODELO'!A5) -> 753940 | G5: ='12_MODELO'!E5-'12_MODELO'!F5 -> 288994.28 | H5: =SUMIFS('10_DESPESAS'!D$2:D$123,'10_DESPESAS'!A$2:A$123,'12_MODELO'!A5,'10_DESPESAS'!B$2:B$123,"Pessoal") -> 95000 | I5: =SUMIFS('10_DESPESAS'!D$2:D$123,'10_DESPESAS'!A$2:A$123,'12_MODELO'!A5,'10_DESPESAS'!B$2:B$123,"Comercial") -> 41033.48 | J5: =SUMIFS('10_DESPESAS'!D$2:D$123,'10_DESPESAS'!A$2:A$123,'12_MODELO'!A5,'10_DESPESAS'!B$2:B$123,"Administrativo") -> 32000 | K5: =SUMIFS('10_DESPESAS'!D$2:D$123,'10_DESPESAS'!A$2:A$123,'12_MODELO'!A5,'10_DESPESAS'!B$2:B$123,"Tecnologia") -> 18000 | L5: =SUMIFS('10_DESPESAS'!D$2:D$123,'10_DESPESAS'!A$2:A$123,'12_MODELO'!A5,'10_DESPESAS'!B$2:B$123,"Operações") -> 25076.02 | M5: =SUM('12_MODELO'!H5:'12_MODELO'!L5) -> 211109.5 | N5: ='12_MODELO'!G5-'12_MODELO'!M5 -> 77884.775 | O5: =MIN('12_MODELO'!AC4*'12_MODELO'!BH5,'12_MODELO'!AC4-'12_MODELO'!AD4+'12_MODELO'!AB5) -> 16260 | P5: ='12_MODELO'!N5-'12_MODELO'!O5 -> 61624.775 | Q5: ='12_MODELO'!AG4*'12_MODELO'!BG5 -> 8952 | R5: ='12_MODELO'!P5-'12_MODELO'!Q5 -> 52672.775 | S5: =MAX(0,'12_MODELO'!R5)*'12_MODELO'!BF5 -> 17908.744 | T5: ='12_MODELO'!R5-'12_MODELO'!S5 -> 34764.032 | U5: ='12_MODELO'!C5*'12_MODELO'!BB5/30 -> 1519758.5 | V5: ='12_MODELO'!F5*'12_MODELO'!BC5/30 -> 1156041.3 | W5: ='12_MODELO'!F5+'12_MODELO'!V5-'12_MODELO'!V4 -> 755642 | X5: ='12_MODELO'!F5*'12_MODELO'!BD5/30 -> 879596.67 | Y5: ='12_MODELO'!H5*20% -> 19000 | Z5: ='12_MODELO'!D5 -> 96884.605 | AA5: ='12_MODELO'!S5 -> 17908.744 | AB5: ='08_PREMISSAS'!V5 -> 18000 | AC5: ='12_MODELO'!AC4+'12_MODELO'!AB5 -> 1644000 | AD5: ='12_MODELO'!AD4+'12_MODELO'!O5 -> 361800 | AE5: ='08_PREMISSAS'!W5 -> 0 | AF5: ='08_PREMISSAS'!X5 -> 18000 | AG5: ='12_MODELO'!AG4+'12_MODELO'!AE5-'12_MODELO'!AF5 -> 728000 | AH5: ='08_PREMISSAS'!Y5 -> 0 | AI5: ='12_MODELO'!AI4 -> 3900000 | AJ5: ='12_MODELO'!AJ4+'12_MODELO'!T5-'12_MODELO'!AH5 -> 472388.45 | AK5: ='12_MODELO'!U4+'12_MODELO'!C5-'12_MODELO'!U5 -> 1138929.1 | AL5: ='12_MODELO'!X4+'12_MODELO'!W5-'12_MODELO'!X5 -> 754347 | AM5: ='12_MODELO'!M5+'12_MODELO'!Y4-'12_MODELO'!Y5 -> 211109.5 | AN5: ='12_MODELO'!Z4+'12_MODELO'!D5-'12_MODELO'!Z5 -> 96827.881 | AO5: ='12_MODELO'!AA4+'12_MODELO'!S5-'12_MODELO'!AA5 -> 18324.255 | AP5: ='12_MODELO'!AK5-'12_MODELO'!AL5-'12_MODELO'!AM5-'12_MODELO'!AN5-'12_MODELO'!Q5-'12_MODELO'!AO5 -> 49368.457 | AQ5: ='12_MODELO'!T5+'12_MODELO'!O5-('12_MODELO'!U5-'12_MODELO'!U4)-('12_MODELO'!V5-'12_MODELO'!V4)+('12_MODELO'!X5-'12_MODELO'!X4)+('12_MODELO'!Y5-'12_MODELO'!Y4)+('12_MODELO'!Z5-'12_MODELO'!Z4)+('12_MODELO'!AA5-'12_MODELO'!AA4) -> 49368.457 | AR5: =-'12_MODELO'!AB5 -> -18000 | AS5: ='12_MODELO'!AE5-'12_MODELO'!AF5-'12_MODELO'!AH5 -> -18000 | AT5: ='12_MODELO'!AQ5+'12_MODELO'!AR5+'12_MODELO'!AS5 -> 13368.457 | AU5: ='12_MODELO'!AV4 -> 2142410.2 | AV5: ='12_MODELO'!AU5+'12_MODELO'!AT5 -> 2155778.6 | AW5: ='12_MODELO'!AV5+'12_MODELO'!U5+'12_MODELO'!V5+'12_MODELO'!AC5-'12_MODELO'!AD5 -> 6113778.5 | AX5: ='12_MODELO'!X5+'12_MODELO'!Y5+'12_MODELO'!Z5+'12_MODELO'!AA5+'12_MODELO'!AG5 -> 1741390 | AY5: ='12_MODELO'!AI5+'12_MODELO'!AJ5 -> 4372388.5 | AZ5: ='12_MODELO'!AW5-'12_MODELO'!AX5-'12_MODELO'!AY5 -> 0 | BA5: ='12_MODELO'!AP5-'12_MODELO'!AQ5 -> -1.5279511e-10 | BB5: ='08_PREMISSAS'!O5 -> 40 | BC5: ='08_PREMISSAS'!P5 -> 46 | BD5: ='08_PREMISSAS'!Q5 -> 35 | BE5: ='08_PREMISSAS'!R5 -> 0.085 | BF5: ='08_PREMISSAS'!S5 -> 0.34 | BG5: ='08_PREMISSAS'!T5 -> 0.012 | BH5: ='08_PREMISSAS'!U5 -> 0.01 | BI5: =IFERROR('12_MODELO'!N5/'12_MODELO'!E5,0) -> 0.074678508 | BJ5: =IFERROR('12_MODELO'!T5/'12_MODELO'!E5,0) -> 0.033332907 | BK5: ='12_MODELO'!AQ5+'12_MODELO'!AR5 -> 31368.457 | BL5: ='12_MODELO'!U5+'12_MODELO'!V5-'12_MODELO'!X5-'12_MODELO'!Y5-'12_MODELO'!Z5-'12_MODELO'!AA5 -> 1662409.8 | BM5: ='12_MODELO'!AG5-'12_MODELO'!AV5 -> -1427778.6 | BN5: =MAX(ABS('15_CONCILIACAO'!F38),ABS('15_CONCILIACAO'!F39),ABS('15_CONCILIACAO'!F40),ABS('15_CONCILIACAO'!F41),ABS('15_CONCILIACAO'!F42),ABS('15_CONCILIACAO'!F43),ABS('15_CONCILIACAO'!F44),ABS('15_CONCILIACAO'!F45),ABS('15_CONCILIACAO'!F46),ABS('15_CONCILIACAO'!F47),ABS('15_CONCILIACAO'!F48),ABS('15_CONCILIACAO'!F49)) -> 9.3132257e-10 | BO5: ='12_MODELO'!AV5+'12_MODELO'!U5+'12_MODELO'!V5 -> 4831578.5 | BP5: ='12_MODELO'!AC5-'12_MODELO'!AD5 -> 1282200 | BQ5: =MIN('12_MODELO'!AG5,'12_MODELO'!AF5*12) -> 216000 | BR5: ='12_MODELO'!AG5-'12_MODELO'!BQ5 -> 512000 | BS5: ='12_MODELO'!AX5-'12_MODELO'!BR5 -> 1229390 | BT5: ='12_MODELO'!BR5 -> 512000 | BU5: =IFERROR('12_MODELO'!BO5/'12_MODELO'!BS5,0) -> 3.9300616
A6: 45413 | B6: Realizado | C6: =SUMIFS('09_VENDAS'!I$2:I$433,'09_VENDAS'!A$2:A$433,'12_MODELO'!A6) -> 1186040.1 | D6: ='12_MODELO'!C6*'12_MODELO'!BE6 -> 100813.41 | E6: ='12_MODELO'!C6-'12_MODELO'!D6 -> 1085226.7 | F6: =SUMIFS('09_VENDAS'!J$2:J$433,'09_VENDAS'!A$2:A$433,'12_MODELO'!A6) -> 785220 | G6: ='12_MODELO'!E6-'12_MODELO'!F6 -> 300006.67 | H6: =SUMIFS('10_DESPESAS'!D$2:D$123,'10_DESPESAS'!A$2:A$123,'12_MODELO'!A6,'10_DESPESAS'!B$2:B$123,"Pessoal") -> 95000 | I6: =SUMIFS('10_DESPESAS'!D$2:D$123,'10_DESPESAS'!A$2:A$123,'12_MODELO'!A6,'10_DESPESAS'!B$2:B$123,"Comercial") -> 42697.44 | J6: =SUMIFS('10_DESPESAS'!D$2:D$123,'10_DESPESAS'!A$2:A$123,'12_MODELO'!A6,'10_DESPESAS'!B$2:B$123,"Administrativo") -> 32000 | K6: =SUMIFS('10_DESPESAS'!D$2:D$123,'10_DESPESAS'!A$2:A$123,'12_MODELO'!A6,'10_DESPESAS'!B$2:B$123,"Tecnologia") -> 18000 | L6: =SUMIFS('10_DESPESAS'!D$2:D$123,'10_DESPESAS'!A$2:A$123,'12_MODELO'!A6,'10_DESPESAS'!B$2:B$123,"Operações") -> 26092.88 | M6: =SUM('12_MODELO'!H6:'12_MODELO'!L6) -> 213790.32 | N6: ='12_MODELO'!G6-'12_MODELO'!M6 -> 86216.353 | O6: =MIN('12_MODELO'!AC5*'12_MODELO'!BH6,'12_MODELO'!AC5-'12_MODELO'!AD5+'12_MODELO'!AB6) -> 16440 | P6: ='12_MODELO'!N6-'12_MODELO'!O6 -> 69776.353 | Q6: ='12_MODELO'!AG5*'12_MODELO'!BG6 -> 8736 | R6: ='12_MODELO'!P6-'12_MODELO'!Q6 -> 61040.353 | S6: =MAX(0,'12_MODELO'!R6)*'12_MODELO'!BF6 -> 20753.72 | T6: ='12_MODELO'!R6-'12_MODELO'!S6 -> 40286.633 | U6: ='12_MODELO'!C6*'12_MODELO'!BB6/30 -> 1581386.8 | V6: ='12_MODELO'!F6*'12_MODELO'!BC6/30 -> 1204004 | W6: ='12_MODELO'!F6+'12_MODELO'!V6-'12_MODELO'!V5 -> 833182.67 | X6: ='12_MODELO'!F6*'12_MODELO'!BD6/30 -> 916090 | Y6: ='12_MODELO'!H6*20% -> 19000 | Z6: ='12_MODELO'!D6 -> 100813.41 | AA6: ='12_MODELO'!S6 -> 20753.72 | AB6: ='08_PREMISSAS'!V6 -> 18000 | AC6: ='12_MODELO'!AC5+'12_MODELO'!AB6 -> 1662000 | AD6: ='12_MODELO'!AD5+'12_MODELO'!O6 -> 378240 | AE6: ='08_PREMISSAS'!W6 -> 0 | AF6: ='08_PREMISSAS'!X6 -> 18000 | AG6: ='12_MODELO'!AG5+'12_MODELO'!AE6-'12_MODELO'!AF6 -> 710000 | AH6: ='08_PREMISSAS'!Y6 -> 0 | AI6: ='12_MODELO'!AI5 -> 3900000 | AJ6: ='12_MODELO'!AJ5+'12_MODELO'!T6-'12_MODELO'!AH6 -> 512675.08 | AK6: ='12_MODELO'!U5+'12_MODELO'!C6-'12_MODELO'!U6 -> 1124411.8 | AL6: ='12_MODELO'!X5+'12_MODELO'!W6-'12_MODELO'!X6 -> 796689.33 | AM6: ='12_MODELO'!M6+'12_MODELO'!Y5-'12_MODELO'!Y6 -> 213790.32 | AN6: ='12_MODELO'!Z5+'12_MODELO'!D6-'12_MODELO'!Z6 -> 96884.605 | AO6: ='12_MODELO'!AA5+'12_MODELO'!S6-'12_MODELO'!AA6 -> 17908.744 | AP6: ='12_MODELO'!AK6-'12_MODELO'!AL6-'12_MODELO'!AM6-'12_MODELO'!AN6-'12_MODELO'!Q6-'12_MODELO'!AO6 -> -9597.1884 | AQ6: ='12_MODELO'!T6+'12_MODELO'!O6-('12_MODELO'!U6-'12_MODELO'!U5)-('12_MODELO'!V6-'12_MODELO'!V5)+('12_MODELO'!X6-'12_MODELO'!X5)+('12_MODELO'!Y6-'12_MODELO'!Y5)+('12_MODELO'!Z6-'12_MODELO'!Z5)+('12_MODELO'!AA6-'12_MODELO'!AA5) -> -9597.1884 | AR6: =-'12_MODELO'!AB6 -> -18000 | AS6: ='12_MODELO'!AE6-'12_MODELO'!AF6-'12_MODELO'!AH6 -> -18000 | AT6: ='12_MODELO'!AQ6+'12_MODELO'!AR6+'12_MODELO'!AS6 -> -45597.188 | AU6: ='12_MODELO'!AV5 -> 2155778.6 | AV6: ='12_MODELO'!AU6+'12_MODELO'!AT6 -> 2110181.4 | AW6: ='12_MODELO'!AV6+'12_MODELO'!U6+'12_MODELO'!V6+'12_MODELO'!AC6-'12_MODELO'!AD6 -> 6179332.2 | AX6: ='12_MODELO'!X6+'12_MODELO'!Y6+'12_MODELO'!Z6+'12_MODELO'!AA6+'12_MODELO'!AG6 -> 1766657.1 | AY6: ='12_MODELO'!AI6+'12_MODELO'!AJ6 -> 4412675.1 | AZ6: ='12_MODELO'!AW6-'12_MODELO'!AX6-'12_MODELO'!AY6 -> 0 | BA6: ='12_MODELO'!AP6-'12_MODELO'!AQ6 -> 8.7311491e-11 | BB6: ='08_PREMISSAS'!O6 -> 40 | BC6: ='08_PREMISSAS'!P6 -> 46 | BD6: ='08_PREMISSAS'!Q6 -> 35 | BE6: ='08_PREMISSAS'!R6 -> 0.085 | BF6: ='08_PREMISSAS'!S6 -> 0.34 | BG6: ='08_PREMISSAS'!T6 -> 0.012 | BH6: ='08_PREMISSAS'!U6 -> 0.01 | BI6: =IFERROR('12_MODELO'!N6/'12_MODELO'!E6,0) -> 0.079445479 | BJ6: =IFERROR('12_MODELO'!T6/'12_MODELO'!E6,0) -> 0.037122782 | BK6: ='12_MODELO'!AQ6+'12_MODELO'!AR6 -> -27597.188 | BL6: ='12_MODELO'!U6+'12_MODELO'!V6-'12_MODELO'!X6-'12_MODELO'!Y6-'12_MODELO'!Z6-'12_MODELO'!AA6 -> 1728733.6 | BM6: ='12_MODELO'!AG6-'12_MODELO'!AV6 -> -1400181.4 | BN6: =MAX(ABS('15_CONCILIACAO'!F50),ABS('15_CONCILIACAO'!F51),ABS('15_CONCILIACAO'!F52),ABS('15_CONCILIACAO'!F53),ABS('15_CONCILIACAO'!F54),ABS('15_CONCILIACAO'!F55),ABS('15_CONCILIACAO'!F56),ABS('15_CONCILIACAO'!F57),ABS('15_CONCILIACAO'!F58),ABS('15_CONCILIACAO'!F59),ABS('15_CONCILIACAO'!F60),ABS('15_CONCILIACAO'!F61)) -> 1.3969839e-09 | BO6: ='12_MODELO'!AV6+'12_MODELO'!U6+'12_MODELO'!V6 -> 4895572.2 | BP6: ='12_MODELO'!AC6-'12_MODELO'!AD6 -> 1283760 | BQ6: =MIN('12_MODELO'!AG6,'12_MODELO'!AF6*12) -> 216000 | BR6: ='12_MODELO'!AG6-'12_MODELO'!BQ6 -> 494000 | BS6: ='12_MODELO'!AX6-'12_MODELO'!BR6 -> 1272657.1 | BT6: ='12_MODELO'!BR6 -> 494000 | BU6: =IFERROR('12_MODELO'!BO6/'12_MODELO'!BS6,0) -> 3.846733
A7: 45444 | B7: Realizado | C7: =SUMIFS('09_VENDAS'!I$2:I$433,'09_VENDAS'!A$2:A$433,'12_MODELO'!A7) -> 1228190.6 | D7: ='12_MODELO'!C7*'12_MODELO'!BE7 -> 104396.2 | E7: ='12_MODELO'!C7-'12_MODELO'!D7 -> 1123794.4 | F7: =SUMIFS('09_VENDAS'!J$2:J$433,'09_VENDAS'!A$2:A$433,'12_MODELO'!A7) -> 812940 | G7: ='12_MODELO'!E7-'12_MODELO'!F7 -> 310854.4 | H7: =SUMIFS('10_DESPESAS'!D$2:D$123,'10_DESPESAS'!A$2:A$123,'12_MODELO'!A7,'10_DESPESAS'!B$2:B$123,"Pessoal") -> 95000 | I7: =SUMIFS('10_DESPESAS'!D$2:D$123,'10_DESPESAS'!A$2:A$123,'12_MODELO'!A7,'10_DESPESAS'!B$2:B$123,"Comercial") -> 44214.86 | J7: =SUMIFS('10_DESPESAS'!D$2:D$123,'10_DESPESAS'!A$2:A$123,'12_MODELO'!A7,'10_DESPESAS'!B$2:B$123,"Administrativo") -> 32000 | K7: =SUMIFS('10_DESPESAS'!D$2:D$123,'10_DESPESAS'!A$2:A$123,'12_MODELO'!A7,'10_DESPESAS'!B$2:B$123,"Tecnologia") -> 18000 | L7: =SUMIFS('10_DESPESAS'!D$2:D$123,'10_DESPESAS'!A$2:A$123,'12_MODELO'!A7,'10_DESPESAS'!B$2:B$123,"Operações") -> 27020.19 | M7: =SUM('12_MODELO'!H7:'12_MODELO'!L7) -> 216235.05 | N7: ='12_MODELO'!G7-'12_MODELO'!M7 -> 94619.349 | O7: =MIN('12_MODELO'!AC6*'12_MODELO'!BH7,'12_MODELO'!AC6-'12_MODELO'!AD6+'12_MODELO'!AB7) -> 16620 | P7: ='12_MODELO'!N7-'12_MODELO'!O7 -> 77999.349 | Q7: ='12_MODELO'!AG6*'12_MODELO'!BG7 -> 8520 | R7: ='12_MODELO'!P7-'12_MODELO'!Q7 -> 69479.349 | S7: =MAX(0,'12_MODELO'!R7)*'12_MODELO'!BF7 -> 23622.979 | T7: ='12_MODELO'!R7-'12_MODELO'!S7 -> 45856.37 | U7: ='12_MODELO'!C7*'12_MODELO'!BB7/30 -> 1637587.5 | V7: ='12_MODELO'!F7*'12_MODELO'!BC7/30 -> 1246508 | W7: ='12_MODELO'!F7+'12_MODELO'!V7-'12_MODELO'!V6 -> 855444 | X7: ='12_MODELO'!F7*'12_MODELO'!BD7/30 -> 948430 | Y7: ='12_MODELO'!H7*20% -> 19000 | Z7: ='12_MODELO'!D7 -> 104396.2 | AA7: ='12_MODELO'!S7 -> 23622.979 | AB7: ='08_PREMISSAS'!V7 -> 90000 | AC7: ='12_MODELO'!AC6+'12_MODELO'!AB7 -> 1752000 | AD7: ='12_MODELO'!AD6+'12_MODELO'!O7 -> 394860 | AE7: ='08_PREMISSAS'!W7 -> 0 | AF7: ='08_PREMISSAS'!X7 -> 18000 | AG7: ='12_MODELO'!AG6+'12_MODELO'!AE7-'12_MODELO'!AF7 -> 692000 | AH7: ='08_PREMISSAS'!Y7 -> 0 | AI7: ='12_MODELO'!AI6 -> 3900000 | AJ7: ='12_MODELO'!AJ6+'12_MODELO'!T7-'12_MODELO'!AH7 -> 558531.45 | AK7: ='12_MODELO'!U6+'12_MODELO'!C7-'12_MODELO'!U7 -> 1171989.9 | AL7: ='12_MODELO'!X6+'12_MODELO'!W7-'12_MODELO'!X7 -> 823104 | AM7: ='12_MODELO'!M7+'12_MODELO'!Y6-'12_MODELO'!Y7 -> 216235.05 | AN7: ='12_MODELO'!Z6+'12_MODELO'!D7-'12_MODELO'!Z7 -> 100813.41 | AO7: ='12_MODELO'!AA6+'12_MODELO'!S7-'12_MODELO'!AA7 -> 20753.72 | AP7: ='12_MODELO'!AK7-'12_MODELO'!AL7-'12_MODELO'!AM7-'12_MODELO'!AN7-'12_MODELO'!Q7-'12_MODELO'!AO7 -> 2563.7298 | AQ7: ='12_MODELO'!T7+'12_MODELO'!O7-('12_MODELO'!U7-'12_MODELO'!U6)-('12_MODELO'!V7-'12_MODELO'!V6)+('12_MODELO'!X7-'12_MODELO'!X6)+('12_MODELO'!Y7-'12_MODELO'!Y6)+('12_MODELO'!Z7-'12_MODELO'!Z6)+('12_MODELO'!AA7-'12_MODELO'!AA6) -> 2563.7298 | AR7: =-'12_MODELO'!AB7 -> -90000 | AS7: ='12_MODELO'!AE7-'12_MODELO'!AF7-'12_MODELO'!AH7 -> -18000 | AT7: ='12_MODELO'!AQ7+'12_MODELO'!AR7+'12_MODELO'!AS7 -> -105436.27 | AU7: ='12_MODELO'!AV6 -> 2110181.4 | AV7: ='12_MODELO'!AU7+'12_MODELO'!AT7 -> 2004745.2 | AW7: ='12_MODELO'!AV7+'12_MODELO'!U7+'12_MODELO'!V7+'12_MODELO'!AC7-'12_MODELO'!AD7 -> 6245980.6 | AX7: ='12_MODELO'!X7+'12_MODELO'!Y7+'12_MODELO'!Z7+'12_MODELO'!AA7+'12_MODELO'!AG7 -> 1787449.2 | AY7: ='12_MODELO'!AI7+'12_MODELO'!AJ7 -> 4458531.5 | AZ7: ='12_MODELO'!AW7-'12_MODELO'!AX7-'12_MODELO'!AY7 -> 0 | BA7: ='12_MODELO'!AP7-'12_MODELO'!AQ7 -> 9.094947e-11 | BB7: ='08_PREMISSAS'!O7 -> 40 | BC7: ='08_PREMISSAS'!P7 -> 46 | BD7: ='08_PREMISSAS'!Q7 -> 35 | BE7: ='08_PREMISSAS'!R7 -> 0.085 | BF7: ='08_PREMISSAS'!S7 -> 0.34 | BG7: ='08_PREMISSAS'!T7 -> 0.012 | BH7: ='08_PREMISSAS'!U7 -> 0.01 | BI7: =IFERROR('12_MODELO'!N7/'12_MODELO'!E7,0) -> 0.084196317 | BJ7: =IFERROR('12_MODELO'!T7/'12_MODELO'!E7,0) -> 0.040804947 | BK7: ='12_MODELO'!AQ7+'12_MODELO'!AR7 -> -87436.27 | BL7: ='12_MODELO'!U7+'12_MODELO'!V7-'12_MODELO'!X7-'12_MODELO'!Y7-'12_MODELO'!Z7-'12_MODELO'!AA7 -> 1788646.3 | BM7: ='12_MODELO'!AG7-'12_MODELO'!AV7 -> -1312745.2 | BN7: =MAX(ABS('15_CONCILIACAO'!F62),ABS('15_CONCILIACAO'!F63),ABS('15_CONCILIACAO'!F64),ABS('15_CONCILIACAO'!F65),ABS('15_CONCILIACAO'!F66),ABS('15_CONCILIACAO'!F67),ABS('15_CONCILIACAO'!F68),ABS('15_CONCILIACAO'!F69),ABS('15_CONCILIACAO'!F70),ABS('15_CONCILIACAO'!F71),ABS('15_CONCILIACAO'!F72),ABS('15_CONCILIACAO'!F73)) -> 1.6298145e-09 | BO7: ='12_MODELO'!AV7+'12_MODELO'!U7+'12_MODELO'!V7 -> 4888840.6 | BP7: ='12_MODELO'!AC7-'12_MODELO'!AD7 -> 1357140 | BQ7: =MIN('12_MODELO'!AG7,'12_MODELO'!AF7*12) -> 216000 | BR7: ='12_MODELO'!AG7-'12_MODELO'!BQ7 -> 476000 | BS7: ='12_MODELO'!AX7-'12_MODELO'!BR7 -> 1311449.2 | BT7: ='12_MODELO'!BR7 -> 476000 | BU7: =IFERROR('12_MODELO'!BO7/'12_MODELO'!BS7,0) -> 3.7278155
A8: 45474 | B8: Realizado | C8: =SUMIFS('09_VENDAS'!I$2:I$433,'09_VENDAS'!A$2:A$433,'12_MODELO'!A8) -> 1083855 | D8: ='12_MODELO'!C8*'12_MODELO'!BE8 -> 92127.672 | E8: ='12_MODELO'!C8-'12_MODELO'!D8 -> 991727.29 | F8: =SUMIFS('09_VENDAS'!J$2:J$433,'09_VENDAS'!A$2:A$433,'12_MODELO'!A8) -> 718240 | G8: ='12_MODELO'!E8-'12_MODELO'!F8 -> 273487.29 | H8: =SUMIFS('10_DESPESAS'!D$2:D$123,'10_DESPESAS'!A$2:A$123,'12_MODELO'!A8,'10_DESPESAS'!B$2:B$123,"Pessoal") -> 98800 | I8: =SUMIFS('10_DESPESAS'!D$2:D$123,'10_DESPESAS'!A$2:A$123,'12_MODELO'!A8,'10_DESPESAS'!B$2:B$123,"Comercial") -> 39018.78 | J8: =SUMIFS('10_DESPESAS'!D$2:D$123,'10_DESPESAS'!A$2:A$123,'12_MODELO'!A8,'10_DESPESAS'!B$2:B$123,"Administrativo") -> 32000 | K8: =SUMIFS('10_DESPESAS'!D$2:D$123,'10_DESPESAS'!A$2:A$123,'12_MODELO'!A8,'10_DESPESAS'!B$2:B$123,"Tecnologia") -> 18000 | L8: =SUMIFS('10_DESPESAS'!D$2:D$123,'10_DESPESAS'!A$2:A$123,'12_MODELO'!A8,'10_DESPESAS'!B$2:B$123,"Operações") -> 23844.81 | M8: =SUM('12_MODELO'!H8:'12_MODELO'!L8) -> 211663.59 | N8: ='12_MODELO'!G8-'12_MODELO'!M8 -> 61823.698 | O8: =MIN('12_MODELO'!AC7*'12_MODELO'!BH8,'12_MODELO'!AC7-'12_MODELO'!AD7+'12_MODELO'!AB8) -> 17520 | P8: ='12_MODELO'!N8-'12_MODELO'!O8 -> 44303.698 | Q8: ='12_MODELO'!AG7*'12_MODELO'!BG8 -> 8304 | R8: ='12_MODELO'!P8-'12_MODELO'!Q8 -> 35999.698 | S8: =MAX(0,'12_MODELO'!R8)*'12_MODELO'!BF8 -> 12239.897 | T8: ='12_MODELO'!R8-'12_MODELO'!S8 -> 23759.801 | U8: ='12_MODELO'!C8*'12_MODELO'!BB8/30 -> 1445139.9 | V8: ='12_MODELO'!F8*'12_MODELO'!BC8/30 -> 1101301.3 | W8: ='12_MODELO'!F8+'12_MODELO'!V8-'12_MODELO'!V7 -> 573033.33 | X8: ='12_MODELO'!F8*'12_MODELO'!BD8/30 -> 837946.67 | Y8: ='12_MODELO'!H8*20% -> 19760 | Z8: ='12_MODELO'!D8 -> 92127.672 | AA8: ='12_MODELO'!S8 -> 12239.897 | AB8: ='08_PREMISSAS'!V8 -> 18000 | AC8: ='12_MODELO'!AC7+'12_MODELO'!AB8 -> 1770000 | AD8: ='12_MODELO'!AD7+'12_MODELO'!O8 -> 412380 | AE8: ='08_PREMISSAS'!W8 -> 0 | AF8: ='08_PREMISSAS'!X8 -> 18000 | AG8: ='12_MODELO'!AG7+'12_MODELO'!AE8-'12_MODELO'!AF8 -> 674000 | AH8: ='08_PREMISSAS'!Y8 -> 0 | AI8: ='12_MODELO'!AI7 -> 3900000 | AJ8: ='12_MODELO'!AJ7+'12_MODELO'!T8-'12_MODELO'!AH8 -> 582291.26 | AK8: ='12_MODELO'!U7+'12_MODELO'!C8-'12_MODELO'!U8 -> 1276302.5 | AL8: ='12_MODELO'!X7+'12_MODELO'!W8-'12_MODELO'!X8 -> 683516.67 | AM8: ='12_MODELO'!M8+'12_MODELO'!Y7-'12_MODELO'!Y8 -> 210903.59 | AN8: ='12_MODELO'!Z7+'12_MODELO'!D8-'12_MODELO'!Z8 -> 104396.2 | AO8: ='12_MODELO'!AA7+'12_MODELO'!S8-'12_MODELO'!AA8 -> 23622.979 | AP8: ='12_MODELO'!AK8-'12_MODELO'!AL8-'12_MODELO'!AM8-'12_MODELO'!AN8-'12_MODELO'!Q8-'12_MODELO'!AO8 -> 245559.04 | AQ8: ='12_MODELO'!T8+'12_MODELO'!O8-('12_MODELO'!U8-'12_MODELO'!U7)-('12_MODELO'!V8-'12_MODELO'!V7)+('12_MODELO'!X8-'12_MODELO'!X7)+('12_MODELO'!Y8-'12_MODELO'!Y7)+('12_MODELO'!Z8-'12_MODELO'!Z7)+('12_MODELO'!AA8-'12_MODELO'!AA7) -> 245559.04 | AR8: =-'12_MODELO'!AB8 -> -18000 | AS8: ='12_MODELO'!AE8-'12_MODELO'!AF8-'12_MODELO'!AH8 -> -18000 | AT8: ='12_MODELO'!AQ8+'12_MODELO'!AR8+'12_MODELO'!AS8 -> 209559.04 | AU8: ='12_MODELO'!AV7 -> 2004745.2 | AV8: ='12_MODELO'!AU8+'12_MODELO'!AT8 -> 2214304.2 | AW8: ='12_MODELO'!AV8+'12_MODELO'!U8+'12_MODELO'!V8+'12_MODELO'!AC8-'12_MODELO'!AD8 -> 6118365.5 | AX8: ='12_MODELO'!X8+'12_MODELO'!Y8+'12_MODELO'!Z8+'12_MODELO'!AA8+'12_MODELO'!AG8 -> 1636074.2 | AY8: ='12_MODELO'!AI8+'12_MODELO'!AJ8 -> 4482291.3 | AZ8: ='12_MODELO'!AW8-'12_MODELO'!AX8-'12_MODELO'!AY8 -> -9.3132257e-10 | BA8: ='12_MODELO'!AP8-'12_MODELO'!AQ8 -> 2.910383e-10 | BB8: ='08_PREMISSAS'!O8 -> 40 | BC8: ='08_PREMISSAS'!P8 -> 46 | BD8: ='08_PREMISSAS'!Q8 -> 35 | BE8: ='08_PREMISSAS'!R8 -> 0.085 | BF8: ='08_PREMISSAS'!S8 -> 0.34 | BG8: ='08_PREMISSAS'!T8 -> 0.012 | BH8: ='08_PREMISSAS'!U8 -> 0.01 | BI8: =IFERROR('12_MODELO'!N8/'12_MODELO'!E8,0) -> 0.062339414 | BJ8: =IFERROR('12_MODELO'!T8/'12_MODELO'!E8,0) -> 0.023957999 | BK8: ='12_MODELO'!AQ8+'12_MODELO'!AR8 -> 227559.04 | BL8: ='12_MODELO'!U8+'12_MODELO'!V8-'12_MODELO'!X8-'12_MODELO'!Y8-'12_MODELO'!Z8-'12_MODELO'!AA8 -> 1584367 | BM8: ='12_MODELO'!AG8-'12_MODELO'!AV8 -> -1540304.2 | BN8: =MAX(ABS('15_CONCILIACAO'!F74),ABS('15_CONCILIACAO'!F75),ABS('15_CONCILIACAO'!F76),ABS('15_CONCILIACAO'!F77),ABS('15_CONCILIACAO'!F78),ABS('15_CONCILIACAO'!F79),ABS('15_CONCILIACAO'!F80),ABS('15_CONCILIACAO'!F81),ABS('15_CONCILIACAO'!F82),ABS('15_CONCILIACAO'!F83),ABS('15_CONCILIACAO'!F84),ABS('15_CONCILIACAO'!F85)) -> 1.8626451e-09 | BO8: ='12_MODELO'!AV8+'12_MODELO'!U8+'12_MODELO'!V8 -> 4760745.5 | BP8: ='12_MODELO'!AC8-'12_MODELO'!AD8 -> 1357620 | BQ8: =MIN('12_MODELO'!AG8,'12_MODELO'!AF8*12) -> 216000 | BR8: ='12_MODELO'!AG8-'12_MODELO'!BQ8 -> 458000 | BS8: ='12_MODELO'!AX8-'12_MODELO'!BR8 -> 1178074.2 | BT8: ='12_MODELO'!BR8 -> 458000 | BU8: =IFERROR('12_MODELO'!BO8/'12_MODELO'!BS8,0) -> 4.0411252
A9: 45505 | B9: Realizado | C9: =SUMIFS('09_VENDAS'!I$2:I$433,'09_VENDAS'!A$2:A$433,'12_MODELO'!A9) -> 1173442.3 | D9: ='12_MODELO'!C9*'12_MODELO'!BE9 -> 99742.599 | E9: ='12_MODELO'!C9-'12_MODELO'!D9 -> 1073699.7 | F9: =SUMIFS('09_VENDAS'!J$2:J$433,'09_VENDAS'!A$2:A$433,'12_MODELO'!A9) -> 776350 | G9: ='12_MODELO'!E9-'12_MODELO'!F9 -> 297349.74 | H9: =SUMIFS('10_DESPESAS'!D$2:D$123,'10_DESPESAS'!A$2:A$123,'12_MODELO'!A9,'10_DESPESAS'!B$2:B$123,"Pessoal") -> 98800 | I9: =SUMIFS('10_DESPESAS'!D$2:D$123,'10_DESPESAS'!A$2:A$123,'12_MODELO'!A9,'10_DESPESAS'!B$2:B$123,"Comercial") -> 42243.92 | J9: =SUMIFS('10_DESPESAS'!D$2:D$123,'10_DESPESAS'!A$2:A$123,'12_MODELO'!A9,'10_DESPESAS'!B$2:B$123,"Administrativo") -> 32000 | K9: =SUMIFS('10_DESPESAS'!D$2:D$123,'10_DESPESAS'!A$2:A$123,'12_MODELO'!A9,'10_DESPESAS'!B$2:B$123,"Tecnologia") -> 18000 | L9: =SUMIFS('10_DESPESAS'!D$2:D$123,'10_DESPESAS'!A$2:A$123,'12_MODELO'!A9,'10_DESPESAS'!B$2:B$123,"Operações") -> 25815.73 | M9: =SUM('12_MODELO'!H9:'12_MODELO'!L9) -> 216859.65 | N9: ='12_MODELO'!G9-'12_MODELO'!M9 -> 80490.091 | O9: =MIN('12_MODELO'!AC8*'12_MODELO'!BH9,'12_MODELO'!AC8-'12_MODELO'!AD8+'12_MODELO'!AB9) -> 17700 | P9: ='12_MODELO'!N9-'12_MODELO'!O9 -> 62790.091 | Q9: ='12_MODELO'!AG8*'12_MODELO'!BG9 -> 8088 | R9: ='12_MODELO'!P9-'12_MODELO'!Q9 -> 54702.091 | S9: =MAX(0,'12_MODELO'!R9)*'12_MODELO'!BF9 -> 18598.711 | T9: ='12_MODELO'!R9-'12_MODELO'!S9 -> 36103.38 | U9: ='12_MODELO'!C9*'12_MODELO'!BB9/30 -> 1564589.8 | V9: ='12_MODELO'!F9*'12_MODELO'!BC9/30 -> 1190403.3 | W9: ='12_MODELO'!F9+'12_MODELO'!V9-'12_MODELO'!V8 -> 865452 | X9: ='12_MODELO'!F9*'12_MODELO'!BD9/30 -> 905741.67 | Y9: ='12_MODELO'!H9*20% -> 19760 | Z9: ='12_MODELO'!D9 -> 99742.599 | AA9: ='12_MODELO'!S9 -> 18598.711 | AB9: ='08_PREMISSAS'!V9 -> 18000 | AC9: ='12_MODELO'!AC8+'12_MODELO'!AB9 -> 1788000 | AD9: ='12_MODELO'!AD8+'12_MODELO'!O9 -> 430080 | AE9: ='08_PREMISSAS'!W9 -> 0 | AF9: ='08_PREMISSAS'!X9 -> 18000 | AG9: ='12_MODELO'!AG8+'12_MODELO'!AE9-'12_MODELO'!AF9 -> 656000 | AH9: ='08_PREMISSAS'!Y9 -> 0 | AI9: ='12_MODELO'!AI8 -> 3900000 | AJ9: ='12_MODELO'!AJ8+'12_MODELO'!T9-'12_MODELO'!AH9 -> 618394.64 | AK9: ='12_MODELO'!U8+'12_MODELO'!C9-'12_MODELO'!U9 -> 1053992.5 | AL9: ='12_MODELO'!X8+'12_MODELO'!W9-'12_MODELO'!X9 -> 797657 | AM9: ='12_MODELO'!M9+'12_MODELO'!Y8-'12_MODELO'!Y9 -> 216859.65 | AN9: ='12_MODELO'!Z8+'12_MODELO'!D9-'12_MODELO'!Z9 -> 92127.672 | AO9: ='12_MODELO'!AA8+'12_MODELO'!S9-'12_MODELO'!AA9 -> 12239.897 | AP9: ='12_MODELO'!AK9-'12_MODELO'!AL9-'12_MODELO'!AM9-'12_MODELO'!AN9-'12_MODELO'!Q9-'12_MODELO'!AO9 -> -72979.719 | AQ9: ='12_MODELO'!T9+'12_MODELO'!O9-('12_MODELO'!U9-'12_MODELO'!U8)-('12_MODELO'!V9-'12_MODELO'!V8)+('12_MODELO'!X9-'12_MODELO'!X8)+('12_MODELO'!Y9-'12_MODELO'!Y8)+('12_MODELO'!Z9-'12_MODELO'!Z8)+('12_MODELO'!AA9-'12_MODELO'!AA8) -> -72979.719 | AR9: =-'12_MODELO'!AB9 -> -18000 | AS9: ='12_MODELO'!AE9-'12_MODELO'!AF9-'12_MODELO'!AH9 -> -18000 | AT9: ='12_MODELO'!AQ9+'12_MODELO'!AR9+'12_MODELO'!AS9 -> -108979.72 | AU9: ='12_MODELO'!AV8 -> 2214304.2 | AV9: ='12_MODELO'!AU9+'12_MODELO'!AT9 -> 2105324.5 | AW9: ='12_MODELO'!AV9+'12_MODELO'!U9+'12_MODELO'!V9+'12_MODELO'!AC9-'12_MODELO'!AD9 -> 6218237.6 | AX9: ='12_MODELO'!X9+'12_MODELO'!Y9+'12_MODELO'!Z9+'12_MODELO'!AA9+'12_MODELO'!AG9 -> 1699843 | AY9: ='12_MODELO'!AI9+'12_MODELO'!AJ9 -> 4518394.6 | AZ9: ='12_MODELO'!AW9-'12_MODELO'!AX9-'12_MODELO'!AY9 -> 9.3132257e-10 | BA9: ='12_MODELO'!AP9-'12_MODELO'!AQ9 -> 2.1827873e-10 | BB9: ='08_PREMISSAS'!O9 -> 40 | BC9: ='08_PREMISSAS'!P9 -> 46 | BD9: ='08_PREMISSAS'!Q9 -> 35 | BE9: ='08_PREMISSAS'!R9 -> 0.085 | BF9: ='08_PREMISSAS'!S9 -> 0.34 | BG9: ='08_PREMISSAS'!T9 -> 0.012 | BH9: ='08_PREMISSAS'!U9 -> 0.01 | BI9: =IFERROR('12_MODELO'!N9/'12_MODELO'!E9,0) -> 0.074965177 | BJ9: =IFERROR('12_MODELO'!T9/'12_MODELO'!E9,0) -> 0.033625211 | BK9: ='12_MODELO'!AQ9+'12_MODELO'!AR9 -> -90979.719 | BL9: ='12_MODELO'!U9+'12_MODELO'!V9-'12_MODELO'!X9-'12_MODELO'!Y9-'12_MODELO'!Z9-'12_MODELO'!AA9 -> 1711150.1 | BM9: ='12_MODELO'!AG9-'12_MODELO'!AV9 -> -1449324.5 | BN9: =MAX(ABS('15_CONCILIACAO'!F86),ABS('15_CONCILIACAO'!F87),ABS('15_CONCILIACAO'!F88),ABS('15_CONCILIACAO'!F89),ABS('15_CONCILIACAO'!F90),ABS('15_CONCILIACAO'!F91),ABS('15_CONCILIACAO'!F92),ABS('15_CONCILIACAO'!F93),ABS('15_CONCILIACAO'!F94),ABS('15_CONCILIACAO'!F95),ABS('15_CONCILIACAO'!F96),ABS('15_CONCILIACAO'!F97)) -> 1.8626451e-09 | BO9: ='12_MODELO'!AV9+'12_MODELO'!U9+'12_MODELO'!V9 -> 4860317.6 | BP9: ='12_MODELO'!AC9-'12_MODELO'!AD9 -> 1357920 | BQ9: =MIN('12_MODELO'!AG9,'12_MODELO'!AF9*12) -> 216000 | BR9: ='12_MODELO'!AG9-'12_MODELO'!BQ9 -> 440000 | BS9: ='12_MODELO'!AX9-'12_MODELO'!BR9 -> 1259843 | BT9: ='12_MODELO'!BR9 -> 440000 | BU9: =IFERROR('12_MODELO'!BO9/'12_MODELO'!BS9,0) -> 3.8578757
A10: 45536 | B10: Realizado | C10: =SUMIFS('09_VENDAS'!I$2:I$433,'09_VENDAS'!A$2:A$433,'12_MODELO'!A10) -> 1218986.3 | D10: ='12_MODELO'!C10*'12_MODELO'!BE10 -> 103613.83 | E10: ='12_MODELO'!C10-'12_MODELO'!D10 -> 1115372.4 | F10: =SUMIFS('09_VENDAS'!J$2:J$433,'09_VENDAS'!A$2:A$433,'12_MODELO'!A10) -> 805520 | G10: ='12_MODELO'!E10-'12_MODELO'!F10 -> 309852.43 | H10: =SUMIFS('10_DESPESAS'!D$2:D$123,'10_DESPESAS'!A$2:A$123,'12_MODELO'!A10,'10_DESPESAS'!B$2:B$123,"Pessoal") -> 98800 | I10: =SUMIFS('10_DESPESAS'!D$2:D$123,'10_DESPESAS'!A$2:A$123,'12_MODELO'!A10,'10_DESPESAS'!B$2:B$123,"Comercial") -> 43883.51 | J10: =SUMIFS('10_DESPESAS'!D$2:D$123,'10_DESPESAS'!A$2:A$123,'12_MODELO'!A10,'10_DESPESAS'!B$2:B$123,"Administrativo") -> 32000 | K10: =SUMIFS('10_DESPESAS'!D$2:D$123,'10_DESPESAS'!A$2:A$123,'12_MODELO'!A10,'10_DESPESAS'!B$2:B$123,"Tecnologia") -> 18000 | L10: =SUMIFS('10_DESPESAS'!D$2:D$123,'10_DESPESAS'!A$2:A$123,'12_MODELO'!A10,'10_DESPESAS'!B$2:B$123,"Operações") -> 26817.7 | M10: =SUM('12_MODELO'!H10:'12_MODELO'!L10) -> 219501.21 | N10: ='12_MODELO'!G10-'12_MODELO'!M10 -> 90351.218 | O10: =MIN('12_MODELO'!AC9*'12_MODELO'!BH10,'12_MODELO'!AC9-'12_MODELO'!AD9+'12_MODELO'!AB10) -> 17880 | P10: ='12_MODELO'!N10-'12_MODELO'!O10 -> 72471.218 | Q10: ='12_MODELO'!AG9*'12_MODELO'!BG10 -> 7872 | R10: ='12_MODELO'!P10-'12_MODELO'!Q10 -> 64599.218 | S10: =MAX(0,'12_MODELO'!R10)*'12_MODELO'!BF10 -> 21963.734 | T10: ='12_MODELO'!R10-'12_MODELO'!S10 -> 42635.484 | U10: ='12_MODELO'!C10*'12_MODELO'!BB10/30 -> 1625315 | V10: ='12_MODELO'!F10*'12_MODELO'!BC10/30 -> 1235130.7 | W10: ='12_MODELO'!F10+'12_MODELO'!V10-'12_MODELO'!V9 -> 850247.33 | X10: ='12_MODELO'!F10*'12_MODELO'!BD10/30 -> 939773.33 | Y10: ='12_MODELO'!H10*20% -> 19760 | Z10: ='12_MODELO'!D10 -> 103613.83 | AA10: ='12_MODELO'!S10 -> 21963.734 | AB10: ='08_PREMISSAS'!V10 -> 90000 | AC10: ='12_MODELO'!AC9+'12_MODELO'!AB10 -> 1878000 | AD10: ='12_MODELO'!AD9+'12_MODELO'!O10 -> 447960 | AE10: ='08_PREMISSAS'!W10 -> 0 | AF10: ='08_PREMISSAS'!X10 -> 18000 | AG10: ='12_MODELO'!AG9+'12_MODELO'!AE10-'12_MODELO'!AF10 -> 638000 | AH10: ='08_PREMISSAS'!Y10 -> 0 | AI10: ='12_MODELO'!AI9 -> 3900000 | AJ10: ='12_MODELO'!AJ9+'12_MODELO'!T10-'12_MODELO'!AH10 -> 661030.12 | AK10: ='12_MODELO'!U9+'12_MODELO'!C10-'12_MODELO'!U10 -> 1158261 | AL10: ='12_MODELO'!X9+'12_MODELO'!W10-'12_MODELO'!X10 -> 816215.67 | AM10: ='12_MODELO'!M10+'12_MODELO'!Y9-'12_MODELO'!Y10 -> 219501.21 | AN10: ='12_MODELO'!Z9+'12_MODELO'!D10-'12_MODELO'!Z10 -> 99742.599 | AO10: ='12_MODELO'!AA9+'12_MODELO'!S10-'12_MODELO'!AA10 -> 18598.711 | AP10: ='12_MODELO'!AK10-'12_MODELO'!AL10-'12_MODELO'!AM10-'12_MODELO'!AN10-'12_MODELO'!Q10-'12_MODELO'!AO10 -> -3669.1532 | AQ10: ='12_MODELO'!T10+'12_MODELO'!O10-('12_MODELO'!U10-'12_MODELO'!U9)-('12_MODELO'!V10-'12_MODELO'!V9)+('12_MODELO'!X10-'12_MODELO'!X9)+('12_MODELO'!Y10-'12_MODELO'!Y9)+('12_MODELO'!Z10-'12_MODELO'!Z9)+('12_MODELO'!AA10-'12_MODELO'!AA9) -> -3669.1532 | AR10: =-'12_MODELO'!AB10 -> -90000 | AS10: ='12_MODELO'!AE10-'12_MODELO'!AF10-'12_MODELO'!AH10 -> -18000 | AT10: ='12_MODELO'!AQ10+'12_MODELO'!AR10+'12_MODELO'!AS10 -> -111669.15 | AU10: ='12_MODELO'!AV9 -> 2105324.5 | AV10: ='12_MODELO'!AU10+'12_MODELO'!AT10 -> 1993655.3 | AW10: ='12_MODELO'!AV10+'12_MODELO'!U10+'12_MODELO'!V10+'12_MODELO'!AC10-'12_MODELO'!AD10 -> 6284141 | AX10: ='12_MODELO'!X10+'12_MODELO'!Y10+'12_MODELO'!Z10+'12_MODELO'!AA10+'12_MODELO'!AG10 -> 1723110.9 | AY10: ='12_MODELO'!AI10+'12_MODELO'!AJ10 -> 4561030.1 | AZ10: ='12_MODELO'!AW10-'12_MODELO'!AX10-'12_MODELO'!AY10 -> 0 | BA10: ='12_MODELO'!AP10-'12_MODELO'!AQ10 -> 3.2378011e-10 | BB10: ='08_PREMISSAS'!O10 -> 40 | BC10: ='08_PREMISSAS'!P10 -> 46 | BD10: ='08_PREMISSAS'!Q10 -> 35 | BE10: ='08_PREMISSAS'!R10 -> 0.085 | BF10: ='08_PREMISSAS'!S10 -> 0.34 | BG10: ='08_PREMISSAS'!T10 -> 0.012 | BH10: ='08_PREMISSAS'!U10 -> 0.01 | BI10: =IFERROR('12_MODELO'!N10/'12_MODELO'!E10,0) -> 0.081005425 | BJ10: =IFERROR('12_MODELO'!T10/'12_MODELO'!E10,0) -> 0.038225334 | BK10: ='12_MODELO'!AQ10+'12_MODELO'!AR10 -> -93669.153 | BL10: ='12_MODELO'!U10+'12_MODELO'!V10-'12_MODELO'!X10-'12_MODELO'!Y10-'12_MODELO'!Z10-'12_MODELO'!AA10 -> 1775334.8 | BM10: ='12_MODELO'!AG10-'12_MODELO'!AV10 -> -1355655.3 | BN10: =MAX(ABS('15_CONCILIACAO'!F98),ABS('15_CONCILIACAO'!F99),ABS('15_CONCILIACAO'!F100),ABS('15_CONCILIACAO'!F101),ABS('15_CONCILIACAO'!F102),ABS('15_CONCILIACAO'!F103),ABS('15_CONCILIACAO'!F104),ABS('15_CONCILIACAO'!F105),ABS('15_CONCILIACAO'!F106),ABS('15_CONCILIACAO'!F107),ABS('15_CONCILIACAO'!F108),ABS('15_CONCILIACAO'!F109)) -> 2.3283064e-09 | BO10: ='12_MODELO'!AV10+'12_MODELO'!U10+'12_MODELO'!V10 -> 4854101 | BP10: ='12_MODELO'!AC10-'12_MODELO'!AD10 -> 1430040 | BQ10: =MIN('12_MODELO'!AG10,'12_MODELO'!AF10*12) -> 216000 | BR10: ='12_MODELO'!AG10-'12_MODELO'!BQ10 -> 422000 | BS10: ='12_MODELO'!AX10-'12_MODELO'!BR10 -> 1301110.9 | BT10: ='12_MODELO'!BR10 -> 422000 | BU10: =IFERROR('12_MODELO'!BO10/'12_MODELO'!BS10,0) -> 3.7307358
A11: 45566 | B11: Realizado | C11: =SUMIFS('09_VENDAS'!I$2:I$433,'09_VENDAS'!A$2:A$433,'12_MODELO'!A11) -> 1336476.7 | D11: ='12_MODELO'!C11*'12_MODELO'!BE11 -> 113600.52 | E11: ='12_MODELO'!C11-'12_MODELO'!D11 -> 1222876.1 | F11: =SUMIFS('09_VENDAS'!J$2:J$433,'09_VENDAS'!A$2:A$433,'12_MODELO'!A11) -> 885430 | G11: ='12_MODELO'!E11-'12_MODELO'!F11 -> 337446.14 | H11: =SUMIFS('10_DESPESAS'!D$2:D$123,'10_DESPESAS'!A$2:A$123,'12_MODELO'!A11,'10_DESPESAS'!B$2:B$123,"Pessoal") -> 98800 | I11: =SUMIFS('10_DESPESAS'!D$2:D$123,'10_DESPESAS'!A$2:A$123,'12_MODELO'!A11,'10_DESPESAS'!B$2:B$123,"Comercial") -> 48113.16 | J11: =SUMIFS('10_DESPESAS'!D$2:D$123,'10_DESPESAS'!A$2:A$123,'12_MODELO'!A11,'10_DESPESAS'!B$2:B$123,"Administrativo") -> 32000 | K11: =SUMIFS('10_DESPESAS'!D$2:D$123,'10_DESPESAS'!A$2:A$123,'12_MODELO'!A11,'10_DESPESAS'!B$2:B$123,"Tecnologia") -> 18000 | L11: =SUMIFS('10_DESPESAS'!D$2:D$123,'10_DESPESAS'!A$2:A$123,'12_MODELO'!A11,'10_DESPESAS'!B$2:B$123,"Operações") -> 29402.49 | M11: =SUM('12_MODELO'!H11:'12_MODELO'!L11) -> 226315.65 | N11: ='12_MODELO'!G11-'12_MODELO'!M11 -> 111130.49 | O11: =MIN('12_MODELO'!AC10*'12_MODELO'!BH11,'12_MODELO'!AC10-'12_MODELO'!AD10+'12_MODELO'!AB11) -> 18780 | P11: ='12_MODELO'!N11-'12_MODELO'!O11 -> 92350.494 | Q11: ='12_MODELO'!AG10*'12_MODELO'!BG11 -> 7656 | R11: ='12_MODELO'!P11-'12_MODELO'!Q11 -> 84694.494 | S11: =MAX(0,'12_MODELO'!R11)*'12_MODELO'!BF11 -> 28796.128 | T11: ='12_MODELO'!R11-'12_MODELO'!S11 -> 55898.366 | U11: ='12_MODELO'!C11*'12_MODELO'!BB11/30 -> 1781968.9 | V11: ='12_MODELO'!F11*'12_MODELO'!BC11/30 -> 1357659.3 | W11: ='12_MODELO'!F11+'12_MODELO'!V11-'12_MODELO'!V10 -> 1007958.7 | X11: ='12_MODELO'!F11*'12_MODELO'!BD11/30 -> 1033001.7 | Y11: ='12_MODELO'!H11*20% -> 19760 | Z11: ='12_MODELO'!D11 -> 113600.52 | AA11: ='12_MODELO'!S11 -> 28796.128 | AB11: ='08_PREMISSAS'!V11 -> 18000 | AC11: ='12_MODELO'!AC10+'12_MODELO'!AB11 -> 1896000 | AD11: ='12_MODELO'!AD10+'12_MODELO'!O11 -> 466740 | AE11: ='08_PREMISSAS'!W11 -> 0 | AF11: ='08_PREMISSAS'!X11 -> 18000 | AG11: ='12_MODELO'!AG10+'12_MODELO'!AE11-'12_MODELO'!AF11 -> 620000 | AH11: ='08_PREMISSAS'!Y11 -> 0 | AI11: ='12_MODELO'!AI10 -> 3900000 | AJ11: ='12_MODELO'!AJ10+'12_MODELO'!T11-'12_MODELO'!AH11 -> 716928.49 | AK11: ='12_MODELO'!U10+'12_MODELO'!C11-'12_MODELO'!U11 -> 1179822.8 | AL11: ='12_MODELO'!X10+'12_MODELO'!W11-'12_MODELO'!X11 -> 914730.33 | AM11: ='12_MODELO'!M11+'12_MODELO'!Y10-'12_MODELO'!Y11 -> 226315.65 | AN11: ='12_MODELO'!Z10+'12_MODELO'!D11-'12_MODELO'!Z11 -> 103613.83 | AO11: ='12_MODELO'!AA10+'12_MODELO'!S11-'12_MODELO'!AA11 -> 21963.734 | AP11: ='12_MODELO'!AK11-'12_MODELO'!AL11-'12_MODELO'!AM11-'12_MODELO'!AN11-'12_MODELO'!Q11-'12_MODELO'!AO11 -> -94456.756 | AQ11: ='12_MODELO'!T11+'12_MODELO'!O11-('12_MODELO'!U11-'12_MODELO'!U10)-('12_MODELO'!V11-'12_MODELO'!V10)+('12_MODELO'!X11-'12_MODELO'!X10)+('12_MODELO'!Y11-'12_MODELO'!Y10)+('12_MODELO'!Z11-'12_MODELO'!Z10)+('12_MODELO'!AA11-'12_MODELO'!AA10) -> -94456.756 | AR11: =-'12_MODELO'!AB11 -> -18000 | AS11: ='12_MODELO'!AE11-'12_MODELO'!AF11-'12_MODELO'!AH11 -> -18000 | AT11: ='12_MODELO'!AQ11+'12_MODELO'!AR11+'12_MODELO'!AS11 -> -130456.76 | AU11: ='12_MODELO'!AV10 -> 1993655.3 | AV11: ='12_MODELO'!AU11+'12_MODELO'!AT11 -> 1863198.6 | AW11: ='12_MODELO'!AV11+'12_MODELO'!U11+'12_MODELO'!V11+'12_MODELO'!AC11-'12_MODELO'!AD11 -> 6432086.8 | AX11: ='12_MODELO'!X11+'12_MODELO'!Y11+'12_MODELO'!Z11+'12_MODELO'!AA11+'12_MODELO'!AG11 -> 1815158.3 | AY11: ='12_MODELO'!AI11+'12_MODELO'!AJ11 -> 4616928.5 | AZ11: ='12_MODELO'!AW11-'12_MODELO'!AX11-'12_MODELO'!AY11 -> 0 | BA11: ='12_MODELO'!AP11-'12_MODELO'!AQ11 -> 1.4551915e-11 | BB11: ='08_PREMISSAS'!O11 -> 40 | BC11: ='08_PREMISSAS'!P11 -> 46 | BD11: ='08_PREMISSAS'!Q11 -> 35 | BE11: ='08_PREMISSAS'!R11 -> 0.085 | BF11: ='08_PREMISSAS'!S11 -> 0.34 | BG11: ='08_PREMISSAS'!T11 -> 0.012 | BH11: ='08_PREMISSAS'!U11 -> 0.01 | BI11: =IFERROR('12_MODELO'!N11/'12_MODELO'!E11,0) -> 0.090876328 | BJ11: =IFERROR('12_MODELO'!T11/'12_MODELO'!E11,0) -> 0.04571057 | BK11: ='12_MODELO'!AQ11+'12_MODELO'!AR11 -> -112456.76 | BL11: ='12_MODELO'!U11+'12_MODELO'!V11-'12_MODELO'!X11-'12_MODELO'!Y11-'12_MODELO'!Z11-'12_MODELO'!AA11 -> 1944469.9 | BM11: ='12_MODELO'!AG11-'12_MODELO'!AV11 -> -1243198.6 | BN11: =MAX(ABS('15_CONCILIACAO'!F110),ABS('15_CONCILIACAO'!F111),ABS('15_CONCILIACAO'!F112),ABS('15_CONCILIACAO'!F113),ABS('15_CONCILIACAO'!F114),ABS('15_CONCILIACAO'!F115),ABS('15_CONCILIACAO'!F116),ABS('15_CONCILIACAO'!F117),ABS('15_CONCILIACAO'!F118),ABS('15_CONCILIACAO'!F119),ABS('15_CONCILIACAO'!F120),ABS('15_CONCILIACAO'!F121)) -> 2.3283064e-09 | BO11: ='12_MODELO'!AV11+'12_MODELO'!U11+'12_MODELO'!V11 -> 5002826.8 | BP11: ='12_MODELO'!AC11-'12_MODELO'!AD11 -> 1429260 | BQ11: =MIN('12_MODELO'!AG11,'12_MODELO'!AF11*12) -> 216000 | BR11: ='12_MODELO'!AG11-'12_MODELO'!BQ11 -> 404000 | BS11: ='12_MODELO'!AX11-'12_MODELO'!BR11 -> 1411158.3 | BT11: ='12_MODELO'!BR11 -> 404000 | BU11: =IFERROR('12_MODELO'!BO11/'12_MODELO'!BS11,0) -> 3.5451917
A12: 45597 | B12: Realizado | C12: =SUMIFS('09_VENDAS'!I$2:I$433,'09_VENDAS'!A$2:A$433,'12_MODELO'!A12) -> 1504412.3 | D12: ='12_MODELO'!C12*'12_MODELO'!BE12 -> 127875.05 | E12: ='12_MODELO'!C12-'12_MODELO'!D12 -> 1376537.3 | F12: =SUMIFS('09_VENDAS'!J$2:J$433,'09_VENDAS'!A$2:A$433,'12_MODELO'!A12) -> 996280 | G12: ='12_MODELO'!E12-'12_MODELO'!F12 -> 380257.27 | H12: =SUMIFS('10_DESPESAS'!D$2:D$123,'10_DESPESAS'!A$2:A$123,'12_MODELO'!A12,'10_DESPESAS'!B$2:B$123,"Pessoal") -> 98800 | I12: =SUMIFS('10_DESPESAS'!D$2:D$123,'10_DESPESAS'!A$2:A$123,'12_MODELO'!A12,'10_DESPESAS'!B$2:B$123,"Comercial") -> 54158.84 | J12: =SUMIFS('10_DESPESAS'!D$2:D$123,'10_DESPESAS'!A$2:A$123,'12_MODELO'!A12,'10_DESPESAS'!B$2:B$123,"Administrativo") -> 32000 | K12: =SUMIFS('10_DESPESAS'!D$2:D$123,'10_DESPESAS'!A$2:A$123,'12_MODELO'!A12,'10_DESPESAS'!B$2:B$123,"Tecnologia") -> 18000 | L12: =SUMIFS('10_DESPESAS'!D$2:D$123,'10_DESPESAS'!A$2:A$123,'12_MODELO'!A12,'10_DESPESAS'!B$2:B$123,"Operações") -> 33097.07 | M12: =SUM('12_MODELO'!H12:'12_MODELO'!L12) -> 236055.91 | N12: ='12_MODELO'!G12-'12_MODELO'!M12 -> 144201.36 | O12: =MIN('12_MODELO'!AC11*'12_MODELO'!BH12,'12_MODELO'!AC11-'12_MODELO'!AD11+'12_MODELO'!AB12) -> 18960 | P12: ='12_MODELO'!N12-'12_MODELO'!O12 -> 125241.36 | Q12: ='12_MODELO'!AG11*'12_MODELO'!BG12 -> 7440 | R12: ='12_MODELO'!P12-'12_MODELO'!Q12 -> 117801.36 | S12: =MAX(0,'12_MODELO'!R12)*'12_MODELO'!BF12 -> 40052.463 | T12: ='12_MODELO'!R12-'12_MODELO'!S12 -> 77748.899 | U12: ='12_MODELO'!C12*'12_MODELO'!BB12/30 -> 2005883.1 | V12: ='12_MODELO'!F12*'12_MODELO'!BC12/30 -> 1527629.3 | W12: ='12_MODELO'!F12+'12_MODELO'!V12-'12_MODELO'!V11 -> 1166250 | X12: ='12_MODELO'!F12*'12_MODELO'!BD12/30 -> 1162326.7 | Y12: ='12_MODELO'!H12*20% -> 19760 | Z12: ='12_MODELO'!D12 -> 127875.05 | AA12: ='12_MODELO'!S12 -> 40052.463 | AB12: ='08_PREMISSAS'!V12 -> 18000 | AC12: ='12_MODELO'!AC11+'12_MODELO'!AB12 -> 1914000 | AD12: ='12_MODELO'!AD11+'12_MODELO'!O12 -> 485700 | AE12: ='08_PREMISSAS'!W12 -> 0 | AF12: ='08_PREMISSAS'!X12 -> 18000 | AG12: ='12_MODELO'!AG11+'12_MODELO'!AE12-'12_MODELO'!AF12 -> 602000 | AH12: ='08_PREMISSAS'!Y12 -> 0 | AI12: ='12_MODELO'!AI11 -> 3900000 | AJ12: ='12_MODELO'!AJ11+'12_MODELO'!T12-'12_MODELO'!AH12 -> 794677.38 | AK12: ='12_MODELO'!U11+'12_MODELO'!C12-'12_MODELO'!U12 -> 1280498.1 | AL12: ='12_MODELO'!X11+'12_MODELO'!W12-'12_MODELO'!X12 -> 1036925 | AM12: ='12_MODELO'!M12+'12_MODELO'!Y11-'12_MODELO'!Y12 -> 236055.91 | AN12: ='12_MODELO'!Z11+'12_MODELO'!D12-'12_MODELO'!Z12 -> 113600.52 | AO12: ='12_MODELO'!AA11+'12_MODELO'!S12-'12_MODELO'!AA12 -> 28796.128 | AP12: ='12_MODELO'!AK12-'12_MODELO'!AL12-'12_MODELO'!AM12-'12_MODELO'!AN12-'12_MODELO'!Q12-'12_MODELO'!AO12 -> -142319.45 | AQ12: ='12_MODELO'!T12+'12_MODELO'!O12-('12_MODELO'!U12-'12_MODELO'!U11)-('12_MODELO'!V12-'12_MODELO'!V11)+('12_MODELO'!X12-'12_MODELO'!X11)+('12_MODELO'!Y12-'12_MODELO'!Y11)+('12_MODELO'!Z12-'12_MODELO'!Z11)+('12_MODELO'!AA12-'12_MODELO'!AA11) -> -142319.45 | AR12: =-'12_MODELO'!AB12 -> -18000 | AS12: ='12_MODELO'!AE12-'12_MODELO'!AF12-'12_MODELO'!AH12 -> -18000 | AT12: ='12_MODELO'!AQ12+'12_MODELO'!AR12+'12_MODELO'!AS12 -> -178319.45 | AU12: ='12_MODELO'!AV11 -> 1863198.6 | AV12: ='12_MODELO'!AU12+'12_MODELO'!AT12 -> 1684879.1 | AW12: ='12_MODELO'!AV12+'12_MODELO'!U12+'12_MODELO'!V12+'12_MODELO'!AC12-'12_MODELO'!AD12 -> 6646691.6 | AX12: ='12_MODELO'!X12+'12_MODELO'!Y12+'12_MODELO'!Z12+'12_MODELO'!AA12+'12_MODELO'!AG12 -> 1952014.2 | AY12: ='12_MODELO'!AI12+'12_MODELO'!AJ12 -> 4694677.4 | AZ12: ='12_MODELO'!AW12-'12_MODELO'!AX12-'12_MODELO'!AY12 -> -9.3132257e-10 | BA12: ='12_MODELO'!AP12-'12_MODELO'!AQ12 -> 2.0372681e-10 | BB12: ='08_PREMISSAS'!O12 -> 40 | BC12: ='08_PREMISSAS'!P12 -> 46 | BD12: ='08_PREMISSAS'!Q12 -> 35 | BE12: ='08_PREMISSAS'!R12 -> 0.085 | BF12: ='08_PREMISSAS'!S12 -> 0.34 | BG12: ='08_PREMISSAS'!T12 -> 0.012 | BH12: ='08_PREMISSAS'!U12 -> 0.01 | BI12: =IFERROR('12_MODELO'!N12/'12_MODELO'!E12,0) -> 0.1047566 | BJ12: =IFERROR('12_MODELO'!T12/'12_MODELO'!E12,0) -> 0.056481507 | BK12: ='12_MODELO'!AQ12+'12_MODELO'!AR12 -> -160319.45 | BL12: ='12_MODELO'!U12+'12_MODELO'!V12-'12_MODELO'!X12-'12_MODELO'!Y12-'12_MODELO'!Z12-'12_MODELO'!AA12 -> 2183498.2 | BM12: ='12_MODELO'!AG12-'12_MODELO'!AV12 -> -1082879.1 | BN12: =MAX(ABS('15_CONCILIACAO'!F122),ABS('15_CONCILIACAO'!F123),ABS('15_CONCILIACAO'!F124),ABS('15_CONCILIACAO'!F125),ABS('15_CONCILIACAO'!F126),ABS('15_CONCILIACAO'!F127),ABS('15_CONCILIACAO'!F128),ABS('15_CONCILIACAO'!F129),ABS('15_CONCILIACAO'!F130),ABS('15_CONCILIACAO'!F131),ABS('15_CONCILIACAO'!F132),ABS('15_CONCILIACAO'!F133)) -> 2.3283064e-09 | BO12: ='12_MODELO'!AV12+'12_MODELO'!U12+'12_MODELO'!V12 -> 5218391.6 | BP12: ='12_MODELO'!AC12-'12_MODELO'!AD12 -> 1428300 | BQ12: =MIN('12_MODELO'!AG12,'12_MODELO'!AF12*12) -> 216000 | BR12: ='12_MODELO'!AG12-'12_MODELO'!BQ12 -> 386000 | BS12: ='12_MODELO'!AX12-'12_MODELO'!BR12 -> 1566014.2 | BT12: ='12_MODELO'!BR12 -> 386000 | BU12: =IFERROR('12_MODELO'!BO12/'12_MODELO'!BS12,0) -> 3.3322761
A13: 45627 | B13: Realizado | C13: =SUMIFS('09_VENDAS'!I$2:I$433,'09_VENDAS'!A$2:A$433,'12_MODELO'!A13) -> 1381719.6 | D13: ='12_MODELO'!C13*'12_MODELO'!BE13 -> 117446.16 | E13: ='12_MODELO'!C13-'12_MODELO'!D13 -> 1264273.4 | F13: =SUMIFS('09_VENDAS'!J$2:J$433,'09_VENDAS'!A$2:A$433,'12_MODELO'!A13) -> 915130 | G13: ='12_MODELO'!E13-'12_MODELO'!F13 -> 349143.42 | H13: =SUMIFS('10_DESPESAS'!D$2:D$123,'10_DESPESAS'!A$2:A$123,'12_MODELO'!A13,'10_DESPESAS'!B$2:B$123,"Pessoal") -> 98800 | I13: =SUMIFS('10_DESPESAS'!D$2:D$123,'10_DESPESAS'!A$2:A$123,'12_MODELO'!A13,'10_DESPESAS'!B$2:B$123,"Comercial") -> 49741.9 | J13: =SUMIFS('10_DESPESAS'!D$2:D$123,'10_DESPESAS'!A$2:A$123,'12_MODELO'!A13,'10_DESPESAS'!B$2:B$123,"Administrativo") -> 32000 | K13: =SUMIFS('10_DESPESAS'!D$2:D$123,'10_DESPESAS'!A$2:A$123,'12_MODELO'!A13,'10_DESPESAS'!B$2:B$123,"Tecnologia") -> 18000 | L13: =SUMIFS('10_DESPESAS'!D$2:D$123,'10_DESPESAS'!A$2:A$123,'12_MODELO'!A13,'10_DESPESAS'!B$2:B$123,"Operações") -> 30397.83 | M13: =SUM('12_MODELO'!H13:'12_MODELO'!L13) -> 228939.73 | N13: ='12_MODELO'!G13-'12_MODELO'!M13 -> 120203.69 | O13: =MIN('12_MODELO'!AC12*'12_MODELO'!BH13,'12_MODELO'!AC12-'12_MODELO'!AD12+'12_MODELO'!AB13) -> 19140 | P13: ='12_MODELO'!N13-'12_MODELO'!O13 -> 101063.69 | Q13: ='12_MODELO'!AG12*'12_MODELO'!BG13 -> 7224 | R13: ='12_MODELO'!P13-'12_MODELO'!Q13 -> 93839.686 | S13: =MAX(0,'12_MODELO'!R13)*'12_MODELO'!BF13 -> 31905.493 | T13: ='12_MODELO'!R13-'12_MODELO'!S13 -> 61934.193 | U13: ='12_MODELO'!C13*'12_MODELO'!BB13/30 -> 1842292.8 | V13: ='12_MODELO'!F13*'12_MODELO'!BC13/30 -> 1403199.3 | W13: ='12_MODELO'!F13+'12_MODELO'!V13-'12_MODELO'!V12 -> 790700 | X13: ='12_MODELO'!F13*'12_MODELO'!BD13/30 -> 1067651.7 | Y13: ='12_MODELO'!H13*20% -> 19760 | Z13: ='12_MODELO'!D13 -> 117446.16 | AA13: ='12_MODELO'!S13 -> 31905.493 | AB13: ='08_PREMISSAS'!V13 -> 90000 | AC13: ='12_MODELO'!AC12+'12_MODELO'!AB13 -> 2004000 | AD13: ='12_MODELO'!AD12+'12_MODELO'!O13 -> 504840 | AE13: ='08_PREMISSAS'!W13 -> 0 | AF13: ='08_PREMISSAS'!X13 -> 18000 | AG13: ='12_MODELO'!AG12+'12_MODELO'!AE13-'12_MODELO'!AF13 -> 584000 | AH13: ='08_PREMISSAS'!Y13 -> 0 | AI13: ='12_MODELO'!AI12 -> 3900000 | AJ13: ='12_MODELO'!AJ12+'12_MODELO'!T13-'12_MODELO'!AH13 -> 856611.58 | AK13: ='12_MODELO'!U12+'12_MODELO'!C13-'12_MODELO'!U13 -> 1545309.9 | AL13: ='12_MODELO'!X12+'12_MODELO'!W13-'12_MODELO'!X13 -> 885375 | AM13: ='12_MODELO'!M13+'12_MODELO'!Y12-'12_MODELO'!Y13 -> 228939.73 | AN13: ='12_MODELO'!Z12+'12_MODELO'!D13-'12_MODELO'!Z13 -> 127875.05 | AO13: ='12_MODELO'!AA12+'12_MODELO'!S13-'12_MODELO'!AA13 -> 40052.463 | AP13: ='12_MODELO'!AK13-'12_MODELO'!AL13-'12_MODELO'!AM13-'12_MODELO'!AN13-'12_MODELO'!Q13-'12_MODELO'!AO13 -> 255843.66 | AQ13: ='12_MODELO'!T13+'12_MODELO'!O13-('12_MODELO'!U13-'12_MODELO'!U12)-('12_MODELO'!V13-'12_MODELO'!V12)+('12_MODELO'!X13-'12_MODELO'!X12)+('12_MODELO'!Y13-'12_MODELO'!Y12)+('12_MODELO'!Z13-'12_MODELO'!Z12)+('12_MODELO'!AA13-'12_MODELO'!AA12) -> 255843.66 | AR13: =-'12_MODELO'!AB13 -> -90000 | AS13: ='12_MODELO'!AE13-'12_MODELO'!AF13-'12_MODELO'!AH13 -> -18000 | AT13: ='12_MODELO'!AQ13+'12_MODELO'!AR13+'12_MODELO'!AS13 -> 147843.66 | AU13: ='12_MODELO'!AV12 -> 1684879.1 | AV13: ='12_MODELO'!AU13+'12_MODELO'!AT13 -> 1832722.8 | AW13: ='12_MODELO'!AV13+'12_MODELO'!U13+'12_MODELO'!V13+'12_MODELO'!AC13-'12_MODELO'!AD13 -> 6577374.9 | AX13: ='12_MODELO'!X13+'12_MODELO'!Y13+'12_MODELO'!Z13+'12_MODELO'!AA13+'12_MODELO'!AG13 -> 1820763.3 | AY13: ='12_MODELO'!AI13+'12_MODELO'!AJ13 -> 4756611.6 | AZ13: ='12_MODELO'!AW13-'12_MODELO'!AX13-'12_MODELO'!AY13 -> 0 | BA13: ='12_MODELO'!AP13-'12_MODELO'!AQ13 -> 5.2386895e-10 | BB13: ='08_PREMISSAS'!O13 -> 40 | BC13: ='08_PREMISSAS'!P13 -> 46 | BD13: ='08_PREMISSAS'!Q13 -> 35 | BE13: ='08_PREMISSAS'!R13 -> 0.085 | BF13: ='08_PREMISSAS'!S13 -> 0.34 | BG13: ='08_PREMISSAS'!T13 -> 0.012 | BH13: ='08_PREMISSAS'!U13 -> 0.01 | BI13: =IFERROR('12_MODELO'!N13/'12_MODELO'!E13,0) -> 0.095077286 | BJ13: =IFERROR('12_MODELO'!T13/'12_MODELO'!E13,0) -> 0.048987973 | BK13: ='12_MODELO'!AQ13+'12_MODELO'!AR13 -> 165843.66 | BL13: ='12_MODELO'!U13+'12_MODELO'!V13-'12_MODELO'!X13-'12_MODELO'!Y13-'12_MODELO'!Z13-'12_MODELO'!AA13 -> 2008728.8 | BM13: ='12_MODELO'!AG13-'12_MODELO'!AV13 -> -1248722.8 | BN13: =MAX(ABS('15_CONCILIACAO'!F134),ABS('15_CONCILIACAO'!F135),ABS('15_CONCILIACAO'!F136),ABS('15_CONCILIACAO'!F137),ABS('15_CONCILIACAO'!F138),ABS('15_CONCILIACAO'!F139),ABS('15_CONCILIACAO'!F140),ABS('15_CONCILIACAO'!F141),ABS('15_CONCILIACAO'!F142),ABS('15_CONCILIACAO'!F143),ABS('15_CONCILIACAO'!F144),ABS('15_CONCILIACAO'!F145)) -> 2.5611371e-09 | BO13: ='12_MODELO'!AV13+'12_MODELO'!U13+'12_MODELO'!V13 -> 5078214.9 | BP13: ='12_MODELO'!AC13-'12_MODELO'!AD13 -> 1499160 | BQ13: =MIN('12_MODELO'!AG13,'12_MODELO'!AF13*12) -> 216000 | BR13: ='12_MODELO'!AG13-'12_MODELO'!BQ13 -> 368000 | BS13: ='12_MODELO'!AX13-'12_MODELO'!BR13 -> 1452763.3 | BT13: ='12_MODELO'!BR13 -> 368000 | BU13: =IFERROR('12_MODELO'!BO13/'12_MODELO'!BS13,0) -> 3.4955556
A14: 45658 | B14: Realizado | C14: =SUMIFS('09_VENDAS'!I$2:I$433,'09_VENDAS'!A$2:A$433,'12_MODELO'!A14) -> 1151091.5 | D14: ='12_MODELO'!C14*'12_MODELO'!BE14 -> 97842.777 | E14: ='12_MODELO'!C14-'12_MODELO'!D14 -> 1053248.7 | F14: =SUMIFS('09_VENDAS'!J$2:J$433,'09_VENDAS'!A$2:A$433,'12_MODELO'!A14) -> 786981.58 | G14: ='12_MODELO'!E14-'12_MODELO'!F14 -> 266267.13 | H14: =SUMIFS('10_DESPESAS'!D$2:D$123,'10_DESPESAS'!A$2:A$123,'12_MODELO'!A14,'10_DESPESAS'!B$2:B$123,"Pessoal") -> 105925 | I14: =SUMIFS('10_DESPESAS'!D$2:D$123,'10_DESPESAS'!A$2:A$123,'12_MODELO'!A14,'10_DESPESAS'!B$2:B$123,"Comercial") -> 41439.29 | J14: =SUMIFS('10_DESPESAS'!D$2:D$123,'10_DESPESAS'!A$2:A$123,'12_MODELO'!A14,'10_DESPESAS'!B$2:B$123,"Administrativo") -> 33920 | K14: =SUMIFS('10_DESPESAS'!D$2:D$123,'10_DESPESAS'!A$2:A$123,'12_MODELO'!A14,'10_DESPESAS'!B$2:B$123,"Tecnologia") -> 20160 | L14: =SUMIFS('10_DESPESAS'!D$2:D$123,'10_DESPESAS'!A$2:A$123,'12_MODELO'!A14,'10_DESPESAS'!B$2:B$123,"Operações") -> 25324.01 | M14: =SUM('12_MODELO'!H14:'12_MODELO'!L14) -> 226768.3 | N14: ='12_MODELO'!G14-'12_MODELO'!M14 -> 39498.833 | O14: =MIN('12_MODELO'!AC13*'12_MODELO'!BH14,'12_MODELO'!AC13-'12_MODELO'!AD13+'12_MODELO'!AB14) -> 20040 | P14: ='12_MODELO'!N14-'12_MODELO'!O14 -> 19458.833 | Q14: ='12_MODELO'!AG13*'12_MODELO'!BG14 -> 7008 | R14: ='12_MODELO'!P14-'12_MODELO'!Q14 -> 12450.833 | S14: =MAX(0,'12_MODELO'!R14)*'12_MODELO'!BF14 -> 4233.2833 | T14: ='12_MODELO'!R14-'12_MODELO'!S14 -> 8217.55 | U14: ='12_MODELO'!C14*'12_MODELO'!BB14/30 -> 1803376.7 | V14: ='12_MODELO'!F14*'12_MODELO'!BC14/30 -> 1364101.4 | W14: ='12_MODELO'!F14+'12_MODELO'!V14-'12_MODELO'!V13 -> 747883.65 | X14: ='12_MODELO'!F14*'12_MODELO'!BD14/30 -> 918145.18 | Y14: ='12_MODELO'!H14*20% -> 21185 | Z14: ='12_MODELO'!D14 -> 97842.777 | AA14: ='12_MODELO'!S14 -> 4233.2833 | AB14: ='08_PREMISSAS'!V14 -> 18000 | AC14: ='12_MODELO'!AC13+'12_MODELO'!AB14 -> 2022000 | AD14: ='12_MODELO'!AD13+'12_MODELO'!O14 -> 524880 | AE14: ='08_PREMISSAS'!W14 -> 0 | AF14: ='08_PREMISSAS'!X14 -> 18000 | AG14: ='12_MODELO'!AG13+'12_MODELO'!AE14-'12_MODELO'!AF14 -> 566000 | AH14: ='08_PREMISSAS'!Y14 -> 0 | AI14: ='12_MODELO'!AI13 -> 3900000 | AJ14: ='12_MODELO'!AJ13+'12_MODELO'!T14-'12_MODELO'!AH14 -> 864829.13 | AK14: ='12_MODELO'!U13+'12_MODELO'!C14-'12_MODELO'!U14 -> 1190007.6 | AL14: ='12_MODELO'!X13+'12_MODELO'!W14-'12_MODELO'!X14 -> 897390.14 | AM14: ='12_MODELO'!M14+'12_MODELO'!Y13-'12_MODELO'!Y14 -> 225343.3 | AN14: ='12_MODELO'!Z13+'12_MODELO'!D14-'12_MODELO'!Z14 -> 117446.16 | AO14: ='12_MODELO'!AA13+'12_MODELO'!S14-'12_MODELO'!AA14 -> 31905.493 | AP14: ='12_MODELO'!AK14-'12_MODELO'!AL14-'12_MODELO'!AM14-'12_MODELO'!AN14-'12_MODELO'!Q14-'12_MODELO'!AO14 -> -89085.504 | AQ14: ='12_MODELO'!T14+'12_MODELO'!O14-('12_MODELO'!U14-'12_MODELO'!U13)-('12_MODELO'!V14-'12_MODELO'!V13)+('12_MODELO'!X14-'12_MODELO'!X13)+('12_MODELO'!Y14-'12_MODELO'!Y13)+('12_MODELO'!Z14-'12_MODELO'!Z13)+('12_MODELO'!AA14-'12_MODELO'!AA13) -> -89085.504 | AR14: =-'12_MODELO'!AB14 -> -18000 | AS14: ='12_MODELO'!AE14-'12_MODELO'!AF14-'12_MODELO'!AH14 -> -18000 | AT14: ='12_MODELO'!AQ14+'12_MODELO'!AR14+'12_MODELO'!AS14 -> -125085.5 | AU14: ='12_MODELO'!AV13 -> 1832722.8 | AV14: ='12_MODELO'!AU14+'12_MODELO'!AT14 -> 1707637.3 | AW14: ='12_MODELO'!AV14+'12_MODELO'!U14+'12_MODELO'!V14+'12_MODELO'!AC14-'12_MODELO'!AD14 -> 6372235.4 | AX14: ='12_MODELO'!X14+'12_MODELO'!Y14+'12_MODELO'!Z14+'12_MODELO'!AA14+'12_MODELO'!AG14 -> 1607406.2 | AY14: ='12_MODELO'!AI14+'12_MODELO'!AJ14 -> 4764829.1 | AZ14: ='12_MODELO'!AW14-'12_MODELO'!AX14-'12_MODELO'!AY14 -> 9.3132257e-10 | BA14: ='12_MODELO'!AP14-'12_MODELO'!AQ14 -> 0 | BB14: ='08_PREMISSAS'!O14 -> 47 | BC14: ='08_PREMISSAS'!P14 -> 52 | BD14: ='08_PREMISSAS'!Q14 -> 35 | BE14: ='08_PREMISSAS'!R14 -> 0.085 | BF14: ='08_PREMISSAS'!S14 -> 0.34 | BG14: ='08_PREMISSAS'!T14 -> 0.012 | BH14: ='08_PREMISSAS'!U14 -> 0.01 | BI14: =IFERROR('12_MODELO'!N14/'12_MODELO'!E14,0) -> 0.037501905 | BJ14: =IFERROR('12_MODELO'!T14/'12_MODELO'!E14,0) -> 0.0078020983 | BK14: ='12_MODELO'!AQ14+'12_MODELO'!AR14 -> -107085.5 | BL14: ='12_MODELO'!U14+'12_MODELO'!V14-'12_MODELO'!X14-'12_MODELO'!Y14-'12_MODELO'!Z14-'12_MODELO'!AA14 -> 2126071.8 | BM14: ='12_MODELO'!AG14-'12_MODELO'!AV14 -> -1141637.3 | BN14: =MAX(ABS('15_CONCILIACAO'!F146),ABS('15_CONCILIACAO'!F147),ABS('15_CONCILIACAO'!F148),ABS('15_CONCILIACAO'!F149),ABS('15_CONCILIACAO'!F150),ABS('15_CONCILIACAO'!F151),ABS('15_CONCILIACAO'!F152),ABS('15_CONCILIACAO'!F153),ABS('15_CONCILIACAO'!F154),ABS('15_CONCILIACAO'!F155),ABS('15_CONCILIACAO'!F156),ABS('15_CONCILIACAO'!F157)) -> 2.5611371e-09 | BO14: ='12_MODELO'!AV14+'12_MODELO'!U14+'12_MODELO'!V14 -> 4875115.4 | BP14: ='12_MODELO'!AC14-'12_MODELO'!AD14 -> 1497120 | BQ14: =MIN('12_MODELO'!AG14,'12_MODELO'!AF14*12) -> 216000 | BR14: ='12_MODELO'!AG14-'12_MODELO'!BQ14 -> 350000 | BS14: ='12_MODELO'!AX14-'12_MODELO'!BR14 -> 1257406.2 | BT14: ='12_MODELO'!BR14 -> 350000 | BU14: =IFERROR('12_MODELO'!BO14/'12_MODELO'!BS14,0) -> 3.8771204
A15: 45689 | B15: Realizado | C15: =SUMIFS('09_VENDAS'!I$2:I$433,'09_VENDAS'!A$2:A$433,'12_MODELO'!A15) -> 1176731.8 | D15: ='12_MODELO'!C15*'12_MODELO'!BE15 -> 100022.2 | E15: ='12_MODELO'!C15-'12_MODELO'!D15 -> 1076709.6 | F15: =SUMIFS('09_VENDAS'!J$2:J$433,'09_VENDAS'!A$2:A$433,'12_MODELO'!A15) -> 805807.26 | G15: ='12_MODELO'!E15-'12_MODELO'!F15 -> 270902.3 | H15: =SUMIFS('10_DESPESAS'!D$2:D$123,'10_DESPESAS'!A$2:A$123,'12_MODELO'!A15,'10_DESPESAS'!B$2:B$123,"Pessoal") -> 105925 | I15: =SUMIFS('10_DESPESAS'!D$2:D$123,'10_DESPESAS'!A$2:A$123,'12_MODELO'!A15,'10_DESPESAS'!B$2:B$123,"Comercial") -> 42362.34 | J15: =SUMIFS('10_DESPESAS'!D$2:D$123,'10_DESPESAS'!A$2:A$123,'12_MODELO'!A15,'10_DESPESAS'!B$2:B$123,"Administrativo") -> 33920 | K15: =SUMIFS('10_DESPESAS'!D$2:D$123,'10_DESPESAS'!A$2:A$123,'12_MODELO'!A15,'10_DESPESAS'!B$2:B$123,"Tecnologia") -> 20160 | L15: =SUMIFS('10_DESPESAS'!D$2:D$123,'10_DESPESAS'!A$2:A$123,'12_MODELO'!A15,'10_DESPESAS'!B$2:B$123,"Operações") -> 25888.1 | M15: =SUM('12_MODELO'!H15:'12_MODELO'!L15) -> 228255.44 | N15: ='12_MODELO'!G15-'12_MODELO'!M15 -> 42646.86 | O15: =MIN('12_MODELO'!AC14*'12_MODELO'!BH15,'12_MODELO'!AC14-'12_MODELO'!AD14+'12_MODELO'!AB15) -> 20220 | P15: ='12_MODELO'!N15-'12_MODELO'!O15 -> 22426.86 | Q15: ='12_MODELO'!AG14*'12_MODELO'!BG15 -> 6792 | R15: ='12_MODELO'!P15-'12_MODELO'!Q15 -> 15634.86 | S15: =MAX(0,'12_MODELO'!R15)*'12_MODELO'!BF15 -> 5315.8525 | T15: ='12_MODELO'!R15-'12_MODELO'!S15 -> 10319.008 | U15: ='12_MODELO'!C15*'12_MODELO'!BB15/30 -> 1843546.4 | V15: ='12_MODELO'!F15*'12_MODELO'!BC15/30 -> 1396732.6 | W15: ='12_MODELO'!F15+'12_MODELO'!V15-'12_MODELO'!V14 -> 838438.44 | X15: ='12_MODELO'!F15*'12_MODELO'!BD15/30 -> 940108.47 | Y15: ='12_MODELO'!H15*20% -> 21185 | Z15: ='12_MODELO'!D15 -> 100022.2 | AA15: ='12_MODELO'!S15 -> 5315.8525 | AB15: ='08_PREMISSAS'!V15 -> 18000 | AC15: ='12_MODELO'!AC14+'12_MODELO'!AB15 -> 2040000 | AD15: ='12_MODELO'!AD14+'12_MODELO'!O15 -> 545100 | AE15: ='08_PREMISSAS'!W15 -> 0 | AF15: ='08_PREMISSAS'!X15 -> 18000 | AG15: ='12_MODELO'!AG14+'12_MODELO'!AE15-'12_MODELO'!AF15 -> 548000 | AH15: ='08_PREMISSAS'!Y15 -> 0 | AI15: ='12_MODELO'!AI14 -> 3900000 | AJ15: ='12_MODELO'!AJ14+'12_MODELO'!T15-'12_MODELO'!AH15 -> 875148.13 | AK15: ='12_MODELO'!U14+'12_MODELO'!C15-'12_MODELO'!U15 -> 1136562 | AL15: ='12_MODELO'!X14+'12_MODELO'!W15-'12_MODELO'!X15 -> 816475.15 | AM15: ='12_MODELO'!M15+'12_MODELO'!Y14-'12_MODELO'!Y15 -> 228255.44 | AN15: ='12_MODELO'!Z14+'12_MODELO'!D15-'12_MODELO'!Z15 -> 97842.777 | AO15: ='12_MODELO'!AA14+'12_MODELO'!S15-'12_MODELO'!AA15 -> 4233.2833 | AP15: ='12_MODELO'!AK15-'12_MODELO'!AL15-'12_MODELO'!AM15-'12_MODELO'!AN15-'12_MODELO'!Q15-'12_MODELO'!AO15 -> -17036.642 | AQ15: ='12_MODELO'!T15+'12_MODELO'!O15-('12_MODELO'!U15-'12_MODELO'!U14)-('12_MODELO'!V15-'12_MODELO'!V14)+('12_MODELO'!X15-'12_MODELO'!X14)+('12_MODELO'!Y15-'12_MODELO'!Y14)+('12_MODELO'!Z15-'12_MODELO'!Z14)+('12_MODELO'!AA15-'12_MODELO'!AA14) -> -17036.642 | AR15: =-'12_MODELO'!AB15 -> -18000 | AS15: ='12_MODELO'!AE15-'12_MODELO'!AF15-'12_MODELO'!AH15 -> -18000 | AT15: ='12_MODELO'!AQ15+'12_MODELO'!AR15+'12_MODELO'!AS15 -> -53036.642 | AU15: ='12_MODELO'!AV14 -> 1707637.3 | AV15: ='12_MODELO'!AU15+'12_MODELO'!AT15 -> 1654600.6 | AW15: ='12_MODELO'!AV15+'12_MODELO'!U15+'12_MODELO'!V15+'12_MODELO'!AC15-'12_MODELO'!AD15 -> 6389779.7 | AX15: ='12_MODELO'!X15+'12_MODELO'!Y15+'12_MODELO'!Z15+'12_MODELO'!AA15+'12_MODELO'!AG15 -> 1614631.5 | AY15: ='12_MODELO'!AI15+'12_MODELO'!AJ15 -> 4775148.1 | AZ15: ='12_MODELO'!AW15-'12_MODELO'!AX15-'12_MODELO'!AY15 -> 0 | BA15: ='12_MODELO'!AP15-'12_MODELO'!AQ15 -> 1.5643309e-10 | BB15: ='08_PREMISSAS'!O15 -> 47 | BC15: ='08_PREMISSAS'!P15 -> 52 | BD15: ='08_PREMISSAS'!Q15 -> 35 | BE15: ='08_PREMISSAS'!R15 -> 0.085 | BF15: ='08_PREMISSAS'!S15 -> 0.34 | BG15: ='08_PREMISSAS'!T15 -> 0.012 | BH15: ='08_PREMISSAS'!U15 -> 0.01 | BI15: =IFERROR('12_MODELO'!N15/'12_MODELO'!E15,0) -> 0.039608509 | BJ15: =IFERROR('12_MODELO'!T15/'12_MODELO'!E15,0) -> 0.009583836 | BK15: ='12_MODELO'!AQ15+'12_MODELO'!AR15 -> -35036.642 | BL15: ='12_MODELO'!U15+'12_MODELO'!V15-'12_MODELO'!X15-'12_MODELO'!Y15-'12_MODELO'!Z15-'12_MODELO'!AA15 -> 2173647.5 | BM15: ='12_MODELO'!AG15-'12_MODELO'!AV15 -> -1106600.6 | BN15: =MAX(ABS('15_CONCILIACAO'!F158),ABS('15_CONCILIACAO'!F159),ABS('15_CONCILIACAO'!F160),ABS('15_CONCILIACAO'!F161),ABS('15_CONCILIACAO'!F162),ABS('15_CONCILIACAO'!F163),ABS('15_CONCILIACAO'!F164),ABS('15_CONCILIACAO'!F165),ABS('15_CONCILIACAO'!F166),ABS('15_CONCILIACAO'!F167),ABS('15_CONCILIACAO'!F168),ABS('15_CONCILIACAO'!F169)) -> 2.5611371e-09 | BO15: ='12_MODELO'!AV15+'12_MODELO'!U15+'12_MODELO'!V15 -> 4894879.7 | BP15: ='12_MODELO'!AC15-'12_MODELO'!AD15 -> 1494900 | BQ15: =MIN('12_MODELO'!AG15,'12_MODELO'!AF15*12) -> 216000 | BR15: ='12_MODELO'!AG15-'12_MODELO'!BQ15 -> 332000 | BS15: ='12_MODELO'!AX15-'12_MODELO'!BR15 -> 1282631.5 | BT15: ='12_MODELO'!BR15 -> 332000 | BU15: =IFERROR('12_MODELO'!BO15/'12_MODELO'!BS15,0) -> 3.8162789
A16: 45717 | B16: Realizado | C16: =SUMIFS('09_VENDAS'!I$2:I$433,'09_VENDAS'!A$2:A$433,'12_MODELO'!A16) -> 1389953.1 | D16: ='12_MODELO'!C16*'12_MODELO'!BE16 -> 118146.01 | E16: ='12_MODELO'!C16-'12_MODELO'!D16 -> 1271807.1 | F16: =SUMIFS('09_VENDAS'!J$2:J$433,'09_VENDAS'!A$2:A$433,'12_MODELO'!A16) -> 952291.92 | G16: ='12_MODELO'!E16-'12_MODELO'!F16 -> 319515.15 | H16: =SUMIFS('10_DESPESAS'!D$2:D$123,'10_DESPESAS'!A$2:A$123,'12_MODELO'!A16,'10_DESPESAS'!B$2:B$123,"Pessoal") -> 105925 | I16: =SUMIFS('10_DESPESAS'!D$2:D$123,'10_DESPESAS'!A$2:A$123,'12_MODELO'!A16,'10_DESPESAS'!B$2:B$123,"Comercial") -> 50038.31 | J16: =SUMIFS('10_DESPESAS'!D$2:D$123,'10_DESPESAS'!A$2:A$123,'12_MODELO'!A16,'10_DESPESAS'!B$2:B$123,"Administrativo") -> 33920 | K16: =SUMIFS('10_DESPESAS'!D$2:D$123,'10_DESPESAS'!A$2:A$123,'12_MODELO'!A16,'10_DESPESAS'!B$2:B$123,"Tecnologia") -> 20160 | L16: =SUMIFS('10_DESPESAS'!D$2:D$123,'10_DESPESAS'!A$2:A$123,'12_MODELO'!A16,'10_DESPESAS'!B$2:B$123,"Operações") -> 30578.97 | M16: =SUM('12_MODELO'!H16:'12_MODELO'!L16) -> 240622.28 | N16: ='12_MODELO'!G16-'12_MODELO'!M16 -> 78892.868 | O16: =MIN('12_MODELO'!AC15*'12_MODELO'!BH16,'12_MODELO'!AC15-'12_MODELO'!AD15+'12_MODELO'!AB16) -> 20400 | P16: ='12_MODELO'!N16-'12_MODELO'!O16 -> 58492.868 | Q16: ='12_MODELO'!AG15*'12_MODELO'!BG16 -> 6576 | R16: ='12_MODELO'!P16-'12_MODELO'!Q16 -> 51916.868 | S16: =MAX(0,'12_MODELO'!R16)*'12_MODELO'!BF16 -> 17651.735 | T16: ='12_MODELO'!R16-'12_MODELO'!S16 -> 34265.133 | U16: ='12_MODELO'!C16*'12_MODELO'!BB16/30 -> 2177593.2 | V16: ='12_MODELO'!F16*'12_MODELO'!BC16/30 -> 1650639.3 | W16: ='12_MODELO'!F16+'12_MODELO'!V16-'12_MODELO'!V15 -> 1206198.7 | X16: ='12_MODELO'!F16*'12_MODELO'!BD16/30 -> 1111007.2 | Y16: ='12_MODELO'!H16*20% -> 21185 | Z16: ='12_MODELO'!D16 -> 118146.01 | AA16: ='12_MODELO'!S16 -> 17651.735 | AB16: ='08_PREMISSAS'!V16 -> 90000 | AC16: ='12_MODELO'!AC15+'12_MODELO'!AB16 -> 2130000 | AD16: ='12_MODELO'!AD15+'12_MODELO'!O16 -> 565500 | AE16: ='08_PREMISSAS'!W16 -> 0 | AF16: ='08_PREMISSAS'!X16 -> 18000 | AG16: ='12_MODELO'!AG15+'12_MODELO'!AE16-'12_MODELO'!AF16 -> 530000 | AH16: ='08_PREMISSAS'!Y16 -> 0 | AI16: ='12_MODELO'!AI15 -> 3900000 | AJ16: ='12_MODELO'!AJ15+'12_MODELO'!T16-'12_MODELO'!AH16 -> 909413.27 | AK16: ='12_MODELO'!U15+'12_MODELO'!C16-'12_MODELO'!U16 -> 1055906.3 | AL16: ='12_MODELO'!X15+'12_MODELO'!W16-'12_MODELO'!X16 -> 1035299.9 | AM16: ='12_MODELO'!M16+'12_MODELO'!Y15-'12_MODELO'!Y16 -> 240622.28 | AN16: ='12_MODELO'!Z15+'12_MODELO'!D16-'12_MODELO'!Z16 -> 100022.2 | AO16: ='12_MODELO'!AA15+'12_MODELO'!S16-'12_MODELO'!AA16 -> 5315.8525 | AP16: ='12_MODELO'!AK16-'12_MODELO'!AL16-'12_MODELO'!AM16-'12_MODELO'!AN16-'12_MODELO'!Q16-'12_MODELO'!AO16 -> -331929.88 | AQ16: ='12_MODELO'!T16+'12_MODELO'!O16-('12_MODELO'!U16-'12_MODELO'!U15)-('12_MODELO'!V16-'12_MODELO'!V15)+('12_MODELO'!X16-'12_MODELO'!X15)+('12_MODELO'!Y16-'12_MODELO'!Y15)+('12_MODELO'!Z16-'12_MODELO'!Z15)+('12_MODELO'!AA16-'12_MODELO'!AA15) -> -331929.88 | AR16: =-'12_MODELO'!AB16 -> -90000 | AS16: ='12_MODELO'!AE16-'12_MODELO'!AF16-'12_MODELO'!AH16 -> -18000 | AT16: ='12_MODELO'!AQ16+'12_MODELO'!AR16+'12_MODELO'!AS16 -> -439929.88 | AU16: ='12_MODELO'!AV15 -> 1654600.6 | AV16: ='12_MODELO'!AU16+'12_MODELO'!AT16 -> 1214670.8 | AW16: ='12_MODELO'!AV16+'12_MODELO'!U16+'12_MODELO'!V16+'12_MODELO'!AC16-'12_MODELO'!AD16 -> 6607403.3 | AX16: ='12_MODELO'!X16+'12_MODELO'!Y16+'12_MODELO'!Z16+'12_MODELO'!AA16+'12_MODELO'!AG16 -> 1797990 | AY16: ='12_MODELO'!AI16+'12_MODELO'!AJ16 -> 4809413.3 | AZ16: ='12_MODELO'!AW16-'12_MODELO'!AX16-'12_MODELO'!AY16 -> -1.8626451e-09 | BA16: ='12_MODELO'!AP16-'12_MODELO'!AQ16 -> 0 | BB16: ='08_PREMISSAS'!O16 -> 47 | BC16: ='08_PREMISSAS'!P16 -> 52 | BD16: ='08_PREMISSAS'!Q16 -> 35 | BE16: ='08_PREMISSAS'!R16 -> 0.085 | BF16: ='08_PREMISSAS'!S16 -> 0.34 | BG16: ='08_PREMISSAS'!T16 -> 0.012 | BH16: ='08_PREMISSAS'!U16 -> 0.01 | BI16: =IFERROR('12_MODELO'!N16/'12_MODELO'!E16,0) -> 0.062032104 | BJ16: =IFERROR('12_MODELO'!T16/'12_MODELO'!E16,0) -> 0.026942084 | BK16: ='12_MODELO'!AQ16+'12_MODELO'!AR16 -> -421929.88 | BL16: ='12_MODELO'!U16+'12_MODELO'!V16-'12_MODELO'!X16-'12_MODELO'!Y16-'12_MODELO'!Z16-'12_MODELO'!AA16 -> 2560242.5 | BM16: ='12_MODELO'!AG16-'12_MODELO'!AV16 -> -684670.77 | BN16: =MAX(ABS('15_CONCILIACAO'!F170),ABS('15_CONCILIACAO'!F171),ABS('15_CONCILIACAO'!F172),ABS('15_CONCILIACAO'!F173),ABS('15_CONCILIACAO'!F174),ABS('15_CONCILIACAO'!F175),ABS('15_CONCILIACAO'!F176),ABS('15_CONCILIACAO'!F177),ABS('15_CONCILIACAO'!F178),ABS('15_CONCILIACAO'!F179),ABS('15_CONCILIACAO'!F180),ABS('15_CONCILIACAO'!F181)) -> 2.5611371e-09 | BO16: ='12_MODELO'!AV16+'12_MODELO'!U16+'12_MODELO'!V16 -> 5042903.3 | BP16: ='12_MODELO'!AC16-'12_MODELO'!AD16 -> 1564500 | BQ16: =MIN('12_MODELO'!AG16,'12_MODELO'!AF16*12) -> 216000 | BR16: ='12_MODELO'!AG16-'12_MODELO'!BQ16 -> 314000 | BS16: ='12_MODELO'!AX16-'12_MODELO'!BR16 -> 1483990 | BT16: ='12_MODELO'!BR16 -> 314000 | BU16: =IFERROR('12_MODELO'!BO16/'12_MODELO'!BS16,0) -> 3.3982057
A17: 45748 | B17: Realizado | C17: =SUMIFS('09_VENDAS'!I$2:I$433,'09_VENDAS'!A$2:A$433,'12_MODELO'!A17) -> 1384297.2 | D17: ='12_MODELO'!C17*'12_MODELO'!BE17 -> 117665.26 | E17: ='12_MODELO'!C17-'12_MODELO'!D17 -> 1266632 | F17: =SUMIFS('09_VENDAS'!J$2:J$433,'09_VENDAS'!A$2:A$433,'12_MODELO'!A17) -> 950090.68 | G17: ='12_MODELO'!E17-'12_MODELO'!F17 -> 316541.28 | H17: =SUMIFS('10_DESPESAS'!D$2:D$123,'10_DESPESAS'!A$2:A$123,'12_MODELO'!A17,'10_DESPESAS'!B$2:B$123,"Pessoal") -> 105925 | I17: =SUMIFS('10_DESPESAS'!D$2:D$123,'10_DESPESAS'!A$2:A$123,'12_MODELO'!A17,'10_DESPESAS'!B$2:B$123,"Comercial") -> 49834.7 | J17: =SUMIFS('10_DESPESAS'!D$2:D$123,'10_DESPESAS'!A$2:A$123,'12_MODELO'!A17,'10_DESPESAS'!B$2:B$123,"Administrativo") -> 33920 | K17: =SUMIFS('10_DESPESAS'!D$2:D$123,'10_DESPESAS'!A$2:A$123,'12_MODELO'!A17,'10_DESPESAS'!B$2:B$123,"Tecnologia") -> 48160 | L17: =SUMIFS('10_DESPESAS'!D$2:D$123,'10_DESPESAS'!A$2:A$123,'12_MODELO'!A17,'10_DESPESAS'!B$2:B$123,"Operações") -> 30454.54 | M17: =SUM('12_MODELO'!H17:'12_MODELO'!L17) -> 268294.24 | N17: ='12_MODELO'!G17-'12_MODELO'!M17 -> 48247.036 | O17: =MIN('12_MODELO'!AC16*'12_MODELO'!BH17,'12_MODELO'!AC16-'12_MODELO'!AD16+'12_MODELO'!AB17) -> 21300 | P17: ='12_MODELO'!N17-'12_MODELO'!O17 -> 26947.036 | Q17: ='12_MODELO'!AG16*'12_MODELO'!BG17 -> 6360 | R17: ='12_MODELO'!P17-'12_MODELO'!Q17 -> 20587.036 | S17: =MAX(0,'12_MODELO'!R17)*'12_MODELO'!BF17 -> 6999.5923 | T17: ='12_MODELO'!R17-'12_MODELO'!S17 -> 13587.444 | U17: ='12_MODELO'!C17*'12_MODELO'!BB17/30 -> 2168732.3 | V17: ='12_MODELO'!F17*'12_MODELO'!BC17/30 -> 1646823.8 | W17: ='12_MODELO'!F17+'12_MODELO'!V17-'12_MODELO'!V16 -> 946275.2 | X17: ='12_MODELO'!F17*'12_MODELO'!BD17/30 -> 1108439.1 | Y17: ='12_MODELO'!H17*20% -> 21185 | Z17: ='12_MODELO'!D17 -> 117665.26 | AA17: ='12_MODELO'!S17 -> 6999.5923 | AB17: ='08_PREMISSAS'!V17 -> 18000 | AC17: ='12_MODELO'!AC16+'12_MODELO'!AB17 -> 2148000 | AD17: ='12_MODELO'!AD16+'12_MODELO'!O17 -> 586800 | AE17: ='08_PREMISSAS'!W17 -> 350000 | AF17: ='08_PREMISSAS'!X17 -> 18000 | AG17: ='12_MODELO'!AG16+'12_MODELO'!AE17-'12_MODELO'!AF17 -> 862000 | AH17: ='08_PREMISSAS'!Y17 -> 0 | AI17: ='12_MODELO'!AI16 -> 3900000 | AJ17: ='12_MODELO'!AJ16+'12_MODELO'!T17-'12_MODELO'!AH17 -> 923000.71 | AK17: ='12_MODELO'!U16+'12_MODELO'!C17-'12_MODELO'!U17 -> 1393158.1 | AL17: ='12_MODELO'!X16+'12_MODELO'!W17-'12_MODELO'!X17 -> 948843.31 | AM17: ='12_MODELO'!M17+'12_MODELO'!Y16-'12_MODELO'!Y17 -> 268294.24 | AN17: ='12_MODELO'!Z16+'12_MODELO'!D17-'12_MODELO'!Z17 -> 118146.01 | AO17: ='12_MODELO'!AA16+'12_MODELO'!S17-'12_MODELO'!AA17 -> 17651.735 | AP17: ='12_MODELO'!AK17-'12_MODELO'!AL17-'12_MODELO'!AM17-'12_MODELO'!AN17-'12_MODELO'!Q17-'12_MODELO'!AO17 -> 33862.77 | AQ17: ='12_MODELO'!T17+'12_MODELO'!O17-('12_MODELO'!U17-'12_MODELO'!U16)-('12_MODELO'!V17-'12_MODELO'!V16)+('12_MODELO'!X17-'12_MODELO'!X16)+('12_MODELO'!Y17-'12_MODELO'!Y16)+('12_MODELO'!Z17-'12_MODELO'!Z16)+('12_MODELO'!AA17-'12_MODELO'!AA16) -> 33862.77 | AR17: =-'12_MODELO'!AB17 -> -18000 | AS17: ='12_MODELO'!AE17-'12_MODELO'!AF17-'12_MODELO'!AH17 -> 332000 | AT17: ='12_MODELO'!AQ17+'12_MODELO'!AR17+'12_MODELO'!AS17 -> 347862.77 | AU17: ='12_MODELO'!AV16 -> 1214670.8 | AV17: ='12_MODELO'!AU17+'12_MODELO'!AT17 -> 1562533.5 | AW17: ='12_MODELO'!AV17+'12_MODELO'!U17+'12_MODELO'!V17+'12_MODELO'!AC17-'12_MODELO'!AD17 -> 6939289.7 | AX17: ='12_MODELO'!X17+'12_MODELO'!Y17+'12_MODELO'!Z17+'12_MODELO'!AA17+'12_MODELO'!AG17 -> 2116289 | AY17: ='12_MODELO'!AI17+'12_MODELO'!AJ17 -> 4823000.7 | AZ17: ='12_MODELO'!AW17-'12_MODELO'!AX17-'12_MODELO'!AY17 -> 0 | BA17: ='12_MODELO'!AP17-'12_MODELO'!AQ17 -> 3.3469405e-10 | BB17: ='08_PREMISSAS'!O17 -> 47 | BC17: ='08_PREMISSAS'!P17 -> 52 | BD17: ='08_PREMISSAS'!Q17 -> 35 | BE17: ='08_PREMISSAS'!R17 -> 0.085 | BF17: ='08_PREMISSAS'!S17 -> 0.34 | BG17: ='08_PREMISSAS'!T17 -> 0.012 | BH17: ='08_PREMISSAS'!U17 -> 0.01 | BI17: =IFERROR('12_MODELO'!N17/'12_MODELO'!E17,0) -> 0.038090809 | BJ17: =IFERROR('12_MODELO'!T17/'12_MODELO'!E17,0) -> 0.010727223 | BK17: ='12_MODELO'!AQ17+'12_MODELO'!AR17 -> 15862.77 | BL17: ='12_MODELO'!U17+'12_MODELO'!V17-'12_MODELO'!X17-'12_MODELO'!Y17-'12_MODELO'!Z17-'12_MODELO'!AA17 -> 2561267.2 | BM17: ='12_MODELO'!AG17-'12_MODELO'!AV17 -> -700533.54 | BN17: =MAX(ABS('15_CONCILIACAO'!F182),ABS('15_CONCILIACAO'!F183),ABS('15_CONCILIACAO'!F184),ABS('15_CONCILIACAO'!F185),ABS('15_CONCILIACAO'!F186),ABS('15_CONCILIACAO'!F187),ABS('15_CONCILIACAO'!F188),ABS('15_CONCILIACAO'!F189),ABS('15_CONCILIACAO'!F190),ABS('15_CONCILIACAO'!F191),ABS('15_CONCILIACAO'!F192),ABS('15_CONCILIACAO'!F193)) -> 3.259629e-09 | BO17: ='12_MODELO'!AV17+'12_MODELO'!U17+'12_MODELO'!V17 -> 5378089.7 | BP17: ='12_MODELO'!AC17-'12_MODELO'!AD17 -> 1561200 | BQ17: =MIN('12_MODELO'!AG17,'12_MODELO'!AF17*12) -> 216000 | BR17: ='12_MODELO'!AG17-'12_MODELO'!BQ17 -> 646000 | BS17: ='12_MODELO'!AX17-'12_MODELO'!BR17 -> 1470289 | BT17: ='12_MODELO'!BR17 -> 646000 | BU17: =IFERROR('12_MODELO'!BO17/'12_MODELO'!BS17,0) -> 3.6578453
A18: 45778 | B18: Realizado | C18: =SUMIFS('09_VENDAS'!I$2:I$433,'09_VENDAS'!A$2:A$433,'12_MODELO'!A18) -> 1449678.5 | D18: ='12_MODELO'!C18*'12_MODELO'!BE18 -> 123222.68 | E18: ='12_MODELO'!C18-'12_MODELO'!D18 -> 1326455.9 | F18: =SUMIFS('09_VENDAS'!J$2:J$433,'09_VENDAS'!A$2:A$433,'12_MODELO'!A18) -> 991818.4 | G18: ='12_MODELO'!E18-'12_MODELO'!F18 -> 334637.45 | H18: =SUMIFS('10_DESPESAS'!D$2:D$123,'10_DESPESAS'!A$2:A$123,'12_MODELO'!A18,'10_DESPESAS'!B$2:B$123,"Pessoal") -> 105925 | I18: =SUMIFS('10_DESPESAS'!D$2:D$123,'10_DESPESAS'!A$2:A$123,'12_MODELO'!A18,'10_DESPESAS'!B$2:B$123,"Comercial") -> 52188.43 | J18: =SUMIFS('10_DESPESAS'!D$2:D$123,'10_DESPESAS'!A$2:A$123,'12_MODELO'!A18,'10_DESPESAS'!B$2:B$123,"Administrativo") -> 33920 | K18: =SUMIFS('10_DESPESAS'!D$2:D$123,'10_DESPESAS'!A$2:A$123,'12_MODELO'!A18,'10_DESPESAS'!B$2:B$123,"Tecnologia") -> 48160 | L18: =SUMIFS('10_DESPESAS'!D$2:D$123,'10_DESPESAS'!A$2:A$123,'12_MODELO'!A18,'10_DESPESAS'!B$2:B$123,"Operações") -> 31892.93 | M18: =SUM('12_MODELO'!H18:'12_MODELO'!L18) -> 272086.36 | N18: ='12_MODELO'!G18-'12_MODELO'!M18 -> 62551.095 | O18: =MIN('12_MODELO'!AC17*'12_MODELO'!BH18,'12_MODELO'!AC17-'12_MODELO'!AD17+'12_MODELO'!AB18) -> 21480 | P18: ='12_MODELO'!N18-'12_MODELO'!O18 -> 41071.095 | Q18: ='12_MODELO'!AG17*'12_MODELO'!BG18 -> 10344 | R18: ='12_MODELO'!P18-'12_MODELO'!Q18 -> 30727.095 | S18: =MAX(0,'12_MODELO'!R18)*'12_MODELO'!BF18 -> 10447.212 | T18: ='12_MODELO'!R18-'12_MODELO'!S18 -> 20279.883 | U18: ='12_MODELO'!C18*'12_MODELO'!BB18/30 -> 2271163 | V18: ='12_MODELO'!F18*'12_MODELO'!BC18/30 -> 1719151.9 | W18: ='12_MODELO'!F18+'12_MODELO'!V18-'12_MODELO'!V17 -> 1064146.4 | X18: ='12_MODELO'!F18*'12_MODELO'!BD18/30 -> 1157121.5 | Y18: ='12_MODELO'!H18*20% -> 21185 | Z18: ='12_MODELO'!D18 -> 123222.68 | AA18: ='12_MODELO'!S18 -> 10447.212 | AB18: ='08_PREMISSAS'!V18 -> 18000 | AC18: ='12_MODELO'!AC17+'12_MODELO'!AB18 -> 2166000 | AD18: ='12_MODELO'!AD17+'12_MODELO'!O18 -> 608280 | AE18: ='08_PREMISSAS'!W18 -> 0 | AF18: ='08_PREMISSAS'!X18 -> 18000 | AG18: ='12_MODELO'!AG17+'12_MODELO'!AE18-'12_MODELO'!AF18 -> 844000 | AH18: ='08_PREMISSAS'!Y18 -> 0 | AI18: ='12_MODELO'!AI17 -> 3900000 | AJ18: ='12_MODELO'!AJ17+'12_MODELO'!T18-'12_MODELO'!AH18 -> 943280.59 | AK18: ='12_MODELO'!U17+'12_MODELO'!C18-'12_MODELO'!U18 -> 1347247.8 | AL18: ='12_MODELO'!X17+'12_MODELO'!W18-'12_MODELO'!X18 -> 1015464.1 | AM18: ='12_MODELO'!M18+'12_MODELO'!Y17-'12_MODELO'!Y18 -> 272086.36 | AN18: ='12_MODELO'!Z17+'12_MODELO'!D18-'12_MODELO'!Z18 -> 117665.26 | AO18: ='12_MODELO'!AA17+'12_MODELO'!S18-'12_MODELO'!AA18 -> 6999.5923 | AP18: ='12_MODELO'!AK18-'12_MODELO'!AL18-'12_MODELO'!AM18-'12_MODELO'!AN18-'12_MODELO'!Q18-'12_MODELO'!AO18 -> -75311.513 | AQ18: ='12_MODELO'!T18+'12_MODELO'!O18-('12_MODELO'!U18-'12_MODELO'!U17)-('12_MODELO'!V18-'12_MODELO'!V17)+('12_MODELO'!X18-'12_MODELO'!X17)+('12_MODELO'!Y18-'12_MODELO'!Y17)+('12_MODELO'!Z18-'12_MODELO'!Z17)+('12_MODELO'!AA18-'12_MODELO'!AA17) -> -75311.513 | AR18: =-'12_MODELO'!AB18 -> -18000 | AS18: ='12_MODELO'!AE18-'12_MODELO'!AF18-'12_MODELO'!AH18 -> -18000 | AT18: ='12_MODELO'!AQ18+'12_MODELO'!AR18+'12_MODELO'!AS18 -> -111311.51 | AU18: ='12_MODELO'!AV17 -> 1562533.5 | AV18: ='12_MODELO'!AU18+'12_MODELO'!AT18 -> 1451222 | AW18: ='12_MODELO'!AV18+'12_MODELO'!U18+'12_MODELO'!V18+'12_MODELO'!AC18-'12_MODELO'!AD18 -> 6999256.9 | AX18: ='12_MODELO'!X18+'12_MODELO'!Y18+'12_MODELO'!Z18+'12_MODELO'!AA18+'12_MODELO'!AG18 -> 2155976.4 | AY18: ='12_MODELO'!AI18+'12_MODELO'!AJ18 -> 4843280.6 | AZ18: ='12_MODELO'!AW18-'12_MODELO'!AX18-'12_MODELO'!AY18 -> -9.3132257e-10 | BA18: ='12_MODELO'!AP18-'12_MODELO'!AQ18 -> 2.910383e-10 | BB18: ='08_PREMISSAS'!O18 -> 47 | BC18: ='08_PREMISSAS'!P18 -> 52 | BD18: ='08_PREMISSAS'!Q18 -> 35 | BE18: ='08_PREMISSAS'!R18 -> 0.085 | BF18: ='08_PREMISSAS'!S18 -> 0.34 | BG18: ='08_PREMISSAS'!T18 -> 0.012 | BH18: ='08_PREMISSAS'!U18 -> 0.01 | BI18: =IFERROR('12_MODELO'!N18/'12_MODELO'!E18,0) -> 0.04715656 | BJ18: =IFERROR('12_MODELO'!T18/'12_MODELO'!E18,0) -> 0.015288773 | BK18: ='12_MODELO'!AQ18+'12_MODELO'!AR18 -> -93311.513 | BL18: ='12_MODELO'!U18+'12_MODELO'!V18-'12_MODELO'!X18-'12_MODELO'!Y18-'12_MODELO'!Z18-'12_MODELO'!AA18 -> 2678338.6 | BM18: ='12_MODELO'!AG18-'12_MODELO'!AV18 -> -607222.02 | BN18: =MAX(ABS('15_CONCILIACAO'!F194),ABS('15_CONCILIACAO'!F195),ABS('15_CONCILIACAO'!F196),ABS('15_CONCILIACAO'!F197),ABS('15_CONCILIACAO'!F198),ABS('15_CONCILIACAO'!F199),ABS('15_CONCILIACAO'!F200),ABS('15_CONCILIACAO'!F201),ABS('15_CONCILIACAO'!F202),ABS('15_CONCILIACAO'!F203),ABS('15_CONCILIACAO'!F204),ABS('15_CONCILIACAO'!F205)) -> 3.7252903e-09 | BO18: ='12_MODELO'!AV18+'12_MODELO'!U18+'12_MODELO'!V18 -> 5441536.9 | BP18: ='12_MODELO'!AC18-'12_MODELO'!AD18 -> 1557720 | BQ18: =MIN('12_MODELO'!AG18,'12_MODELO'!AF18*12) -> 216000 | BR18: ='12_MODELO'!AG18-'12_MODELO'!BQ18 -> 628000 | BS18: ='12_MODELO'!AX18-'12_MODELO'!BR18 -> 1527976.4 | BT18: ='12_MODELO'!BR18 -> 628000 | BU18: =IFERROR('12_MODELO'!BO18/'12_MODELO'!BS18,0) -> 3.5612704
A19: 45809 | B19: Realizado | C19: =SUMIFS('09_VENDAS'!I$2:I$433,'09_VENDAS'!A$2:A$433,'12_MODELO'!A19) -> 1471161 | D19: ='12_MODELO'!C19*'12_MODELO'!BE19 -> 125048.68 | E19: ='12_MODELO'!C19-'12_MODELO'!D19 -> 1346112.3 | F19: =SUMIFS('09_VENDAS'!J$2:J$433,'09_VENDAS'!A$2:A$433,'12_MODELO'!A19) -> 1007209.9 | G19: ='12_MODELO'!E19-'12_MODELO'!F19 -> 338902.35 | H19: =SUMIFS('10_DESPESAS'!D$2:D$123,'10_DESPESAS'!A$2:A$123,'12_MODELO'!A19,'10_DESPESAS'!B$2:B$123,"Pessoal") -> 105925 | I19: =SUMIFS('10_DESPESAS'!D$2:D$123,'10_DESPESAS'!A$2:A$123,'12_MODELO'!A19,'10_DESPESAS'!B$2:B$123,"Comercial") -> 52961.79 | J19: =SUMIFS('10_DESPESAS'!D$2:D$123,'10_DESPESAS'!A$2:A$123,'12_MODELO'!A19,'10_DESPESAS'!B$2:B$123,"Administrativo") -> 33920 | K19: =SUMIFS('10_DESPESAS'!D$2:D$123,'10_DESPESAS'!A$2:A$123,'12_MODELO'!A19,'10_DESPESAS'!B$2:B$123,"Tecnologia") -> 20160 | L19: =SUMIFS('10_DESPESAS'!D$2:D$123,'10_DESPESAS'!A$2:A$123,'12_MODELO'!A19,'10_DESPESAS'!B$2:B$123,"Operações") -> 32365.54 | M19: =SUM('12_MODELO'!H19:'12_MODELO'!L19) -> 245332.33 | N19: ='12_MODELO'!G19-'12_MODELO'!M19 -> 93570.018 | O19: =MIN('12_MODELO'!AC18*'12_MODELO'!BH19,'12_MODELO'!AC18-'12_MODELO'!AD18+'12_MODELO'!AB19) -> 21660 | P19: ='12_MODELO'!N19-'12_MODELO'!O19 -> 71910.018 | Q19: ='12_MODELO'!AG18*'12_MODELO'!BG19 -> 10128 | R19: ='12_MODELO'!P19-'12_MODELO'!Q19 -> 61782.018 | S19: =MAX(0,'12_MODELO'!R19)*'12_MODELO'!BF19 -> 21005.886 | T19: ='12_MODELO'!R19-'12_MODELO'!S19 -> 40776.132 | U19: ='12_MODELO'!C19*'12_MODELO'!BB19/30 -> 2304818.9 | V19: ='12_MODELO'!F19*'12_MODELO'!BC19/30 -> 1745830.6 | W19: ='12_MODELO'!F19+'12_MODELO'!V19-'12_MODELO'!V18 -> 1033888.6 | X19: ='12_MODELO'!F19*'12_MODELO'!BD19/30 -> 1175078.3 | Y19: ='12_MODELO'!H19*20% -> 21185 | Z19: ='12_MODELO'!D19 -> 125048.68 | AA19: ='12_MODELO'!S19 -> 21005.886 | AB19: ='08_PREMISSAS'!V19 -> 90000 | AC19: ='12_MODELO'!AC18+'12_MODELO'!AB19 -> 2256000 | AD19: ='12_MODELO'!AD18+'12_MODELO'!O19 -> 629940 | AE19: ='08_PREMISSAS'!W19 -> 0 | AF19: ='08_PREMISSAS'!X19 -> 18000 | AG19: ='12_MODELO'!AG18+'12_MODELO'!AE19-'12_MODELO'!AF19 -> 826000 | AH19: ='08_PREMISSAS'!Y19 -> 0 | AI19: ='12_MODELO'!AI18 -> 3900000 | AJ19: ='12_MODELO'!AJ18+'12_MODELO'!T19-'12_MODELO'!AH19 -> 984056.73 | AK19: ='12_MODELO'!U18+'12_MODELO'!C19-'12_MODELO'!U19 -> 1437505.1 | AL19: ='12_MODELO'!X18+'12_MODELO'!W19-'12_MODELO'!X19 -> 1015931.8 | AM19: ='12_MODELO'!M19+'12_MODELO'!Y18-'12_MODELO'!Y19 -> 245332.33 | AN19: ='12_MODELO'!Z18+'12_MODELO'!D19-'12_MODELO'!Z19 -> 123222.68 | AO19: ='12_MODELO'!AA18+'12_MODELO'!S19-'12_MODELO'!AA19 -> 10447.212 | AP19: ='12_MODELO'!AK19-'12_MODELO'!AL19-'12_MODELO'!AM19-'12_MODELO'!AN19-'12_MODELO'!Q19-'12_MODELO'!AO19 -> 32443.117 | AQ19: ='12_MODELO'!T19+'12_MODELO'!O19-('12_MODELO'!U19-'12_MODELO'!U18)-('12_MODELO'!V19-'12_MODELO'!V18)+('12_MODELO'!X19-'12_MODELO'!X18)+('12_MODELO'!Y19-'12_MODELO'!Y18)+('12_MODELO'!Z19-'12_MODELO'!Z18)+('12_MODELO'!AA19-'12_MODELO'!AA18) -> 32443.117 | AR19: =-'12_MODELO'!AB19 -> -90000 | AS19: ='12_MODELO'!AE19-'12_MODELO'!AF19-'12_MODELO'!AH19 -> -18000 | AT19: ='12_MODELO'!AQ19+'12_MODELO'!AR19+'12_MODELO'!AS19 -> -75556.883 | AU19: ='12_MODELO'!AV18 -> 1451222 | AV19: ='12_MODELO'!AU19+'12_MODELO'!AT19 -> 1375665.1 | AW19: ='12_MODELO'!AV19+'12_MODELO'!U19+'12_MODELO'!V19+'12_MODELO'!AC19-'12_MODELO'!AD19 -> 7052374.6 | AX19: ='12_MODELO'!X19+'12_MODELO'!Y19+'12_MODELO'!Z19+'12_MODELO'!AA19+'12_MODELO'!AG19 -> 2168317.8 | AY19: ='12_MODELO'!AI19+'12_MODELO'!AJ19 -> 4884056.7 | AZ19: ='12_MODELO'!AW19-'12_MODELO'!AX19-'12_MODELO'!AY19 -> 0 | BA19: ='12_MODELO'!AP19-'12_MODELO'!AQ19 -> 1.891749e-10 | BB19: ='08_PREMISSAS'!O19 -> 47 | BC19: ='08_PREMISSAS'!P19 -> 52 | BD19: ='08_PREMISSAS'!Q19 -> 35 | BE19: ='08_PREMISSAS'!R19 -> 0.085 | BF19: ='08_PREMISSAS'!S19 -> 0.34 | BG19: ='08_PREMISSAS'!T19 -> 0.012 | BH19: ='08_PREMISSAS'!U19 -> 0.01 | BI19: =IFERROR('12_MODELO'!N19/'12_MODELO'!E19,0) -> 0.069511302 | BJ19: =IFERROR('12_MODELO'!T19/'12_MODELO'!E19,0) -> 0.030291776 | BK19: ='12_MODELO'!AQ19+'12_MODELO'!AR19 -> -57556.883 | BL19: ='12_MODELO'!U19+'12_MODELO'!V19-'12_MODELO'!X19-'12_MODELO'!Y19-'12_MODELO'!Z19-'12_MODELO'!AA19 -> 2708331.6 | BM19: ='12_MODELO'!AG19-'12_MODELO'!AV19 -> -549665.14 | BN19: =MAX(ABS('15_CONCILIACAO'!F206),ABS('15_CONCILIACAO'!F207),ABS('15_CONCILIACAO'!F208),ABS('15_CONCILIACAO'!F209),ABS('15_CONCILIACAO'!F210),ABS('15_CONCILIACAO'!F211),ABS('15_CONCILIACAO'!F212),ABS('15_CONCILIACAO'!F213),ABS('15_CONCILIACAO'!F214),ABS('15_CONCILIACAO'!F215),ABS('15_CONCILIACAO'!F216),ABS('15_CONCILIACAO'!F217)) -> 3.9581209e-09 | BO19: ='12_MODELO'!AV19+'12_MODELO'!U19+'12_MODELO'!V19 -> 5426314.6 | BP19: ='12_MODELO'!AC19-'12_MODELO'!AD19 -> 1626060 | BQ19: =MIN('12_MODELO'!AG19,'12_MODELO'!AF19*12) -> 216000 | BR19: ='12_MODELO'!AG19-'12_MODELO'!BQ19 -> 610000 | BS19: ='12_MODELO'!AX19-'12_MODELO'!BR19 -> 1558317.8 | BT19: ='12_MODELO'!BR19 -> 610000 | BU19: =IFERROR('12_MODELO'!BO19/'12_MODELO'!BS19,0) -> 3.4821616
A20: 45839 | B20: Realizado | C20: =SUMIFS('09_VENDAS'!I$2:I$433,'09_VENDAS'!A$2:A$433,'12_MODELO'!A20) -> 1207312.5 | D20: ='12_MODELO'!C20*'12_MODELO'!BE20 -> 102621.56 | E20: ='12_MODELO'!C20-'12_MODELO'!D20 -> 1104690.9 | F20: =SUMIFS('09_VENDAS'!J$2:J$433,'09_VENDAS'!A$2:A$433,'12_MODELO'!A20) -> 820084.68 | G20: ='12_MODELO'!E20-'12_MODELO'!F20 -> 284606.24 | H20: =SUMIFS('10_DESPESAS'!D$2:D$123,'10_DESPESAS'!A$2:A$123,'12_MODELO'!A20,'10_DESPESAS'!B$2:B$123,"Pessoal") -> 110162 | I20: =SUMIFS('10_DESPESAS'!D$2:D$123,'10_DESPESAS'!A$2:A$123,'12_MODELO'!A20,'10_DESPESAS'!B$2:B$123,"Comercial") -> 43463.25 | J20: =SUMIFS('10_DESPESAS'!D$2:D$123,'10_DESPESAS'!A$2:A$123,'12_MODELO'!A20,'10_DESPESAS'!B$2:B$123,"Administrativo") -> 33920 | K20: =SUMIFS('10_DESPESAS'!D$2:D$123,'10_DESPESAS'!A$2:A$123,'12_MODELO'!A20,'10_DESPESAS'!B$2:B$123,"Tecnologia") -> 20160 | L20: =SUMIFS('10_DESPESAS'!D$2:D$123,'10_DESPESAS'!A$2:A$123,'12_MODELO'!A20,'10_DESPESAS'!B$2:B$123,"Operações") -> 26560.87 | M20: =SUM('12_MODELO'!H20:'12_MODELO'!L20) -> 234266.12 | N20: ='12_MODELO'!G20-'12_MODELO'!M20 -> 50340.119 | O20: =MIN('12_MODELO'!AC19*'12_MODELO'!BH20,'12_MODELO'!AC19-'12_MODELO'!AD19+'12_MODELO'!AB20) -> 22560 | P20: ='12_MODELO'!N20-'12_MODELO'!O20 -> 27780.119 | Q20: ='12_MODELO'!AG19*'12_MODELO'!BG20 -> 9912 | R20: ='12_MODELO'!P20-'12_MODELO'!Q20 -> 17868.119 | S20: =MAX(0,'12_MODELO'!R20)*'12_MODELO'!BF20 -> 6075.1605 | T20: ='12_MODELO'!R20-'12_MODELO'!S20 -> 11792.959 | U20: ='12_MODELO'!C20*'12_MODELO'!BB20/30 -> 2414625 | V20: ='12_MODELO'!F20*'12_MODELO'!BC20/30 -> 1694841.7 | W20: ='12_MODELO'!F20+'12_MODELO'!V20-'12_MODELO'!V19 -> 769095.79 | X20: ='12_MODELO'!F20*'12_MODELO'!BD20/30 -> 956765.46 | Y20: ='12_MODELO'!H20*20% -> 22032.4 | Z20: ='12_MODELO'!D20 -> 102621.56 | AA20: ='12_MODELO'!S20 -> 6075.1605 | AB20: ='08_PREMISSAS'!V20 -> 18000 | AC20: ='12_MODELO'!AC19+'12_MODELO'!AB20 -> 2274000 | AD20: ='12_MODELO'!AD19+'12_MODELO'!O20 -> 652500 | AE20: ='08_PREMISSAS'!W20 -> 0 | AF20: ='08_PREMISSAS'!X20 -> 18000 | AG20: ='12_MODELO'!AG19+'12_MODELO'!AE20-'12_MODELO'!AF20 -> 808000 | AH20: ='08_PREMISSAS'!Y20 -> 0 | AI20: ='12_MODELO'!AI19 -> 3900000 | AJ20: ='12_MODELO'!AJ19+'12_MODELO'!T20-'12_MODELO'!AH20 -> 995849.68 | AK20: ='12_MODELO'!U19+'12_MODELO'!C20-'12_MODELO'!U20 -> 1097506.4 | AL20: ='12_MODELO'!X19+'12_MODELO'!W20-'12_MODELO'!X20 -> 987408.59 | AM20: ='12_MODELO'!M20+'12_MODELO'!Y19-'12_MODELO'!Y20 -> 233418.72 | AN20: ='12_MODELO'!Z19+'12_MODELO'!D20-'12_MODELO'!Z20 -> 125048.68 | AO20: ='12_MODELO'!AA19+'12_MODELO'!S20-'12_MODELO'!AA20 -> 21005.886 | AP20: ='12_MODELO'!AK20-'12_MODELO'!AL20-'12_MODELO'!AM20-'12_MODELO'!AN20-'12_MODELO'!Q20-'12_MODELO'!AO20 -> -279287.51 | AQ20: ='12_MODELO'!T20+'12_MODELO'!O20-('12_MODELO'!U20-'12_MODELO'!U19)-('12_MODELO'!V20-'12_MODELO'!V19)+('12_MODELO'!X20-'12_MODELO'!X19)+('12_MODELO'!Y20-'12_MODELO'!Y19)+('12_MODELO'!Z20-'12_MODELO'!Z19)+('12_MODELO'!AA20-'12_MODELO'!AA19) -> -279287.51 | AR20: =-'12_MODELO'!AB20 -> -18000 | AS20: ='12_MODELO'!AE20-'12_MODELO'!AF20-'12_MODELO'!AH20 -> -18000 | AT20: ='12_MODELO'!AQ20+'12_MODELO'!AR20+'12_MODELO'!AS20 -> -315287.51 | AU20: ='12_MODELO'!AV19 -> 1375665.1 | AV20: ='12_MODELO'!AU20+'12_MODELO'!AT20 -> 1060377.6 | AW20: ='12_MODELO'!AV20+'12_MODELO'!U20+'12_MODELO'!V20+'12_MODELO'!AC20-'12_MODELO'!AD20 -> 6791344.3 | AX20: ='12_MODELO'!X20+'12_MODELO'!Y20+'12_MODELO'!Z20+'12_MODELO'!AA20+'12_MODELO'!AG20 -> 1895494.6 | AY20: ='12_MODELO'!AI20+'12_MODELO'!AJ20 -> 4895849.7 | AZ20: ='12_MODELO'!AW20-'12_MODELO'!AX20-'12_MODELO'!AY20 -> 0 | BA20: ='12_MODELO'!AP20-'12_MODELO'!AQ20 -> 1.7462298e-10 | BB20: ='08_PREMISSAS'!O20 -> 60 | BC20: ='08_PREMISSAS'!P20 -> 62 | BD20: ='08_PREMISSAS'!Q20 -> 35 | BE20: ='08_PREMISSAS'!R20 -> 0.085 | BF20: ='08_PREMISSAS'!S20 -> 0.34 | BG20: ='08_PREMISSAS'!T20 -> 0.012 | BH20: ='08_PREMISSAS'!U20 -> 0.01 | BI20: =IFERROR('12_MODELO'!N20/'12_MODELO'!E20,0) -> 0.045569415 | BJ20: =IFERROR('12_MODELO'!T20/'12_MODELO'!E20,0) -> 0.010675347 | BK20: ='12_MODELO'!AQ20+'12_MODELO'!AR20 -> -297287.51 | BL20: ='12_MODELO'!U20+'12_MODELO'!V20-'12_MODELO'!X20-'12_MODELO'!Y20-'12_MODELO'!Z20-'12_MODELO'!AA20 -> 3021972.1 | BM20: ='12_MODELO'!AG20-'12_MODELO'!AV20 -> -252377.63 | BN20: =MAX(ABS('15_CONCILIACAO'!F218),ABS('15_CONCILIACAO'!F219),ABS('15_CONCILIACAO'!F220),ABS('15_CONCILIACAO'!F221),ABS('15_CONCILIACAO'!F222),ABS('15_CONCILIACAO'!F223),ABS('15_CONCILIACAO'!F224),ABS('15_CONCILIACAO'!F225),ABS('15_CONCILIACAO'!F226),ABS('15_CONCILIACAO'!F227),ABS('15_CONCILIACAO'!F228),ABS('15_CONCILIACAO'!F229)) -> 4.1909516e-09 | BO20: ='12_MODELO'!AV20+'12_MODELO'!U20+'12_MODELO'!V20 -> 5169844.3 | BP20: ='12_MODELO'!AC20-'12_MODELO'!AD20 -> 1621500 | BQ20: =MIN('12_MODELO'!AG20,'12_MODELO'!AF20*12) -> 216000 | BR20: ='12_MODELO'!AG20-'12_MODELO'!BQ20 -> 592000 | BS20: ='12_MODELO'!AX20-'12_MODELO'!BR20 -> 1303494.6 | BT20: ='12_MODELO'!BR20 -> 592000 | BU20: =IFERROR('12_MODELO'!BO20/'12_MODELO'!BS20,0) -> 3.9661417
A21: 45870 | B21: Realizado | C21: =SUMIFS('09_VENDAS'!I$2:I$433,'09_VENDAS'!A$2:A$433,'12_MODELO'!A21) -> 1298644.8 | D21: ='12_MODELO'!C21*'12_MODELO'!BE21 -> 110384.81 | E21: ='12_MODELO'!C21-'12_MODELO'!D21 -> 1188260 | F21: =SUMIFS('09_VENDAS'!J$2:J$433,'09_VENDAS'!A$2:A$433,'12_MODELO'!A21) -> 883132.1 | G21: ='12_MODELO'!E21-'12_MODELO'!F21 -> 305127.93 | H21: =SUMIFS('10_DESPESAS'!D$2:D$123,'10_DESPESAS'!A$2:A$123,'12_MODELO'!A21,'10_DESPESAS'!B$2:B$123,"Pessoal") -> 110162 | I21: =SUMIFS('10_DESPESAS'!D$2:D$123,'10_DESPESAS'!A$2:A$123,'12_MODELO'!A21,'10_DESPESAS'!B$2:B$123,"Comercial") -> 46751.21 | J21: =SUMIFS('10_DESPESAS'!D$2:D$123,'10_DESPESAS'!A$2:A$123,'12_MODELO'!A21,'10_DESPESAS'!B$2:B$123,"Administrativo") -> 33920 | K21: =SUMIFS('10_DESPESAS'!D$2:D$123,'10_DESPESAS'!A$2:A$123,'12_MODELO'!A21,'10_DESPESAS'!B$2:B$123,"Tecnologia") -> 20160 | L21: =SUMIFS('10_DESPESAS'!D$2:D$123,'10_DESPESAS'!A$2:A$123,'12_MODELO'!A21,'10_DESPESAS'!B$2:B$123,"Operações") -> 28570.19 | M21: =SUM('12_MODELO'!H21:'12_MODELO'!L21) -> 239563.4 | N21: ='12_MODELO'!G21-'12_MODELO'!M21 -> 65564.529 | O21: =MIN('12_MODELO'!AC20*'12_MODELO'!BH21,'12_MODELO'!AC20-'12_MODELO'!AD20+'12_MODELO'!AB21) -> 22740 | P21: ='12_MODELO'!N21-'12_MODELO'!O21 -> 42824.529 | Q21: ='12_MODELO'!AG20*'12_MODELO'!BG21 -> 9696 | R21: ='12_MODELO'!P21-'12_MODELO'!Q21 -> 33128.529 | S21: =MAX(0,'12_MODELO'!R21)*'12_MODELO'!BF21 -> 11263.7 | T21: ='12_MODELO'!R21-'12_MODELO'!S21 -> 21864.829 | U21: ='12_MODELO'!C21*'12_MODELO'!BB21/30 -> 2597289.7 | V21: ='12_MODELO'!F21*'12_MODELO'!BC21/30 -> 1825139.7 | W21: ='12_MODELO'!F21+'12_MODELO'!V21-'12_MODELO'!V20 -> 1013430.1 | X21: ='12_MODELO'!F21*'12_MODELO'!BD21/30 -> 1030320.8 | Y21: ='12_MODELO'!H21*20% -> 22032.4 | Z21: ='12_MODELO'!D21 -> 110384.81 | AA21: ='12_MODELO'!S21 -> 11263.7 | AB21: ='08_PREMISSAS'!V21 -> 18000 | AC21: ='12_MODELO'!AC20+'12_MODELO'!AB21 -> 2292000 | AD21: ='12_MODELO'!AD20+'12_MODELO'!O21 -> 675240 | AE21: ='08_PREMISSAS'!W21 -> 0 | AF21: ='08_PREMISSAS'!X21 -> 18000 | AG21: ='12_MODELO'!AG20+'12_MODELO'!AE21-'12_MODELO'!AF21 -> 790000 | AH21: ='08_PREMISSAS'!Y21 -> 0 | AI21: ='12_MODELO'!AI20 -> 3900000 | AJ21: ='12_MODELO'!AJ20+'12_MODELO'!T21-'12_MODELO'!AH21 -> 1017714.5 | AK21: ='12_MODELO'!U20+'12_MODELO'!C21-'12_MODELO'!U21 -> 1115980.1 | AL21: ='12_MODELO'!X20+'12_MODELO'!W21-'12_MODELO'!X21 -> 939874.78 | AM21: ='12_MODELO'!M21+'12_MODELO'!Y20-'12_MODELO'!Y21 -> 239563.4 | AN21: ='12_MODELO'!Z20+'12_MODELO'!D21-'12_MODELO'!Z21 -> 102621.56 | AO21: ='12_MODELO'!AA20+'12_MODELO'!S21-'12_MODELO'!AA21 -> 6075.1605 | AP21: ='12_MODELO'!AK21-'12_MODELO'!AL21-'12_MODELO'!AM21-'12_MODELO'!AN21-'12_MODELO'!Q21-'12_MODELO'!AO21 -> -181850.78 | AQ21: ='12_MODELO'!T21+'12_MODELO'!O21-('12_MODELO'!U21-'12_MODELO'!U20)-('12_MODELO'!V21-'12_MODELO'!V20)+('12_MODELO'!X21-'12_MODELO'!X20)+('12_MODELO'!Y21-'12_MODELO'!Y20)+('12_MODELO'!Z21-'12_MODELO'!Z20)+('12_MODELO'!AA21-'12_MODELO'!AA20) -> -181850.78 | AR21: =-'12_MODELO'!AB21 -> -18000 | AS21: ='12_MODELO'!AE21-'12_MODELO'!AF21-'12_MODELO'!AH21 -> -18000 | AT21: ='12_MODELO'!AQ21+'12_MODELO'!AR21+'12_MODELO'!AS21 -> -217850.78 | AU21: ='12_MODELO'!AV20 -> 1060377.6 | AV21: ='12_MODELO'!AU21+'12_MODELO'!AT21 -> 842526.85 | AW21: ='12_MODELO'!AV21+'12_MODELO'!U21+'12_MODELO'!V21+'12_MODELO'!AC21-'12_MODELO'!AD21 -> 6881716.2 | AX21: ='12_MODELO'!X21+'12_MODELO'!Y21+'12_MODELO'!Z21+'12_MODELO'!AA21+'12_MODELO'!AG21 -> 1964001.7 | AY21: ='12_MODELO'!AI21+'12_MODELO'!AJ21 -> 4917714.5 | AZ21: ='12_MODELO'!AW21-'12_MODELO'!AX21-'12_MODELO'!AY21 -> 0 | BA21: ='12_MODELO'!AP21-'12_MODELO'!AQ21 -> -2.6193447e-10 | BB21: ='08_PREMISSAS'!O21 -> 60 | BC21: ='08_PREMISSAS'!P21 -> 62 | BD21: ='08_PREMISSAS'!Q21 -> 35 | BE21: ='08_PREMISSAS'!R21 -> 0.085 | BF21: ='08_PREMISSAS'!S21 -> 0.34 | BG21: ='08_PREMISSAS'!T21 -> 0.012 | BH21: ='08_PREMISSAS'!U21 -> 0.01 | BI21: =IFERROR('12_MODELO'!N21/'12_MODELO'!E21,0) -> 0.05517692 | BJ21: =IFERROR('12_MODELO'!T21/'12_MODELO'!E21,0) -> 0.018400711 | BK21: ='12_MODELO'!AQ21+'12_MODELO'!AR21 -> -199850.78 | BL21: ='12_MODELO'!U21+'12_MODELO'!V21-'12_MODELO'!X21-'12_MODELO'!Y21-'12_MODELO'!Z21-'12_MODELO'!AA21 -> 3248427.7 | BM21: ='12_MODELO'!AG21-'12_MODELO'!AV21 -> -52526.855 | BN21: =MAX(ABS('15_CONCILIACAO'!F230),ABS('15_CONCILIACAO'!F231),ABS('15_CONCILIACAO'!F232),ABS('15_CONCILIACAO'!F233),ABS('15_CONCILIACAO'!F234),ABS('15_CONCILIACAO'!F235),ABS('15_CONCILIACAO'!F236),ABS('15_CONCILIACAO'!F237),ABS('15_CONCILIACAO'!F238),ABS('15_CONCILIACAO'!F239),ABS('15_CONCILIACAO'!F240),ABS('15_CONCILIACAO'!F241)) -> 3.9581209e-09 | BO21: ='12_MODELO'!AV21+'12_MODELO'!U21+'12_MODELO'!V21 -> 5264956.2 | BP21: ='12_MODELO'!AC21-'12_MODELO'!AD21 -> 1616760 | BQ21: =MIN('12_MODELO'!AG21,'12_MODELO'!AF21*12) -> 216000 | BR21: ='12_MODELO'!AG21-'12_MODELO'!BQ21 -> 574000 | BS21: ='12_MODELO'!AX21-'12_MODELO'!BR21 -> 1390001.7 | BT21: ='12_MODELO'!BR21 -> 574000 | BU21: =IFERROR('12_MODELO'!BO21/'12_MODELO'!BS21,0) -> 3.7877337
A22: 45901 | B22: Realizado | C22: =SUMIFS('09_VENDAS'!I$2:I$433,'09_VENDAS'!A$2:A$433,'12_MODELO'!A22) -> 1385311.4 | D22: ='12_MODELO'!C22*'12_MODELO'!BE22 -> 117751.46 | E22: ='12_MODELO'!C22-'12_MODELO'!D22 -> 1267559.9 | F22: =SUMIFS('09_VENDAS'!J$2:J$433,'09_VENDAS'!A$2:A$433,'12_MODELO'!A22) -> 941100.92 | G22: ='12_MODELO'!E22-'12_MODELO'!F22 -> 326458.97 | H22: =SUMIFS('10_DESPESAS'!D$2:D$123,'10_DESPESAS'!A$2:A$123,'12_MODELO'!A22,'10_DESPESAS'!B$2:B$123,"Pessoal") -> 110162 | I22: =SUMIFS('10_DESPESAS'!D$2:D$123,'10_DESPESAS'!A$2:A$123,'12_MODELO'!A22,'10_DESPESAS'!B$2:B$123,"Comercial") -> 49871.21 | J22: =SUMIFS('10_DESPESAS'!D$2:D$123,'10_DESPESAS'!A$2:A$123,'12_MODELO'!A22,'10_DESPESAS'!B$2:B$123,"Administrativo") -> 33920 | K22: =SUMIFS('10_DESPESAS'!D$2:D$123,'10_DESPESAS'!A$2:A$123,'12_MODELO'!A22,'10_DESPESAS'!B$2:B$123,"Tecnologia") -> 20160 | L22: =SUMIFS('10_DESPESAS'!D$2:D$123,'10_DESPESAS'!A$2:A$123,'12_MODELO'!A22,'10_DESPESAS'!B$2:B$123,"Operações") -> 30476.85 | M22: =SUM('12_MODELO'!H22:'12_MODELO'!L22) -> 244590.06 | N22: ='12_MODELO'!G22-'12_MODELO'!M22 -> 81868.905 | O22: =MIN('12_MODELO'!AC21*'12_MODELO'!BH22,'12_MODELO'!AC21-'12_MODELO'!AD21+'12_MODELO'!AB22) -> 22920 | P22: ='12_MODELO'!N22-'12_MODELO'!O22 -> 58948.905 | Q22: ='12_MODELO'!AG21*'12_MODELO'!BG22 -> 9480 | R22: ='12_MODELO'!P22-'12_MODELO'!Q22 -> 49468.905 | S22: =MAX(0,'12_MODELO'!R22)*'12_MODELO'!BF22 -> 16819.428 | T22: ='12_MODELO'!R22-'12_MODELO'!S22 -> 32649.477 | U22: ='12_MODELO'!C22*'12_MODELO'!BB22/30 -> 2770622.7 | V22: ='12_MODELO'!F22*'12_MODELO'!BC22/30 -> 1944941.9 | W22: ='12_MODELO'!F22+'12_MODELO'!V22-'12_MODELO'!V21 -> 1060903.1 | X22: ='12_MODELO'!F22*'12_MODELO'!BD22/30 -> 1097951.1 | Y22: ='12_MODELO'!H22*20% -> 22032.4 | Z22: ='12_MODELO'!D22 -> 117751.46 | AA22: ='12_MODELO'!S22 -> 16819.428 | AB22: ='08_PREMISSAS'!V22 -> 90000 | AC22: ='12_MODELO'!AC21+'12_MODELO'!AB22 -> 2382000 | AD22: ='12_MODELO'!AD21+'12_MODELO'!O22 -> 698160 | AE22: ='08_PREMISSAS'!W22 -> 0 | AF22: ='08_PREMISSAS'!X22 -> 18000 | AG22: ='12_MODELO'!AG21+'12_MODELO'!AE22-'12_MODELO'!AF22 -> 772000 | AH22: ='08_PREMISSAS'!Y22 -> 0 | AI22: ='12_MODELO'!AI21 -> 3900000 | AJ22: ='12_MODELO'!AJ21+'12_MODELO'!T22-'12_MODELO'!AH22 -> 1050364 | AK22: ='12_MODELO'!U21+'12_MODELO'!C22-'12_MODELO'!U22 -> 1211978.3 | AL22: ='12_MODELO'!X21+'12_MODELO'!W22-'12_MODELO'!X22 -> 993272.86 | AM22: ='12_MODELO'!M22+'12_MODELO'!Y21-'12_MODELO'!Y22 -> 244590.06 | AN22: ='12_MODELO'!Z21+'12_MODELO'!D22-'12_MODELO'!Z22 -> 110384.81 | AO22: ='12_MODELO'!AA21+'12_MODELO'!S22-'12_MODELO'!AA22 -> 11263.7 | AP22: ='12_MODELO'!AK22-'12_MODELO'!AL22-'12_MODELO'!AM22-'12_MODELO'!AN22-'12_MODELO'!Q22-'12_MODELO'!AO22 -> -157013.1 | AQ22: ='12_MODELO'!T22+'12_MODELO'!O22-('12_MODELO'!U22-'12_MODELO'!U21)-('12_MODELO'!V22-'12_MODELO'!V21)+('12_MODELO'!X22-'12_MODELO'!X21)+('12_MODELO'!Y22-'12_MODELO'!Y21)+('12_MODELO'!Z22-'12_MODELO'!Z21)+('12_MODELO'!AA22-'12_MODELO'!AA21) -> -157013.1 | AR22: =-'12_MODELO'!AB22 -> -90000 | AS22: ='12_MODELO'!AE22-'12_MODELO'!AF22-'12_MODELO'!AH22 -> -18000 | AT22: ='12_MODELO'!AQ22+'12_MODELO'!AR22+'12_MODELO'!AS22 -> -265013.1 | AU22: ='12_MODELO'!AV21 -> 842526.85 | AV22: ='12_MODELO'!AU22+'12_MODELO'!AT22 -> 577513.76 | AW22: ='12_MODELO'!AV22+'12_MODELO'!U22+'12_MODELO'!V22+'12_MODELO'!AC22-'12_MODELO'!AD22 -> 6976918.4 | AX22: ='12_MODELO'!X22+'12_MODELO'!Y22+'12_MODELO'!Z22+'12_MODELO'!AA22+'12_MODELO'!AG22 -> 2026554.4 | AY22: ='12_MODELO'!AI22+'12_MODELO'!AJ22 -> 4950364 | AZ22: ='12_MODELO'!AW22-'12_MODELO'!AX22-'12_MODELO'!AY22 -> 0 | BA22: ='12_MODELO'!AP22-'12_MODELO'!AQ22 -> -2.6193447e-10 | BB22: ='08_PREMISSAS'!O22 -> 60 | BC22: ='08_PREMISSAS'!P22 -> 62 | BD22: ='08_PREMISSAS'!Q22 -> 35 | BE22: ='08_PREMISSAS'!R22 -> 0.085 | BF22: ='08_PREMISSAS'!S22 -> 0.34 | BG22: ='08_PREMISSAS'!T22 -> 0.012 | BH22: ='08_PREMISSAS'!U22 -> 0.01 | BI22: =IFERROR('12_MODELO'!N22/'12_MODELO'!E22,0) -> 0.064587801 | BJ22: =IFERROR('12_MODELO'!T22/'12_MODELO'!E22,0) -> 0.02575774 | BK22: ='12_MODELO'!AQ22+'12_MODELO'!AR22 -> -247013.1 | BL22: ='12_MODELO'!U22+'12_MODELO'!V22-'12_MODELO'!X22-'12_MODELO'!Y22-'12_MODELO'!Z22-'12_MODELO'!AA22 -> 3461010.2 | BM22: ='12_MODELO'!AG22-'12_MODELO'!AV22 -> 194486.24 | BN22: =MAX(ABS('15_CONCILIACAO'!F242),ABS('15_CONCILIACAO'!F243),ABS('15_CONCILIACAO'!F244),ABS('15_CONCILIACAO'!F245),ABS('15_CONCILIACAO'!F246),ABS('15_CONCILIACAO'!F247),ABS('15_CONCILIACAO'!F248),ABS('15_CONCILIACAO'!F249),ABS('15_CONCILIACAO'!F250),ABS('15_CONCILIACAO'!F251),ABS('15_CONCILIACAO'!F252),ABS('15_CONCILIACAO'!F253)) -> 3.608875e-09 | BO22: ='12_MODELO'!AV22+'12_MODELO'!U22+'12_MODELO'!V22 -> 5293078.4 | BP22: ='12_MODELO'!AC22-'12_MODELO'!AD22 -> 1683840 | BQ22: =MIN('12_MODELO'!AG22,'12_MODELO'!AF22*12) -> 216000 | BR22: ='12_MODELO'!AG22-'12_MODELO'!BQ22 -> 556000 | BS22: ='12_MODELO'!AX22-'12_MODELO'!BR22 -> 1470554.4 | BT22: ='12_MODELO'!BR22 -> 556000 | BU22: =IFERROR('12_MODELO'!BO22/'12_MODELO'!BS22,0) -> 3.5993762
A23: 45931 | B23: Realizado | C23: =SUMIFS('09_VENDAS'!I$2:I$433,'09_VENDAS'!A$2:A$433,'12_MODELO'!A23) -> 1555988.9 | D23: ='12_MODELO'!C23*'12_MODELO'!BE23 -> 132259.06 | E23: ='12_MODELO'!C23-'12_MODELO'!D23 -> 1423729.8 | F23: =SUMIFS('09_VENDAS'!J$2:J$433,'09_VENDAS'!A$2:A$433,'12_MODELO'!A23) -> 1065026.9 | G23: ='12_MODELO'!E23-'12_MODELO'!F23 -> 358702.97 | H23: =SUMIFS('10_DESPESAS'!D$2:D$123,'10_DESPESAS'!A$2:A$123,'12_MODELO'!A23,'10_DESPESAS'!B$2:B$123,"Pessoal") -> 110162 | I23: =SUMIFS('10_DESPESAS'!D$2:D$123,'10_DESPESAS'!A$2:A$123,'12_MODELO'!A23,'10_DESPESAS'!B$2:B$123,"Comercial") -> 56015.6 | J23: =SUMIFS('10_DESPESAS'!D$2:D$123,'10_DESPESAS'!A$2:A$123,'12_MODELO'!A23,'10_DESPESAS'!B$2:B$123,"Administrativo") -> 33920 | K23: =SUMIFS('10_DESPESAS'!D$2:D$123,'10_DESPESAS'!A$2:A$123,'12_MODELO'!A23,'10_DESPESAS'!B$2:B$123,"Tecnologia") -> 20160 | L23: =SUMIFS('10_DESPESAS'!D$2:D$123,'10_DESPESAS'!A$2:A$123,'12_MODELO'!A23,'10_DESPESAS'!B$2:B$123,"Operações") -> 34231.76 | M23: =SUM('12_MODELO'!H23:'12_MODELO'!L23) -> 254489.36 | N23: ='12_MODELO'!G23-'12_MODELO'!M23 -> 104213.61 | O23: =MIN('12_MODELO'!AC22*'12_MODELO'!BH23,'12_MODELO'!AC22-'12_MODELO'!AD22+'12_MODELO'!AB23) -> 23820 | P23: ='12_MODELO'!N23-'12_MODELO'!O23 -> 80393.614 | Q23: ='12_MODELO'!AG22*'12_MODELO'!BG23 -> 9264 | R23: ='12_MODELO'!P23-'12_MODELO'!Q23 -> 71129.614 | S23: =MAX(0,'12_MODELO'!R23)*'12_MODELO'!BF23 -> 24184.069 | T23: ='12_MODELO'!R23-'12_MODELO'!S23 -> 46945.545 | U23: ='12_MODELO'!C23*'12_MODELO'!BB23/30 -> 2437715.9 | V23: ='12_MODELO'!F23*'12_MODELO'!BC23/30 -> 1846046.6 | W23: ='12_MODELO'!F23+'12_MODELO'!V23-'12_MODELO'!V22 -> 966131.52 | X23: ='12_MODELO'!F23*'12_MODELO'!BD23/30 -> 1242531.3 | Y23: ='12_MODELO'!H23*20% -> 22032.4 | Z23: ='12_MODELO'!D23 -> 132259.06 | AA23: ='12_MODELO'!S23 -> 24184.069 | AB23: ='08_PREMISSAS'!V23 -> 18000 | AC23: ='12_MODELO'!AC22+'12_MODELO'!AB23 -> 2400000 | AD23: ='12_MODELO'!AD22+'12_MODELO'!O23 -> 721980 | AE23: ='08_PREMISSAS'!W23 -> 0 | AF23: ='08_PREMISSAS'!X23 -> 18000 | AG23: ='12_MODELO'!AG22+'12_MODELO'!AE23-'12_MODELO'!AF23 -> 754000 | AH23: ='08_PREMISSAS'!Y23 -> 0 | AI23: ='12_MODELO'!AI22 -> 3900000 | AJ23: ='12_MODELO'!AJ22+'12_MODELO'!T23-'12_MODELO'!AH23 -> 1097309.5 | AK23: ='12_MODELO'!U22+'12_MODELO'!C23-'12_MODELO'!U23 -> 1888895.7 | AL23: ='12_MODELO'!X22+'12_MODELO'!W23-'12_MODELO'!X23 -> 821551.25 | AM23: ='12_MODELO'!M23+'12_MODELO'!Y22-'12_MODELO'!Y23 -> 254489.36 | AN23: ='12_MODELO'!Z22+'12_MODELO'!D23-'12_MODELO'!Z23 -> 117751.46 | AO23: ='12_MODELO'!AA22+'12_MODELO'!S23-'12_MODELO'!AA23 -> 16819.428 | AP23: ='12_MODELO'!AK23-'12_MODELO'!AL23-'12_MODELO'!AM23-'12_MODELO'!AN23-'12_MODELO'!Q23-'12_MODELO'!AO23 -> 669020.16 | AQ23: ='12_MODELO'!T23+'12_MODELO'!O23-('12_MODELO'!U23-'12_MODELO'!U22)-('12_MODELO'!V23-'12_MODELO'!V22)+('12_MODELO'!X23-'12_MODELO'!X22)+('12_MODELO'!Y23-'12_MODELO'!Y22)+('12_MODELO'!Z23-'12_MODELO'!Z22)+('12_MODELO'!AA23-'12_MODELO'!AA22) -> 669020.16 | AR23: =-'12_MODELO'!AB23 -> -18000 | AS23: ='12_MODELO'!AE23-'12_MODELO'!AF23-'12_MODELO'!AH23 -> -18000 | AT23: ='12_MODELO'!AQ23+'12_MODELO'!AR23+'12_MODELO'!AS23 -> 633020.16 | AU23: ='12_MODELO'!AV22 -> 577513.76 | AV23: ='12_MODELO'!AU23+'12_MODELO'!AT23 -> 1210533.9 | AW23: ='12_MODELO'!AV23+'12_MODELO'!U23+'12_MODELO'!V23+'12_MODELO'!AC23-'12_MODELO'!AD23 -> 7172316.4 | AX23: ='12_MODELO'!X23+'12_MODELO'!Y23+'12_MODELO'!Z23+'12_MODELO'!AA23+'12_MODELO'!AG23 -> 2175006.9 | AY23: ='12_MODELO'!AI23+'12_MODELO'!AJ23 -> 4997309.5 | AZ23: ='12_MODELO'!AW23-'12_MODELO'!AX23-'12_MODELO'!AY23 -> -9.3132257e-10 | BA23: ='12_MODELO'!AP23-'12_MODELO'!AQ23 -> -2.3283064e-10 | BB23: ='08_PREMISSAS'!O23 -> 47 | BC23: ='08_PREMISSAS'!P23 -> 52 | BD23: ='08_PREMISSAS'!Q23 -> 35 | BE23: ='08_PREMISSAS'!R23 -> 0.085 | BF23: ='08_PREMISSAS'!S23 -> 0.34 | BG23: ='08_PREMISSAS'!T23 -> 0.012 | BH23: ='08_PREMISSAS'!U23 -> 0.01 | BI23: =IFERROR('12_MODELO'!N23/'12_MODELO'!E23,0) -> 0.073197605 | BJ23: =IFERROR('12_MODELO'!T23/'12_MODELO'!E23,0) -> 0.032973633 | BK23: ='12_MODELO'!AQ23+'12_MODELO'!AR23 -> 651020.16 | BL23: ='12_MODELO'!U23+'12_MODELO'!V23-'12_MODELO'!X23-'12_MODELO'!Y23-'12_MODELO'!Z23-'12_MODELO'!AA23 -> 2862755.6 | BM23: ='12_MODELO'!AG23-'12_MODELO'!AV23 -> -456533.91 | BN23: =MAX(ABS('15_CONCILIACAO'!F254),ABS('15_CONCILIACAO'!F255),ABS('15_CONCILIACAO'!F256),ABS('15_CONCILIACAO'!F257),ABS('15_CONCILIACAO'!F258),ABS('15_CONCILIACAO'!F259),ABS('15_CONCILIACAO'!F260),ABS('15_CONCILIACAO'!F261),ABS('15_CONCILIACAO'!F262),ABS('15_CONCILIACAO'!F263),ABS('15_CONCILIACAO'!F264),ABS('15_CONCILIACAO'!F265)) -> 3.259629e-09 | BO23: ='12_MODELO'!AV23+'12_MODELO'!U23+'12_MODELO'!V23 -> 5494296.4 | BP23: ='12_MODELO'!AC23-'12_MODELO'!AD23 -> 1678020 | BQ23: =MIN('12_MODELO'!AG23,'12_MODELO'!AF23*12) -> 216000 | BR23: ='12_MODELO'!AG23-'12_MODELO'!BQ23 -> 538000 | BS23: ='12_MODELO'!AX23-'12_MODELO'!BR23 -> 1637006.9 | BT23: ='12_MODELO'!BR23 -> 538000 | BU23: =IFERROR('12_MODELO'!BO23/'12_MODELO'!BS23,0) -> 3.3563063
A24: 45962 | B24: Realizado | C24: =SUMIFS('09_VENDAS'!I$2:I$433,'09_VENDAS'!A$2:A$433,'12_MODELO'!A24) -> 1824414.7 | D24: ='12_MODELO'!C24*'12_MODELO'!BE24 -> 155075.25 | E24: ='12_MODELO'!C24-'12_MODELO'!D24 -> 1669339.5 | F24: =SUMIFS('09_VENDAS'!J$2:J$433,'09_VENDAS'!A$2:A$433,'12_MODELO'!A24) -> 1249236.5 | G24: ='12_MODELO'!E24-'12_MODELO'!F24 -> 420102.95 | H24: =SUMIFS('10_DESPESAS'!D$2:D$123,'10_DESPESAS'!A$2:A$123,'12_MODELO'!A24,'10_DESPESAS'!B$2:B$123,"Pessoal") -> 110162 | I24: =SUMIFS('10_DESPESAS'!D$2:D$123,'10_DESPESAS'!A$2:A$123,'12_MODELO'!A24,'10_DESPESAS'!B$2:B$123,"Comercial") -> 65678.93 | J24: =SUMIFS('10_DESPESAS'!D$2:D$123,'10_DESPESAS'!A$2:A$123,'12_MODELO'!A24,'10_DESPESAS'!B$2:B$123,"Administrativo") -> 33920 | K24: =SUMIFS('10_DESPESAS'!D$2:D$123,'10_DESPESAS'!A$2:A$123,'12_MODELO'!A24,'10_DESPESAS'!B$2:B$123,"Tecnologia") -> 20160 | L24: =SUMIFS('10_DESPESAS'!D$2:D$123,'10_DESPESAS'!A$2:A$123,'12_MODELO'!A24,'10_DESPESAS'!B$2:B$123,"Operações") -> 40137.12 | M24: =SUM('12_MODELO'!H24:'12_MODELO'!L24) -> 270058.05 | N24: ='12_MODELO'!G24-'12_MODELO'!M24 -> 150044.9 | O24: =MIN('12_MODELO'!AC23*'12_MODELO'!BH24,'12_MODELO'!AC23-'12_MODELO'!AD23+'12_MODELO'!AB24) -> 24000 | P24: ='12_MODELO'!N24-'12_MODELO'!O24 -> 126044.9 | Q24: ='12_MODELO'!AG23*'12_MODELO'!BG24 -> 9048 | R24: ='12_MODELO'!P24-'12_MODELO'!Q24 -> 116996.9 | S24: =MAX(0,'12_MODELO'!R24)*'12_MODELO'!BF24 -> 39778.946 | T24: ='12_MODELO'!R24-'12_MODELO'!S24 -> 77217.953 | U24: ='12_MODELO'!C24*'12_MODELO'!BB24/30 -> 2858249.7 | V24: ='12_MODELO'!F24*'12_MODELO'!BC24/30 -> 2165343.3 | W24: ='12_MODELO'!F24+'12_MODELO'!V24-'12_MODELO'!V23 -> 1568533.3 | X24: ='12_MODELO'!F24*'12_MODELO'!BD24/30 -> 1457442.6 | Y24: ='12_MODELO'!H24*20% -> 22032.4 | Z24: ='12_MODELO'!D24 -> 155075.25 | AA24: ='12_MODELO'!S24 -> 39778.946 | AB24: ='08_PREMISSAS'!V24 -> 18000 | AC24: ='12_MODELO'!AC23+'12_MODELO'!AB24 -> 2418000 | AD24: ='12_MODELO'!AD23+'12_MODELO'!O24 -> 745980 | AE24: ='08_PREMISSAS'!W24 -> 0 | AF24: ='08_PREMISSAS'!X24 -> 18000 | AG24: ='12_MODELO'!AG23+'12_MODELO'!AE24-'12_MODELO'!AF24 -> 736000 | AH24: ='08_PREMISSAS'!Y24 -> 0 | AI24: ='12_MODELO'!AI23 -> 3900000 | AJ24: ='12_MODELO'!AJ23+'12_MODELO'!T24-'12_MODELO'!AH24 -> 1174527.5 | AK24: ='12_MODELO'!U23+'12_MODELO'!C24-'12_MODELO'!U24 -> 1403880.9 | AL24: ='12_MODELO'!X23+'12_MODELO'!W24-'12_MODELO'!X24 -> 1353622 | AM24: ='12_MODELO'!M24+'12_MODELO'!Y23-'12_MODELO'!Y24 -> 270058.05 | AN24: ='12_MODELO'!Z23+'12_MODELO'!D24-'12_MODELO'!Z24 -> 132259.06 | AO24: ='12_MODELO'!AA23+'12_MODELO'!S24-'12_MODELO'!AA24 -> 24184.069 | AP24: ='12_MODELO'!AK24-'12_MODELO'!AL24-'12_MODELO'!AM24-'12_MODELO'!AN24-'12_MODELO'!Q24-'12_MODELO'!AO24 -> -385290.25 | AQ24: ='12_MODELO'!T24+'12_MODELO'!O24-('12_MODELO'!U24-'12_MODELO'!U23)-('12_MODELO'!V24-'12_MODELO'!V23)+('12_MODELO'!X24-'12_MODELO'!X23)+('12_MODELO'!Y24-'12_MODELO'!Y23)+('12_MODELO'!Z24-'12_MODELO'!Z23)+('12_MODELO'!AA24-'12_MODELO'!AA23) -> -385290.25 | AR24: =-'12_MODELO'!AB24 -> -18000 | AS24: ='12_MODELO'!AE24-'12_MODELO'!AF24-'12_MODELO'!AH24 -> -18000 | AT24: ='12_MODELO'!AQ24+'12_MODELO'!AR24+'12_MODELO'!AS24 -> -421290.25 | AU24: ='12_MODELO'!AV23 -> 1210533.9 | AV24: ='12_MODELO'!AU24+'12_MODELO'!AT24 -> 789243.66 | AW24: ='12_MODELO'!AV24+'12_MODELO'!U24+'12_MODELO'!V24+'12_MODELO'!AC24-'12_MODELO'!AD24 -> 7484856.7 | AX24: ='12_MODELO'!X24+'12_MODELO'!Y24+'12_MODELO'!Z24+'12_MODELO'!AA24+'12_MODELO'!AG24 -> 2410329.2 | AY24: ='12_MODELO'!AI24+'12_MODELO'!AJ24 -> 5074527.5 | AZ24: ='12_MODELO'!AW24-'12_MODELO'!AX24-'12_MODELO'!AY24 -> 0 | BA24: ='12_MODELO'!AP24-'12_MODELO'!AQ24 -> 2.3283064e-10 | BB24: ='08_PREMISSAS'!O24 -> 47 | BC24: ='08_PREMISSAS'!P24 -> 52 | BD24: ='08_PREMISSAS'!Q24 -> 35 | BE24: ='08_PREMISSAS'!R24 -> 0.085 | BF24: ='08_PREMISSAS'!S24 -> 0.34 | BG24: ='08_PREMISSAS'!T24 -> 0.012 | BH24: ='08_PREMISSAS'!U24 -> 0.01 | BI24: =IFERROR('12_MODELO'!N24/'12_MODELO'!E24,0) -> 0.089882796 | BJ24: =IFERROR('12_MODELO'!T24/'12_MODELO'!E24,0) -> 0.046256591 | BK24: ='12_MODELO'!AQ24+'12_MODELO'!AR24 -> -403290.25 | BL24: ='12_MODELO'!U24+'12_MODELO'!V24-'12_MODELO'!X24-'12_MODELO'!Y24-'12_MODELO'!Z24-'12_MODELO'!AA24 -> 3349263.8 | BM24: ='12_MODELO'!AG24-'12_MODELO'!AV24 -> -53243.664 | BN24: =MAX(ABS('15_CONCILIACAO'!F266),ABS('15_CONCILIACAO'!F267),ABS('15_CONCILIACAO'!F268),ABS('15_CONCILIACAO'!F269),ABS('15_CONCILIACAO'!F270),ABS('15_CONCILIACAO'!F271),ABS('15_CONCILIACAO'!F272),ABS('15_CONCILIACAO'!F273),ABS('15_CONCILIACAO'!F274),ABS('15_CONCILIACAO'!F275),ABS('15_CONCILIACAO'!F276),ABS('15_CONCILIACAO'!F277)) -> 3.4924597e-09 | BO24: ='12_MODELO'!AV24+'12_MODELO'!U24+'12_MODELO'!V24 -> 5812836.7 | BP24: ='12_MODELO'!AC24-'12_MODELO'!AD24 -> 1672020 | BQ24: =MIN('12_MODELO'!AG24,'12_MODELO'!AF24*12) -> 216000 | BR24: ='12_MODELO'!AG24-'12_MODELO'!BQ24 -> 520000 | BS24: ='12_MODELO'!AX24-'12_MODELO'!BR24 -> 1890329.2 | BT24: ='12_MODELO'!BR24 -> 520000 | BU24: =IFERROR('12_MODELO'!BO24/'12_MODELO'!BS24,0) -> 3.0750394
A25: 45992 | B25: Realizado | C25: =SUMIFS('09_VENDAS'!I$2:I$433,'09_VENDAS'!A$2:A$433,'12_MODELO'!A25) -> 1695124.1 | D25: ='12_MODELO'!C25*'12_MODELO'!BE25 -> 144085.55 | E25: ='12_MODELO'!C25-'12_MODELO'!D25 -> 1551038.5 | F25: =SUMIFS('09_VENDAS'!J$2:J$433,'09_VENDAS'!A$2:A$433,'12_MODELO'!A25) -> 1161908.2 | G25: ='12_MODELO'!E25-'12_MODELO'!F25 -> 389130.37 | H25: =SUMIFS('10_DESPESAS'!D$2:D$123,'10_DESPESAS'!A$2:A$123,'12_MODELO'!A25,'10_DESPESAS'!B$2:B$123,"Pessoal") -> 110162 | I25: =SUMIFS('10_DESPESAS'!D$2:D$123,'10_DESPESAS'!A$2:A$123,'12_MODELO'!A25,'10_DESPESAS'!B$2:B$123,"Comercial") -> 61024.47 | J25: =SUMIFS('10_DESPESAS'!D$2:D$123,'10_DESPESAS'!A$2:A$123,'12_MODELO'!A25,'10_DESPESAS'!B$2:B$123,"Administrativo") -> 33920 | K25: =SUMIFS('10_DESPESAS'!D$2:D$123,'10_DESPESAS'!A$2:A$123,'12_MODELO'!A25,'10_DESPESAS'!B$2:B$123,"Tecnologia") -> 20160 | L25: =SUMIFS('10_DESPESAS'!D$2:D$123,'10_DESPESAS'!A$2:A$123,'12_MODELO'!A25,'10_DESPESAS'!B$2:B$123,"Operações") -> 37292.73 | M25: =SUM('12_MODELO'!H25:'12_MODELO'!L25) -> 262559.2 | N25: ='12_MODELO'!G25-'12_MODELO'!M25 -> 126571.17 | O25: =MIN('12_MODELO'!AC24*'12_MODELO'!BH25,'12_MODELO'!AC24-'12_MODELO'!AD24+'12_MODELO'!AB25) -> 24180 | P25: ='12_MODELO'!N25-'12_MODELO'!O25 -> 102391.17 | Q25: ='12_MODELO'!AG24*'12_MODELO'!BG25 -> 8832 | R25: ='12_MODELO'!P25-'12_MODELO'!Q25 -> 93559.173 | S25: =MAX(0,'12_MODELO'!R25)*'12_MODELO'!BF25 -> 31810.119 | T25: ='12_MODELO'!R25-'12_MODELO'!S25 -> 61749.054 | U25: ='12_MODELO'!C25*'12_MODELO'!BB25/30 -> 2655694.4 | V25: ='12_MODELO'!F25*'12_MODELO'!BC25/30 -> 2013974.1 | W25: ='12_MODELO'!F25+'12_MODELO'!V25-'12_MODELO'!V24 -> 1010539 | X25: ='12_MODELO'!F25*'12_MODELO'!BD25/30 -> 1355559.5 | Y25: ='12_MODELO'!H25*20% -> 22032.4 | Z25: ='12_MODELO'!D25 -> 144085.55 | AA25: ='12_MODELO'!S25 -> 31810.119 | AB25: ='08_PREMISSAS'!V25 -> 90000 | AC25: ='12_MODELO'!AC24+'12_MODELO'!AB25 -> 2508000 | AD25: ='12_MODELO'!AD24+'12_MODELO'!O25 -> 770160 | AE25: ='08_PREMISSAS'!W25 -> 0 | AF25: ='08_PREMISSAS'!X25 -> 18000 | AG25: ='12_MODELO'!AG24+'12_MODELO'!AE25-'12_MODELO'!AF25 -> 718000 | AH25: ='08_PREMISSAS'!Y25 -> 0 | AI25: ='12_MODELO'!AI24 -> 3900000 | AJ25: ='12_MODELO'!AJ24+'12_MODELO'!T25-'12_MODELO'!AH25 -> 1236276.5 | AK25: ='12_MODELO'!U24+'12_MODELO'!C25-'12_MODELO'!U25 -> 1897679.4 | AL25: ='12_MODELO'!X24+'12_MODELO'!W25-'12_MODELO'!X25 -> 1112422.1 | AM25: ='12_MODELO'!M25+'12_MODELO'!Y24-'12_MODELO'!Y25 -> 262559.2 | AN25: ='12_MODELO'!Z24+'12_MODELO'!D25-'12_MODELO'!Z25 -> 155075.25 | AO25: ='12_MODELO'!AA24+'12_MODELO'!S25-'12_MODELO'!AA25 -> 39778.946 | AP25: ='12_MODELO'!AK25-'12_MODELO'!AL25-'12_MODELO'!AM25-'12_MODELO'!AN25-'12_MODELO'!Q25-'12_MODELO'!AO25 -> 319011.93 | AQ25: ='12_MODELO'!T25+'12_MODELO'!O25-('12_MODELO'!U25-'12_MODELO'!U24)-('12_MODELO'!V25-'12_MODELO'!V24)+('12_MODELO'!X25-'12_MODELO'!X24)+('12_MODELO'!Y25-'12_MODELO'!Y24)+('12_MODELO'!Z25-'12_MODELO'!Z24)+('12_MODELO'!AA25-'12_MODELO'!AA24) -> 319011.93 | AR25: =-'12_MODELO'!AB25 -> -90000 | AS25: ='12_MODELO'!AE25-'12_MODELO'!AF25-'12_MODELO'!AH25 -> -18000 | AT25: ='12_MODELO'!AQ25+'12_MODELO'!AR25+'12_MODELO'!AS25 -> 211011.93 | AU25: ='12_MODELO'!AV24 -> 789243.66 | AV25: ='12_MODELO'!AU25+'12_MODELO'!AT25 -> 1000255.6 | AW25: ='12_MODELO'!AV25+'12_MODELO'!U25+'12_MODELO'!V25+'12_MODELO'!AC25-'12_MODELO'!AD25 -> 7407764.1 | AX25: ='12_MODELO'!X25+'12_MODELO'!Y25+'12_MODELO'!Z25+'12_MODELO'!AA25+'12_MODELO'!AG25 -> 2271487.6 | AY25: ='12_MODELO'!AI25+'12_MODELO'!AJ25 -> 5136276.5 | AZ25: ='12_MODELO'!AW25-'12_MODELO'!AX25-'12_MODELO'!AY25 -> 9.3132257e-10 | BA25: ='12_MODELO'!AP25-'12_MODELO'!AQ25 -> 5.8207661e-10 | BB25: ='08_PREMISSAS'!O25 -> 47 | BC25: ='08_PREMISSAS'!P25 -> 52 | BD25: ='08_PREMISSAS'!Q25 -> 35 | BE25: ='08_PREMISSAS'!R25 -> 0.085 | BF25: ='08_PREMISSAS'!S25 -> 0.34 | BG25: ='08_PREMISSAS'!T25 -> 0.012 | BH25: ='08_PREMISSAS'!U25 -> 0.01 | BI25: =IFERROR('12_MODELO'!N25/'12_MODELO'!E25,0) -> 0.081604145 | BJ25: =IFERROR('12_MODELO'!T25/'12_MODELO'!E25,0) -> 0.039811425 | BK25: ='12_MODELO'!AQ25+'12_MODELO'!AR25 -> 229011.93 | BL25: ='12_MODELO'!U25+'12_MODELO'!V25-'12_MODELO'!X25-'12_MODELO'!Y25-'12_MODELO'!Z25-'12_MODELO'!AA25 -> 3116181 | BM25: ='12_MODELO'!AG25-'12_MODELO'!AV25 -> -282255.59 | BN25: =MAX(ABS('15_CONCILIACAO'!F278),ABS('15_CONCILIACAO'!F279),ABS('15_CONCILIACAO'!F280),ABS('15_CONCILIACAO'!F281),ABS('15_CONCILIACAO'!F282),ABS('15_CONCILIACAO'!F283),ABS('15_CONCILIACAO'!F284),ABS('15_CONCILIACAO'!F285),ABS('15_CONCILIACAO'!F286),ABS('15_CONCILIACAO'!F287),ABS('15_CONCILIACAO'!F288),ABS('15_CONCILIACAO'!F289)) -> 4.1909516e-09 | BO25: ='12_MODELO'!AV25+'12_MODELO'!U25+'12_MODELO'!V25 -> 5669924.1 | BP25: ='12_MODELO'!AC25-'12_MODELO'!AD25 -> 1737840 | BQ25: =MIN('12_MODELO'!AG25,'12_MODELO'!AF25*12) -> 216000 | BR25: ='12_MODELO'!AG25-'12_MODELO'!BQ25 -> 502000 | BS25: ='12_MODELO'!AX25-'12_MODELO'!BR25 -> 1769487.6 | BT25: ='12_MODELO'!BR25 -> 502000 | BU25: =IFERROR('12_MODELO'!BO25/'12_MODELO'!BS25,0) -> 3.2042746
A26: 45292 | B26: Orçamento | C26: ='08_PREMISSAS'!C26*'08_PREMISSAS'!D26 -> 888000 | D26: ='12_MODELO'!C26*'12_MODELO'!BE26 -> 75480 | E26: ='12_MODELO'!C26-'12_MODELO'!D26 -> 812520 | F26: ='12_MODELO'!C26*'08_PREMISSAS'!E26 -> 578088 | G26: ='12_MODELO'!E26-'12_MODELO'!F26 -> 234432 | H26: ='08_PREMISSAS'!J26 -> 95000 | I26: ='12_MODELO'!C26*'08_PREMISSAS'!F26 -> 30192 | J26: ='08_PREMISSAS'!L26 -> 33000 | K26: ='08_PREMISSAS'!M26 -> 19000 | L26: ='12_MODELO'!C26*'08_PREMISSAS'!G26 -> 18648 | M26: =SUM('12_MODELO'!H26:'12_MODELO'!L26) -> 195840 | N26: ='12_MODELO'!G26-'12_MODELO'!M26 -> 38592 | O26: =MIN('11_SALDO_INICIAL'!B9*'12_MODELO'!BH26,'11_SALDO_INICIAL'!B9-'11_SALDO_INICIAL'!B10+'12_MODELO'!AB26) -> 15000 | P26: ='12_MODELO'!N26-'12_MODELO'!O26 -> 23592 | Q26: ='11_SALDO_INICIAL'!B11*'12_MODELO'!BG26 -> 9600 | R26: ='12_MODELO'!P26-'12_MODELO'!Q26 -> 13992 | S26: =MAX(0,'12_MODELO'!R26)*'12_MODELO'!BF26 -> 4757.28 | T26: ='12_MODELO'!R26-'12_MODELO'!S26 -> 9234.72 | U26: ='12_MODELO'!C26*'12_MODELO'!BB26/30 -> 1184000 | V26: ='12_MODELO'!F26*'12_MODELO'!BC26/30 -> 867132 | W26: ='12_MODELO'!F26+'12_MODELO'!V26-'11_SALDO_INICIAL'!B4 -> 745220 | X26: ='12_MODELO'!F26*'12_MODELO'!BD26/30 -> 693705.6 | Y26: ='12_MODELO'!H26*20% -> 19000 | Z26: ='12_MODELO'!D26 -> 75480 | AA26: ='12_MODELO'!S26 -> 4757.28 | AB26: ='08_PREMISSAS'!V26 -> 18000 | AC26: ='11_SALDO_INICIAL'!B9+'12_MODELO'!AB26 -> 1518000 | AD26: ='11_SALDO_INICIAL'!B10+'12_MODELO'!O26 -> 315000 | AE26: ='08_PREMISSAS'!W26 -> 0 | AF26: ='08_PREMISSAS'!X26 -> 18000 | AG26: ='11_SALDO_INICIAL'!B11+'12_MODELO'!AE26-'12_MODELO'!AF26 -> 782000 | AH26: ='08_PREMISSAS'!Y26 -> 0 | AI26: ='11_SALDO_INICIAL'!B12 -> 3900000 | AJ26: ='11_SALDO_INICIAL'!B13+'12_MODELO'!T26-'12_MODELO'!AH26 -> 389234.72 | AK26: ='11_SALDO_INICIAL'!B3+'12_MODELO'!C26-'12_MODELO'!U26 -> 604000 | AL26: ='11_SALDO_INICIAL'!B5+'12_MODELO'!W26-'12_MODELO'!X26 -> 601514.4 | AM26: ='12_MODELO'!M26+'11_SALDO_INICIAL'!B6-'12_MODELO'!Y26 -> 216840 | AN26: ='11_SALDO_INICIAL'!B7+'12_MODELO'!D26-'12_MODELO'!Z26 -> 80000 | AO26: ='11_SALDO_INICIAL'!B8+'12_MODELO'!S26-'12_MODELO'!AA26 -> 50000 | AP26: ='12_MODELO'!AK26-'12_MODELO'!AL26-'12_MODELO'!AM26-'12_MODELO'!AN26-'12_MODELO'!Q26-'12_MODELO'!AO26 -> -353954.4 | AQ26: ='12_MODELO'!T26+'12_MODELO'!O26-('12_MODELO'!U26-'11_SALDO_INICIAL'!B3)-('12_MODELO'!V26-'11_SALDO_INICIAL'!B4)+('12_MODELO'!X26-'11_SALDO_INICIAL'!B5)+('12_MODELO'!Y26-'11_SALDO_INICIAL'!B6)+('12_MODELO'!Z26-'11_SALDO_INICIAL'!B7)+('12_MODELO'!AA26-'11_SALDO_INICIAL'!B8) -> -353954.4 | AR26: =-'12_MODELO'!AB26 -> -18000 | AS26: ='12_MODELO'!AE26-'12_MODELO'!AF26-'12_MODELO'!AH26 -> -18000 | AT26: ='12_MODELO'!AQ26+'12_MODELO'!AR26+'12_MODELO'!AS26 -> -389954.4 | AU26: ='11_SALDO_INICIAL'!B2 -> 3000000 | AV26: ='12_MODELO'!AU26+'12_MODELO'!AT26 -> 2610045.6 | AW26: ='12_MODELO'!AV26+'12_MODELO'!U26+'12_MODELO'!V26+'12_MODELO'!AC26-'12_MODELO'!AD26 -> 5864177.6 | AX26: ='12_MODELO'!X26+'12_MODELO'!Y26+'12_MODELO'!Z26+'12_MODELO'!AA26+'12_MODELO'!AG26 -> 1574942.9 | AY26: ='12_MODELO'!AI26+'12_MODELO'!AJ26 -> 4289234.7 | AZ26: ='12_MODELO'!AW26-'12_MODELO'!AX26-'12_MODELO'!AY26 -> 0 | BA26: ='12_MODELO'!AP26-'12_MODELO'!AQ26 -> 0 | BB26: ='08_PREMISSAS'!O26 -> 40 | BC26: ='08_PREMISSAS'!P26 -> 45 | BD26: ='08_PREMISSAS'!Q26 -> 36 | BE26: ='08_PREMISSAS'!R26 -> 0.085 | BF26: ='08_PREMISSAS'!S26 -> 0.34 | BG26: ='08_PREMISSAS'!T26 -> 0.012 | BH26: ='08_PREMISSAS'!U26 -> 0.01 | BI26: =IFERROR('12_MODELO'!N26/'12_MODELO'!E26,0) -> 0.047496677 | BJ26: =IFERROR('12_MODELO'!T26/'12_MODELO'!E26,0) -> 0.011365529 | BK26: ='12_MODELO'!AQ26+'12_MODELO'!AR26 -> -371954.4 | BL26: ='12_MODELO'!U26+'12_MODELO'!V26-'12_MODELO'!X26-'12_MODELO'!Y26-'12_MODELO'!Z26-'12_MODELO'!AA26 -> 1258189.1 | BM26: ='12_MODELO'!AG26-'12_MODELO'!AV26 -> -1828045.6 | BN26: =0 -> 0 | BO26: ='12_MODELO'!AV26+'12_MODELO'!U26+'12_MODELO'!V26 -> 4661177.6 | BP26: ='12_MODELO'!AC26-'12_MODELO'!AD26 -> 1203000 | BQ26: =MIN('12_MODELO'!AG26,'12_MODELO'!AF26*12) -> 216000 | BR26: ='12_MODELO'!AG26-'12_MODELO'!BQ26 -> 566000 | BS26: ='12_MODELO'!AX26-'12_MODELO'!BR26 -> 1008942.9 | BT26: ='12_MODELO'!BR26 -> 566000 | BU26: =IFERROR('12_MODELO'!BO26/'12_MODELO'!BS26,0) -> 4.6198627
A27: 45323 | B27: Orçamento | C27: ='08_PREMISSAS'!C27*'08_PREMISSAS'!D27 -> 921300 | D27: ='12_MODELO'!C27*'12_MODELO'!BE27 -> 78310.5 | E27: ='12_MODELO'!C27-'12_MODELO'!D27 -> 842989.5 | F27: ='12_MODELO'!C27*'08_PREMISSAS'!E27 -> 599766.3 | G27: ='12_MODELO'!E27-'12_MODELO'!F27 -> 243223.2 | H27: ='08_PREMISSAS'!J27 -> 95000 | I27: ='12_MODELO'!C27*'08_PREMISSAS'!F27 -> 31324.2 | J27: ='08_PREMISSAS'!L27 -> 33000 | K27: ='08_PREMISSAS'!M27 -> 19000 | L27: ='12_MODELO'!C27*'08_PREMISSAS'!G27 -> 19347.3 | M27: =SUM('12_MODELO'!H27:'12_MODELO'!L27) -> 197671.5 | N27: ='12_MODELO'!G27-'12_MODELO'!M27 -> 45551.7 | O27: =MIN('12_MODELO'!AC26*'12_MODELO'!BH27,'12_MODELO'!AC26-'12_MODELO'!AD26+'12_MODELO'!AB27) -> 15180 | P27: ='12_MODELO'!N27-'12_MODELO'!O27 -> 30371.7 | Q27: ='12_MODELO'!AG26*'12_MODELO'!BG27 -> 9384 | R27: ='12_MODELO'!P27-'12_MODELO'!Q27 -> 20987.7 | S27: =MAX(0,'12_MODELO'!R27)*'12_MODELO'!BF27 -> 7135.818 | T27: ='12_MODELO'!R27-'12_MODELO'!S27 -> 13851.882 | U27: ='12_MODELO'!C27*'12_MODELO'!BB27/30 -> 1228400 | V27: ='12_MODELO'!F27*'12_MODELO'!BC27/30 -> 899649.45 | W27: ='12_MODELO'!F27+'12_MODELO'!V27-'12_MODELO'!V26 -> 632283.75 | X27: ='12_MODELO'!F27*'12_MODELO'!BD27/30 -> 719719.56 | Y27: ='12_MODELO'!H27*20% -> 19000 | Z27: ='12_MODELO'!D27 -> 78310.5 | AA27: ='12_MODELO'!S27 -> 7135.818 | AB27: ='08_PREMISSAS'!V27 -> 18000 | AC27: ='12_MODELO'!AC26+'12_MODELO'!AB27 -> 1536000 | AD27: ='12_MODELO'!AD26+'12_MODELO'!O27 -> 330180 | AE27: ='08_PREMISSAS'!W27 -> 0 | AF27: ='08_PREMISSAS'!X27 -> 18000 | AG27: ='12_MODELO'!AG26+'12_MODELO'!AE27-'12_MODELO'!AF27 -> 764000 | AH27: ='08_PREMISSAS'!Y27 -> 0 | AI27: ='12_MODELO'!AI26 -> 3900000 | AJ27: ='12_MODELO'!AJ26+'12_MODELO'!T27-'12_MODELO'!AH27 -> 403086.6 | AK27: ='12_MODELO'!U26+'12_MODELO'!C27-'12_MODELO'!U27 -> 876900 | AL27: ='12_MODELO'!X26+'12_MODELO'!W27-'12_MODELO'!X27 -> 606269.79 | AM27: ='12_MODELO'!M27+'12_MODELO'!Y26-'12_MODELO'!Y27 -> 197671.5 | AN27: ='12_MODELO'!Z26+'12_MODELO'!D27-'12_MODELO'!Z27 -> 75480 | AO27: ='12_MODELO'!AA26+'12_MODELO'!S27-'12_MODELO'!AA27 -> 4757.28 | AP27: ='12_MODELO'!AK27-'12_MODELO'!AL27-'12_MODELO'!AM27-'12_MODELO'!AN27-'12_MODELO'!Q27-'12_MODELO'!AO27 -> -16662.57 | AQ27: ='12_MODELO'!T27+'12_MODELO'!O27-('12_MODELO'!U27-'12_MODELO'!U26)-('12_MODELO'!V27-'12_MODELO'!V26)+('12_MODELO'!X27-'12_MODELO'!X26)+('12_MODELO'!Y27-'12_MODELO'!Y26)+('12_MODELO'!Z27-'12_MODELO'!Z26)+('12_MODELO'!AA27-'12_MODELO'!AA26) -> -16662.57 | AR27: =-'12_MODELO'!AB27 -> -18000 | AS27: ='12_MODELO'!AE27-'12_MODELO'!AF27-'12_MODELO'!AH27 -> -18000 | AT27: ='12_MODELO'!AQ27+'12_MODELO'!AR27+'12_MODELO'!AS27 -> -52662.57 | AU27: ='12_MODELO'!AV26 -> 2610045.6 | AV27: ='12_MODELO'!AU27+'12_MODELO'!AT27 -> 2557383 | AW27: ='12_MODELO'!AV27+'12_MODELO'!U27+'12_MODELO'!V27+'12_MODELO'!AC27-'12_MODELO'!AD27 -> 5891252.5 | AX27: ='12_MODELO'!X27+'12_MODELO'!Y27+'12_MODELO'!Z27+'12_MODELO'!AA27+'12_MODELO'!AG27 -> 1588165.9 | AY27: ='12_MODELO'!AI27+'12_MODELO'!AJ27 -> 4303086.6 | AZ27: ='12_MODELO'!AW27-'12_MODELO'!AX27-'12_MODELO'!AY27 -> 0 | BA27: ='12_MODELO'!AP27-'12_MODELO'!AQ27 -> 0 | BB27: ='08_PREMISSAS'!O27 -> 40 | BC27: ='08_PREMISSAS'!P27 -> 45 | BD27: ='08_PREMISSAS'!Q27 -> 36 | BE27: ='08_PREMISSAS'!R27 -> 0.085 | BF27: ='08_PREMISSAS'!S27 -> 0.34 | BG27: ='08_PREMISSAS'!T27 -> 0.012 | BH27: ='08_PREMISSAS'!U27 -> 0.01 | BI27: =IFERROR('12_MODELO'!N27/'12_MODELO'!E27,0) -> 0.054035904 | BJ27: =IFERROR('12_MODELO'!T27/'12_MODELO'!E27,0) -> 0.016431856 | BK27: ='12_MODELO'!AQ27+'12_MODELO'!AR27 -> -34662.57 | BL27: ='12_MODELO'!U27+'12_MODELO'!V27-'12_MODELO'!X27-'12_MODELO'!Y27-'12_MODELO'!Z27-'12_MODELO'!AA27 -> 1303883.6 | BM27: ='12_MODELO'!AG27-'12_MODELO'!AV27 -> -1793383 | BN27: =0 -> 0 | BO27: ='12_MODELO'!AV27+'12_MODELO'!U27+'12_MODELO'!V27 -> 4685432.5 | BP27: ='12_MODELO'!AC27-'12_MODELO'!AD27 -> 1205820 | BQ27: =MIN('12_MODELO'!AG27,'12_MODELO'!AF27*12) -> 216000 | BR27: ='12_MODELO'!AG27-'12_MODELO'!BQ27 -> 548000 | BS27: ='12_MODELO'!AX27-'12_MODELO'!BR27 -> 1040165.9 | BT27: ='12_MODELO'!BR27 -> 548000 | BU27: =IFERROR('12_MODELO'!BO27/'12_MODELO'!BS27,0) -> 4.5045051
A28: 45352 | B28: Orçamento | C28: ='08_PREMISSAS'!C28*'08_PREMISSAS'!D28 -> 1098900 | D28: ='12_MODELO'!C28*'12_MODELO'!BE28 -> 93406.5 | E28: ='12_MODELO'!C28-'12_MODELO'!D28 -> 1005493.5 | F28: ='12_MODELO'!C28*'08_PREMISSAS'!E28 -> 715383.9 | G28: ='12_MODELO'!E28-'12_MODELO'!F28 -> 290109.6 | H28: ='08_PREMISSAS'!J28 -> 95000 | I28: ='12_MODELO'!C28*'08_PREMISSAS'!F28 -> 37362.6 | J28: ='08_PREMISSAS'!L28 -> 33000 | K28: ='08_PREMISSAS'!M28 -> 19000 | L28: ='12_MODELO'!C28*'08_PREMISSAS'!G28 -> 23076.9 | M28: =SUM('12_MODELO'!H28:'12_MODELO'!L28) -> 207439.5 | N28: ='12_MODELO'!G28-'12_MODELO'!M28 -> 82670.1 | O28: =MIN('12_MODELO'!AC27*'12_MODELO'!BH28,'12_MODELO'!AC27-'12_MODELO'!AD27+'12_MODELO'!AB28) -> 15360 | P28: ='12_MODELO'!N28-'12_MODELO'!O28 -> 67310.1 | Q28: ='12_MODELO'!AG27*'12_MODELO'!BG28 -> 9168 | R28: ='12_MODELO'!P28-'12_MODELO'!Q28 -> 58142.1 | S28: =MAX(0,'12_MODELO'!R28)*'12_MODELO'!BF28 -> 19768.314 | T28: ='12_MODELO'!R28-'12_MODELO'!S28 -> 38373.786 | U28: ='12_MODELO'!C28*'12_MODELO'!BB28/30 -> 1465200 | V28: ='12_MODELO'!F28*'12_MODELO'!BC28/30 -> 1073075.9 | W28: ='12_MODELO'!F28+'12_MODELO'!V28-'12_MODELO'!V27 -> 888810.3 | X28: ='12_MODELO'!F28*'12_MODELO'!BD28/30 -> 858460.68 | Y28: ='12_MODELO'!H28*20% -> 19000 | Z28: ='12_MODELO'!D28 -> 93406.5 | AA28: ='12_MODELO'!S28 -> 19768.314 | AB28: ='08_PREMISSAS'!V28 -> 90000 | AC28: ='12_MODELO'!AC27+'12_MODELO'!AB28 -> 1626000 | AD28: ='12_MODELO'!AD27+'12_MODELO'!O28 -> 345540 | AE28: ='08_PREMISSAS'!W28 -> 0 | AF28: ='08_PREMISSAS'!X28 -> 18000 | AG28: ='12_MODELO'!AG27+'12_MODELO'!AE28-'12_MODELO'!AF28 -> 746000 | AH28: ='08_PREMISSAS'!Y28 -> 0 | AI28: ='12_MODELO'!AI27 -> 3900000 | AJ28: ='12_MODELO'!AJ27+'12_MODELO'!T28-'12_MODELO'!AH28 -> 441460.39 | AK28: ='12_MODELO'!U27+'12_MODELO'!C28-'12_MODELO'!U28 -> 862100 | AL28: ='12_MODELO'!X27+'12_MODELO'!W28-'12_MODELO'!X28 -> 750069.18 | AM28: ='12_MODELO'!M28+'12_MODELO'!Y27-'12_MODELO'!Y28 -> 207439.5 | AN28: ='12_MODELO'!Z27+'12_MODELO'!D28-'12_MODELO'!Z28 -> 78310.5 | AO28: ='12_MODELO'!AA27+'12_MODELO'!S28-'12_MODELO'!AA28 -> 7135.818 | AP28: ='12_MODELO'!AK28-'12_MODELO'!AL28-'12_MODELO'!AM28-'12_MODELO'!AN28-'12_MODELO'!Q28-'12_MODELO'!AO28 -> -190023 | AQ28: ='12_MODELO'!T28+'12_MODELO'!O28-('12_MODELO'!U28-'12_MODELO'!U27)-('12_MODELO'!V28-'12_MODELO'!V27)+('12_MODELO'!X28-'12_MODELO'!X27)+('12_MODELO'!Y28-'12_MODELO'!Y27)+('12_MODELO'!Z28-'12_MODELO'!Z27)+('12_MODELO'!AA28-'12_MODELO'!AA27) -> -190023 | AR28: =-'12_MODELO'!AB28 -> -90000 | AS28: ='12_MODELO'!AE28-'12_MODELO'!AF28-'12_MODELO'!AH28 -> -18000 | AT28: ='12_MODELO'!AQ28+'12_MODELO'!AR28+'12_MODELO'!AS28 -> -298023 | AU28: ='12_MODELO'!AV27 -> 2557383 | AV28: ='12_MODELO'!AU28+'12_MODELO'!AT28 -> 2259360 | AW28: ='12_MODELO'!AV28+'12_MODELO'!U28+'12_MODELO'!V28+'12_MODELO'!AC28-'12_MODELO'!AD28 -> 6078095.9 | AX28: ='12_MODELO'!X28+'12_MODELO'!Y28+'12_MODELO'!Z28+'12_MODELO'!AA28+'12_MODELO'!AG28 -> 1736635.5 | AY28: ='12_MODELO'!AI28+'12_MODELO'!AJ28 -> 4341460.4 | AZ28: ='12_MODELO'!AW28-'12_MODELO'!AX28-'12_MODELO'!AY28 -> 0 | BA28: ='12_MODELO'!AP28-'12_MODELO'!AQ28 -> 2.6193447e-10 | BB28: ='08_PREMISSAS'!O28 -> 40 | BC28: ='08_PREMISSAS'!P28 -> 45 | BD28: ='08_PREMISSAS'!Q28 -> 36 | BE28: ='08_PREMISSAS'!R28 -> 0.085 | BF28: ='08_PREMISSAS'!S28 -> 0.34 | BG28: ='08_PREMISSAS'!T28 -> 0.012 | BH28: ='08_PREMISSAS'!U28 -> 0.01 | BI28: =IFERROR('12_MODELO'!N28/'12_MODELO'!E28,0) -> 0.082218433 | BJ28: =IFERROR('12_MODELO'!T28/'12_MODELO'!E28,0) -> 0.038164131 | BK28: ='12_MODELO'!AQ28+'12_MODELO'!AR28 -> -280023 | BL28: ='12_MODELO'!U28+'12_MODELO'!V28-'12_MODELO'!X28-'12_MODELO'!Y28-'12_MODELO'!Z28-'12_MODELO'!AA28 -> 1547640.4 | BM28: ='12_MODELO'!AG28-'12_MODELO'!AV28 -> -1513360 | BN28: =0 -> 0 | BO28: ='12_MODELO'!AV28+'12_MODELO'!U28+'12_MODELO'!V28 -> 4797635.9 | BP28: ='12_MODELO'!AC28-'12_MODELO'!AD28 -> 1280460 | BQ28: =MIN('12_MODELO'!AG28,'12_MODELO'!AF28*12) -> 216000 | BR28: ='12_MODELO'!AG28-'12_MODELO'!BQ28 -> 530000 | BS28: ='12_MODELO'!AX28-'12_MODELO'!BR28 -> 1206635.5 | BT28: ='12_MODELO'!BR28 -> 530000 | BU28: =IFERROR('12_MODELO'!BO28/'12_MODELO'!BS28,0) -> 3.9760441
A29: 45383 | B29: Orçamento | C29: ='08_PREMISSAS'!C29*'08_PREMISSAS'!D29 -> 1076700 | D29: ='12_MODELO'!C29*'12_MODELO'!BE29 -> 91519.5 | E29: ='12_MODELO'!C29-'12_MODELO'!D29 -> 985180.5 | F29: ='12_MODELO'!C29*'08_PREMISSAS'!E29 -> 700931.7 | G29: ='12_MODELO'!E29-'12_MODELO'!F29 -> 284248.8 | H29: ='08_PREMISSAS'!J29 -> 95000 | I29: ='12_MODELO'!C29*'08_PREMISSAS'!F29 -> 36607.8 | J29: ='08_PREMISSAS'!L29 -> 33000 | K29: ='08_PREMISSAS'!M29 -> 19000 | L29: ='12_MODELO'!C29*'08_PREMISSAS'!G29 -> 22610.7 | M29: =SUM('12_MODELO'!H29:'12_MODELO'!L29) -> 206218.5 | N29: ='12_MODELO'!G29-'12_MODELO'!M29 -> 78030.3 | O29: =MIN('12_MODELO'!AC28*'12_MODELO'!BH29,'12_MODELO'!AC28-'12_MODELO'!AD28+'12_MODELO'!AB29) -> 16260 | P29: ='12_MODELO'!N29-'12_MODELO'!O29 -> 61770.3 | Q29: ='12_MODELO'!AG28*'12_MODELO'!BG29 -> 8952 | R29: ='12_MODELO'!P29-'12_MODELO'!Q29 -> 52818.3 | S29: =MAX(0,'12_MODELO'!R29)*'12_MODELO'!BF29 -> 17958.222 | T29: ='12_MODELO'!R29-'12_MODELO'!S29 -> 34860.078 | U29: ='12_MODELO'!C29*'12_MODELO'!BB29/30 -> 1435600 | V29: ='12_MODELO'!F29*'12_MODELO'!BC29/30 -> 1051397.6 | W29: ='12_MODELO'!F29+'12_MODELO'!V29-'12_MODELO'!V28 -> 679253.4 | X29: ='12_MODELO'!F29*'12_MODELO'!BD29/30 -> 841118.04 | Y29: ='12_MODELO'!H29*20% -> 19000 | Z29: ='12_MODELO'!D29 -> 91519.5 | AA29: ='12_MODELO'!S29 -> 17958.222 | AB29: ='08_PREMISSAS'!V29 -> 18000 | AC29: ='12_MODELO'!AC28+'12_MODELO'!AB29 -> 1644000 | AD29: ='12_MODELO'!AD28+'12_MODELO'!O29 -> 361800 | AE29: ='08_PREMISSAS'!W29 -> 0 | AF29: ='08_PREMISSAS'!X29 -> 18000 | AG29: ='12_MODELO'!AG28+'12_MODELO'!AE29-'12_MODELO'!AF29 -> 728000 | AH29: ='08_PREMISSAS'!Y29 -> 0 | AI29: ='12_MODELO'!AI28 -> 3900000 | AJ29: ='12_MODELO'!AJ28+'12_MODELO'!T29-'12_MODELO'!AH29 -> 476320.47 | AK29: ='12_MODELO'!U28+'12_MODELO'!C29-'12_MODELO'!U29 -> 1106300 | AL29: ='12_MODELO'!X28+'12_MODELO'!W29-'12_MODELO'!X29 -> 696596.04 | AM29: ='12_MODELO'!M29+'12_MODELO'!Y28-'12_MODELO'!Y29 -> 206218.5 | AN29: ='12_MODELO'!Z28+'12_MODELO'!D29-'12_MODELO'!Z29 -> 93406.5 | AO29: ='12_MODELO'!AA28+'12_MODELO'!S29-'12_MODELO'!AA29 -> 19768.314 | AP29: ='12_MODELO'!AK29-'12_MODELO'!AL29-'12_MODELO'!AM29-'12_MODELO'!AN29-'12_MODELO'!Q29-'12_MODELO'!AO29 -> 81358.646 | AQ29: ='12_MODELO'!T29+'12_MODELO'!O29-('12_MODELO'!U29-'12_MODELO'!U28)-('12_MODELO'!V29-'12_MODELO'!V28)+('12_MODELO'!X29-'12_MODELO'!X28)+('12_MODELO'!Y29-'12_MODELO'!Y28)+('12_MODELO'!Z29-'12_MODELO'!Z28)+('12_MODELO'!AA29-'12_MODELO'!AA28) -> 81358.646 | AR29: =-'12_MODELO'!AB29 -> -18000 | AS29: ='12_MODELO'!AE29-'12_MODELO'!AF29-'12_MODELO'!AH29 -> -18000 | AT29: ='12_MODELO'!AQ29+'12_MODELO'!AR29+'12_MODELO'!AS29 -> 45358.646 | AU29: ='12_MODELO'!AV28 -> 2259360 | AV29: ='12_MODELO'!AU29+'12_MODELO'!AT29 -> 2304718.7 | AW29: ='12_MODELO'!AV29+'12_MODELO'!U29+'12_MODELO'!V29+'12_MODELO'!AC29-'12_MODELO'!AD29 -> 6073916.2 | AX29: ='12_MODELO'!X29+'12_MODELO'!Y29+'12_MODELO'!Z29+'12_MODELO'!AA29+'12_MODELO'!AG29 -> 1697595.8 | AY29: ='12_MODELO'!AI29+'12_MODELO'!AJ29 -> 4376320.5 | AZ29: ='12_MODELO'!AW29-'12_MODELO'!AX29-'12_MODELO'!AY29 -> 0 | BA29: ='12_MODELO'!AP29-'12_MODELO'!AQ29 -> 0 | BB29: ='08_PREMISSAS'!O29 -> 40 | BC29: ='08_PREMISSAS'!P29 -> 45 | BD29: ='08_PREMISSAS'!Q29 -> 36 | BE29: ='08_PREMISSAS'!R29 -> 0.085 | BF29: ='08_PREMISSAS'!S29 -> 0.34 | BG29: ='08_PREMISSAS'!T29 -> 0.012 | BH29: ='08_PREMISSAS'!U29 -> 0.01 | BI29: =IFERROR('12_MODELO'!N29/'12_MODELO'!E29,0) -> 0.079204065 | BJ29: =IFERROR('12_MODELO'!T29/'12_MODELO'!E29,0) -> 0.035384458 | BK29: ='12_MODELO'!AQ29+'12_MODELO'!AR29 -> 63358.646 | BL29: ='12_MODELO'!U29+'12_MODELO'!V29-'12_MODELO'!X29-'12_MODELO'!Y29-'12_MODELO'!Z29-'12_MODELO'!AA29 -> 1517401.8 | BM29: ='12_MODELO'!AG29-'12_MODELO'!AV29 -> -1576718.7 | BN29: =0 -> 0 | BO29: ='12_MODELO'!AV29+'12_MODELO'!U29+'12_MODELO'!V29 -> 4791716.2 | BP29: ='12_MODELO'!AC29-'12_MODELO'!AD29 -> 1282200 | BQ29: =MIN('12_MODELO'!AG29,'12_MODELO'!AF29*12) -> 216000 | BR29: ='12_MODELO'!AG29-'12_MODELO'!BQ29 -> 512000 | BS29: ='12_MODELO'!AX29-'12_MODELO'!BR29 -> 1185595.8 | BT29: ='12_MODELO'!BR29 -> 512000 | BU29: =IFERROR('12_MODELO'!BO29/'12_MODELO'!BS29,0) -> 4.0416105
A30: 45413 | B30: Orçamento | C30: ='08_PREMISSAS'!C30*'08_PREMISSAS'!D30 -> 1143300 | D30: ='12_MODELO'!C30*'12_MODELO'!BE30 -> 97180.5 | E30: ='12_MODELO'!C30-'12_MODELO'!D30 -> 1046119.5 | F30: ='12_MODELO'!C30*'08_PREMISSAS'!E30 -> 744288.3 | G30: ='12_MODELO'!E30-'12_MODELO'!F30 -> 301831.2 | H30: ='08_PREMISSAS'!J30 -> 95000 | I30: ='12_MODELO'!C30*'08_PREMISSAS'!F30 -> 38872.2 | J30: ='08_PREMISSAS'!L30 -> 33000 | K30: ='08_PREMISSAS'!M30 -> 19000 | L30: ='12_MODELO'!C30*'08_PREMISSAS'!G30 -> 24009.3 | M30: =SUM('12_MODELO'!H30:'12_MODELO'!L30) -> 209881.5 | N30: ='12_MODELO'!G30-'12_MODELO'!M30 -> 91949.7 | O30: =MIN('12_MODELO'!AC29*'12_MODELO'!BH30,'12_MODELO'!AC29-'12_MODELO'!AD29+'12_MODELO'!AB30) -> 16440 | P30: ='12_MODELO'!N30-'12_MODELO'!O30 -> 75509.7 | Q30: ='12_MODELO'!AG29*'12_MODELO'!BG30 -> 8736 | R30: ='12_MODELO'!P30-'12_MODELO'!Q30 -> 66773.7 | S30: =MAX(0,'12_MODELO'!R30)*'12_MODELO'!BF30 -> 22703.058 | T30: ='12_MODELO'!R30-'12_MODELO'!S30 -> 44070.642 | U30: ='12_MODELO'!C30*'12_MODELO'!BB30/30 -> 1524400 | V30: ='12_MODELO'!F30*'12_MODELO'!BC30/30 -> 1116432.5 | W30: ='12_MODELO'!F30+'12_MODELO'!V30-'12_MODELO'!V29 -> 809323.2 | X30: ='12_MODELO'!F30*'12_MODELO'!BD30/30 -> 893145.96 | Y30: ='12_MODELO'!H30*20% -> 19000 | Z30: ='12_MODELO'!D30 -> 97180.5 | AA30: ='12_MODELO'!S30 -> 22703.058 | AB30: ='08_PREMISSAS'!V30 -> 18000 | AC30: ='12_MODELO'!AC29+'12_MODELO'!AB30 -> 1662000 | AD30: ='12_MODELO'!AD29+'12_MODELO'!O30 -> 378240 | AE30: ='08_PREMISSAS'!W30 -> 0 | AF30: ='08_PREMISSAS'!X30 -> 18000 | AG30: ='12_MODELO'!AG29+'12_MODELO'!AE30-'12_MODELO'!AF30 -> 710000 | AH30: ='08_PREMISSAS'!Y30 -> 0 | AI30: ='12_MODELO'!AI29 -> 3900000 | AJ30: ='12_MODELO'!AJ29+'12_MODELO'!T30-'12_MODELO'!AH30 -> 520391.11 | AK30: ='12_MODELO'!U29+'12_MODELO'!C30-'12_MODELO'!U30 -> 1054500 | AL30: ='12_MODELO'!X29+'12_MODELO'!W30-'12_MODELO'!X30 -> 757295.28 | AM30: ='12_MODELO'!M30+'12_MODELO'!Y29-'12_MODELO'!Y30 -> 209881.5 | AN30: ='12_MODELO'!Z29+'12_MODELO'!D30-'12_MODELO'!Z30 -> 91519.5 | AO30: ='12_MODELO'!AA29+'12_MODELO'!S30-'12_MODELO'!AA30 -> 17958.222 | AP30: ='12_MODELO'!AK30-'12_MODELO'!AL30-'12_MODELO'!AM30-'12_MODELO'!AN30-'12_MODELO'!Q30-'12_MODELO'!AO30 -> -30890.502 | AQ30: ='12_MODELO'!T30+'12_MODELO'!O30-('12_MODELO'!U30-'12_MODELO'!U29)-('12_MODELO'!V30-'12_MODELO'!V29)+('12_MODELO'!X30-'12_MODELO'!X29)+('12_MODELO'!Y30-'12_MODELO'!Y29)+('12_MODELO'!Z30-'12_MODELO'!Z29)+('12_MODELO'!AA30-'12_MODELO'!AA29) -> -30890.502 | AR30: =-'12_MODELO'!AB30 -> -18000 | AS30: ='12_MODELO'!AE30-'12_MODELO'!AF30-'12_MODELO'!AH30 -> -18000 | AT30: ='12_MODELO'!AQ30+'12_MODELO'!AR30+'12_MODELO'!AS30 -> -66890.502 | AU30: ='12_MODELO'!AV29 -> 2304718.7 | AV30: ='12_MODELO'!AU30+'12_MODELO'!AT30 -> 2237828.2 | AW30: ='12_MODELO'!AV30+'12_MODELO'!U30+'12_MODELO'!V30+'12_MODELO'!AC30-'12_MODELO'!AD30 -> 6162420.6 | AX30: ='12_MODELO'!X30+'12_MODELO'!Y30+'12_MODELO'!Z30+'12_MODELO'!AA30+'12_MODELO'!AG30 -> 1742029.5 | AY30: ='12_MODELO'!AI30+'12_MODELO'!AJ30 -> 4420391.1 | AZ30: ='12_MODELO'!AW30-'12_MODELO'!AX30-'12_MODELO'!AY30 -> 0 | BA30: ='12_MODELO'!AP30-'12_MODELO'!AQ30 -> 1.200533e-10 | BB30: ='08_PREMISSAS'!O30 -> 40 | BC30: ='08_PREMISSAS'!P30 -> 45 | BD30: ='08_PREMISSAS'!Q30 -> 36 | BE30: ='08_PREMISSAS'!R30 -> 0.085 | BF30: ='08_PREMISSAS'!S30 -> 0.34 | BG30: ='08_PREMISSAS'!T30 -> 0.012 | BH30: ='08_PREMISSAS'!U30 -> 0.01 | BI30: =IFERROR('12_MODELO'!N30/'12_MODELO'!E30,0) -> 0.087895981 | BJ30: =IFERROR('12_MODELO'!T30/'12_MODELO'!E30,0) -> 0.042127732 | BK30: ='12_MODELO'!AQ30+'12_MODELO'!AR30 -> -48890.502 | BL30: ='12_MODELO'!U30+'12_MODELO'!V30-'12_MODELO'!X30-'12_MODELO'!Y30-'12_MODELO'!Z30-'12_MODELO'!AA30 -> 1608802.9 | BM30: ='12_MODELO'!AG30-'12_MODELO'!AV30 -> -1527828.2 | BN30: =0 -> 0 | BO30: ='12_MODELO'!AV30+'12_MODELO'!U30+'12_MODELO'!V30 -> 4878660.6 | BP30: ='12_MODELO'!AC30-'12_MODELO'!AD30 -> 1283760 | BQ30: =MIN('12_MODELO'!AG30,'12_MODELO'!AF30*12) -> 216000 | BR30: ='12_MODELO'!AG30-'12_MODELO'!BQ30 -> 494000 | BS30: ='12_MODELO'!AX30-'12_MODELO'!BR30 -> 1248029.5 | BT30: ='12_MODELO'!BR30 -> 494000 | BU30: =IFERROR('12_MODELO'!BO30/'12_MODELO'!BS30,0) -> 3.9090907
A31: 45444 | B31: Orçamento | C31: ='08_PREMISSAS'!C31*'08_PREMISSAS'!D31 -> 1154400 | D31: ='12_MODELO'!C31*'12_MODELO'!BE31 -> 98124 | E31: ='12_MODELO'!C31-'12_MODELO'!D31 -> 1056276 | F31: ='12_MODELO'!C31*'08_PREMISSAS'!E31 -> 751514.4 | G31: ='12_MODELO'!E31-'12_MODELO'!F31 -> 304761.6 | H31: ='08_PREMISSAS'!J31 -> 95000 | I31: ='12_MODELO'!C31*'08_PREMISSAS'!F31 -> 39249.6 | J31: ='08_PREMISSAS'!L31 -> 33000 | K31: ='08_PREMISSAS'!M31 -> 19000 | L31: ='12_MODELO'!C31*'08_PREMISSAS'!G31 -> 24242.4 | M31: =SUM('12_MODELO'!H31:'12_MODELO'!L31) -> 210492 | N31: ='12_MODELO'!G31-'12_MODELO'!M31 -> 94269.6 | O31: =MIN('12_MODELO'!AC30*'12_MODELO'!BH31,'12_MODELO'!AC30-'12_MODELO'!AD30+'12_MODELO'!AB31) -> 16620 | P31: ='12_MODELO'!N31-'12_MODELO'!O31 -> 77649.6 | Q31: ='12_MODELO'!AG30*'12_MODELO'!BG31 -> 8520 | R31: ='12_MODELO'!P31-'12_MODELO'!Q31 -> 69129.6 | S31: =MAX(0,'12_MODELO'!R31)*'12_MODELO'!BF31 -> 23504.064 | T31: ='12_MODELO'!R31-'12_MODELO'!S31 -> 45625.536 | U31: ='12_MODELO'!C31*'12_MODELO'!BB31/30 -> 1539200 | V31: ='12_MODELO'!F31*'12_MODELO'!BC31/30 -> 1127271.6 | W31: ='12_MODELO'!F31+'12_MODELO'!V31-'12_MODELO'!V30 -> 762353.55 | X31: ='12_MODELO'!F31*'12_MODELO'!BD31/30 -> 901817.28 | Y31: ='12_MODELO'!H31*20% -> 19000 | Z31: ='12_MODELO'!D31 -> 98124 | AA31: ='12_MODELO'!S31 -> 23504.064 | AB31: ='08_PREMISSAS'!V31 -> 90000 | AC31: ='12_MODELO'!AC30+'12_MODELO'!AB31 -> 1752000 | AD31: ='12_MODELO'!AD30+'12_MODELO'!O31 -> 394860 | AE31: ='08_PREMISSAS'!W31 -> 0 | AF31: ='08_PREMISSAS'!X31 -> 18000 | AG31: ='12_MODELO'!AG30+'12_MODELO'!AE31-'12_MODELO'!AF31 -> 692000 | AH31: ='08_PREMISSAS'!Y31 -> 0 | AI31: ='12_MODELO'!AI30 -> 3900000 | AJ31: ='12_MODELO'!AJ30+'12_MODELO'!T31-'12_MODELO'!AH31 -> 566016.64 | AK31: ='12_MODELO'!U30+'12_MODELO'!C31-'12_MODELO'!U31 -> 1139600 | AL31: ='12_MODELO'!X30+'12_MODELO'!W31-'12_MODELO'!X31 -> 753682.23 | AM31: ='12_MODELO'!M31+'12_MODELO'!Y30-'12_MODELO'!Y31 -> 210492 | AN31: ='12_MODELO'!Z30+'12_MODELO'!D31-'12_MODELO'!Z31 -> 97180.5 | AO31: ='12_MODELO'!AA30+'12_MODELO'!S31-'12_MODELO'!AA31 -> 22703.058 | AP31: ='12_MODELO'!AK31-'12_MODELO'!AL31-'12_MODELO'!AM31-'12_MODELO'!AN31-'12_MODELO'!Q31-'12_MODELO'!AO31 -> 47022.212 | AQ31: ='12_MODELO'!T31+'12_MODELO'!O31-('12_MODELO'!U31-'12_MODELO'!U30)-('12_MODELO'!V31-'12_MODELO'!V30)+('12_MODELO'!X31-'12_MODELO'!X30)+('12_MODELO'!Y31-'12_MODELO'!Y30)+('12_MODELO'!Z31-'12_MODELO'!Z30)+('12_MODELO'!AA31-'12_MODELO'!AA30) -> 47022.212 | AR31: =-'12_MODELO'!AB31 -> -90000 | AS31: ='12_MODELO'!AE31-'12_MODELO'!AF31-'12_MODELO'!AH31 -> -18000 | AT31: ='12_MODELO'!AQ31+'12_MODELO'!AR31+'12_MODELO'!AS31 -> -60977.788 | AU31: ='12_MODELO'!AV30 -> 2237828.2 | AV31: ='12_MODELO'!AU31+'12_MODELO'!AT31 -> 2176850.4 | AW31: ='12_MODELO'!AV31+'12_MODELO'!U31+'12_MODELO'!V31+'12_MODELO'!AC31-'12_MODELO'!AD31 -> 6200462 | AX31: ='12_MODELO'!X31+'12_MODELO'!Y31+'12_MODELO'!Z31+'12_MODELO'!AA31+'12_MODELO'!AG31 -> 1734445.3 | AY31: ='12_MODELO'!AI31+'12_MODELO'!AJ31 -> 4466016.6 | AZ31: ='12_MODELO'!AW31-'12_MODELO'!AX31-'12_MODELO'!AY31 -> 0 | BA31: ='12_MODELO'!AP31-'12_MODELO'!AQ31 -> 2.3283064e-10 | BB31: ='08_PREMISSAS'!O31 -> 40 | BC31: ='08_PREMISSAS'!P31 -> 45 | BD31: ='08_PREMISSAS'!Q31 -> 36 | BE31: ='08_PREMISSAS'!R31 -> 0.085 | BF31: ='08_PREMISSAS'!S31 -> 0.34 | BG31: ='08_PREMISSAS'!T31 -> 0.012 | BH31: ='08_PREMISSAS'!U31 -> 0.01 | BI31: =IFERROR('12_MODELO'!N31/'12_MODELO'!E31,0) -> 0.089247129 | BJ31: =IFERROR('12_MODELO'!T31/'12_MODELO'!E31,0) -> 0.04319471 | BK31: ='12_MODELO'!AQ31+'12_MODELO'!AR31 -> -42977.788 | BL31: ='12_MODELO'!U31+'12_MODELO'!V31-'12_MODELO'!X31-'12_MODELO'!Y31-'12_MODELO'!Z31-'12_MODELO'!AA31 -> 1624026.3 | BM31: ='12_MODELO'!AG31-'12_MODELO'!AV31 -> -1484850.4 | BN31: =0 -> 0 | BO31: ='12_MODELO'!AV31+'12_MODELO'!U31+'12_MODELO'!V31 -> 4843322 | BP31: ='12_MODELO'!AC31-'12_MODELO'!AD31 -> 1357140 | BQ31: =MIN('12_MODELO'!AG31,'12_MODELO'!AF31*12) -> 216000 | BR31: ='12_MODELO'!AG31-'12_MODELO'!BQ31 -> 476000 | BS31: ='12_MODELO'!AX31-'12_MODELO'!BR31 -> 1258445.3 | BT31: ='12_MODELO'!BR31 -> 476000 | BU31: =IFERROR('12_MODELO'!BO31/'12_MODELO'!BS31,0) -> 3.848655
A32: 45474 | B32: Orçamento | C32: ='08_PREMISSAS'!C32*'08_PREMISSAS'!D32 -> 1043400 | D32: ='12_MODELO'!C32*'12_MODELO'!BE32 -> 88689 | E32: ='12_MODELO'!C32-'12_MODELO'!D32 -> 954711 | F32: ='12_MODELO'!C32*'08_PREMISSAS'!E32 -> 679253.4 | G32: ='12_MODELO'!E32-'12_MODELO'!F32 -> 275457.6 | H32: ='08_PREMISSAS'!J32 -> 95000 | I32: ='12_MODELO'!C32*'08_PREMISSAS'!F32 -> 35475.6 | J32: ='08_PREMISSAS'!L32 -> 33000 | K32: ='08_PREMISSAS'!M32 -> 19000 | L32: ='12_MODELO'!C32*'08_PREMISSAS'!G32 -> 21911.4 | M32: =SUM('12_MODELO'!H32:'12_MODELO'!L32) -> 204387 | N32: ='12_MODELO'!G32-'12_MODELO'!M32 -> 71070.6 | O32: =MIN('12_MODELO'!AC31*'12_MODELO'!BH32,'12_MODELO'!AC31-'12_MODELO'!AD31+'12_MODELO'!AB32) -> 17520 | P32: ='12_MODELO'!N32-'12_MODELO'!O32 -> 53550.6 | Q32: ='12_MODELO'!AG31*'12_MODELO'!BG32 -> 8304 | R32: ='12_MODELO'!P32-'12_MODELO'!Q32 -> 45246.6 | S32: =MAX(0,'12_MODELO'!R32)*'12_MODELO'!BF32 -> 15383.844 | T32: ='12_MODELO'!R32-'12_MODELO'!S32 -> 29862.756 | U32: ='12_MODELO'!C32*'12_MODELO'!BB32/30 -> 1391200 | V32: ='12_MODELO'!F32*'12_MODELO'!BC32/30 -> 1018880.1 | W32: ='12_MODELO'!F32+'12_MODELO'!V32-'12_MODELO'!V31 -> 570861.9 | X32: ='12_MODELO'!F32*'12_MODELO'!BD32/30 -> 815104.08 | Y32: ='12_MODELO'!H32*20% -> 19000 | Z32: ='12_MODELO'!D32 -> 88689 | AA32: ='12_MODELO'!S32 -> 15383.844 | AB32: ='08_PREMISSAS'!V32 -> 18000 | AC32: ='12_MODELO'!AC31+'12_MODELO'!AB32 -> 1770000 | AD32: ='12_MODELO'!AD31+'12_MODELO'!O32 -> 412380 | AE32: ='08_PREMISSAS'!W32 -> 0 | AF32: ='08_PREMISSAS'!X32 -> 18000 | AG32: ='12_MODELO'!AG31+'12_MODELO'!AE32-'12_MODELO'!AF32 -> 674000 | AH32: ='08_PREMISSAS'!Y32 -> 0 | AI32: ='12_MODELO'!AI31 -> 3900000 | AJ32: ='12_MODELO'!AJ31+'12_MODELO'!T32-'12_MODELO'!AH32 -> 595879.4 | AK32: ='12_MODELO'!U31+'12_MODELO'!C32-'12_MODELO'!U32 -> 1191400 | AL32: ='12_MODELO'!X31+'12_MODELO'!W32-'12_MODELO'!X32 -> 657575.1 | AM32: ='12_MODELO'!M32+'12_MODELO'!Y31-'12_MODELO'!Y32 -> 204387 | AN32: ='12_MODELO'!Z31+'12_MODELO'!D32-'12_MODELO'!Z32 -> 98124 | AO32: ='12_MODELO'!AA31+'12_MODELO'!S32-'12_MODELO'!AA32 -> 23504.064 | AP32: ='12_MODELO'!AK32-'12_MODELO'!AL32-'12_MODELO'!AM32-'12_MODELO'!AN32-'12_MODELO'!Q32-'12_MODELO'!AO32 -> 199505.84 | AQ32: ='12_MODELO'!T32+'12_MODELO'!O32-('12_MODELO'!U32-'12_MODELO'!U31)-('12_MODELO'!V32-'12_MODELO'!V31)+('12_MODELO'!X32-'12_MODELO'!X31)+('12_MODELO'!Y32-'12_MODELO'!Y31)+('12_MODELO'!Z32-'12_MODELO'!Z31)+('12_MODELO'!AA32-'12_MODELO'!AA31) -> 199505.84 | AR32: =-'12_MODELO'!AB32 -> -18000 | AS32: ='12_MODELO'!AE32-'12_MODELO'!AF32-'12_MODELO'!AH32 -> -18000 | AT32: ='12_MODELO'!AQ32+'12_MODELO'!AR32+'12_MODELO'!AS32 -> 163505.84 | AU32: ='12_MODELO'!AV31 -> 2176850.4 | AV32: ='12_MODELO'!AU32+'12_MODELO'!AT32 -> 2340356.2 | AW32: ='12_MODELO'!AV32+'12_MODELO'!U32+'12_MODELO'!V32+'12_MODELO'!AC32-'12_MODELO'!AD32 -> 6108056.3 | AX32: ='12_MODELO'!X32+'12_MODELO'!Y32+'12_MODELO'!Z32+'12_MODELO'!AA32+'12_MODELO'!AG32 -> 1612176.9 | AY32: ='12_MODELO'!AI32+'12_MODELO'!AJ32 -> 4495879.4 | AZ32: ='12_MODELO'!AW32-'12_MODELO'!AX32-'12_MODELO'!AY32 -> 0 | BA32: ='12_MODELO'!AP32-'12_MODELO'!AQ32 -> 2.0372681e-10 | BB32: ='08_PREMISSAS'!O32 -> 40 | BC32: ='08_PREMISSAS'!P32 -> 45 | BD32: ='08_PREMISSAS'!Q32 -> 36 | BE32: ='08_PREMISSAS'!R32 -> 0.085 | BF32: ='08_PREMISSAS'!S32 -> 0.34 | BG32: ='08_PREMISSAS'!T32 -> 0.012 | BH32: ='08_PREMISSAS'!U32 -> 0.01 | BI32: =IFERROR('12_MODELO'!N32/'12_MODELO'!E32,0) -> 0.074442004 | BJ32: =IFERROR('12_MODELO'!T32/'12_MODELO'!E32,0) -> 0.031279367 | BK32: ='12_MODELO'!AQ32+'12_MODELO'!AR32 -> 181505.84 | BL32: ='12_MODELO'!U32+'12_MODELO'!V32-'12_MODELO'!X32-'12_MODELO'!Y32-'12_MODELO'!Z32-'12_MODELO'!AA32 -> 1471903.2 | BM32: ='12_MODELO'!AG32-'12_MODELO'!AV32 -> -1666356.2 | BN32: =0 -> 0 | BO32: ='12_MODELO'!AV32+'12_MODELO'!U32+'12_MODELO'!V32 -> 4750436.3 | BP32: ='12_MODELO'!AC32-'12_MODELO'!AD32 -> 1357620 | BQ32: =MIN('12_MODELO'!AG32,'12_MODELO'!AF32*12) -> 216000 | BR32: ='12_MODELO'!AG32-'12_MODELO'!BQ32 -> 458000 | BS32: ='12_MODELO'!AX32-'12_MODELO'!BR32 -> 1154176.9 | BT32: ='12_MODELO'!BR32 -> 458000 | BU32: =IFERROR('12_MODELO'!BO32/'12_MODELO'!BS32,0) -> 4.1158649
A33: 45505 | B33: Orçamento | C33: ='08_PREMISSAS'!C33*'08_PREMISSAS'!D33 -> 1132200 | D33: ='12_MODELO'!C33*'12_MODELO'!BE33 -> 96237 | E33: ='12_MODELO'!C33-'12_MODELO'!D33 -> 1035963 | F33: ='12_MODELO'!C33*'08_PREMISSAS'!E33 -> 737062.2 | G33: ='12_MODELO'!E33-'12_MODELO'!F33 -> 298900.8 | H33: ='08_PREMISSAS'!J33 -> 95000 | I33: ='12_MODELO'!C33*'08_PREMISSAS'!F33 -> 38494.8 | J33: ='08_PREMISSAS'!L33 -> 33000 | K33: ='08_PREMISSAS'!M33 -> 19000 | L33: ='12_MODELO'!C33*'08_PREMISSAS'!G33 -> 23776.2 | M33: =SUM('12_MODELO'!H33:'12_MODELO'!L33) -> 209271 | N33: ='12_MODELO'!G33-'12_MODELO'!M33 -> 89629.8 | O33: =MIN('12_MODELO'!AC32*'12_MODELO'!BH33,'12_MODELO'!AC32-'12_MODELO'!AD32+'12_MODELO'!AB33) -> 17700 | P33: ='12_MODELO'!N33-'12_MODELO'!O33 -> 71929.8 | Q33: ='12_MODELO'!AG32*'12_MODELO'!BG33 -> 8088 | R33: ='12_MODELO'!P33-'12_MODELO'!Q33 -> 63841.8 | S33: =MAX(0,'12_MODELO'!R33)*'12_MODELO'!BF33 -> 21706.212 | T33: ='12_MODELO'!R33-'12_MODELO'!S33 -> 42135.588 | U33: ='12_MODELO'!C33*'12_MODELO'!BB33/30 -> 1509600 | V33: ='12_MODELO'!F33*'12_MODELO'!BC33/30 -> 1105593.3 | W33: ='12_MODELO'!F33+'12_MODELO'!V33-'12_MODELO'!V32 -> 823775.4 | X33: ='12_MODELO'!F33*'12_MODELO'!BD33/30 -> 884474.64 | Y33: ='12_MODELO'!H33*20% -> 19000 | Z33: ='12_MODELO'!D33 -> 96237 | AA33: ='12_MODELO'!S33 -> 21706.212 | AB33: ='08_PREMISSAS'!V33 -> 18000 | AC33: ='12_MODELO'!AC32+'12_MODELO'!AB33 -> 1788000 | AD33: ='12_MODELO'!AD32+'12_MODELO'!O33 -> 430080 | AE33: ='08_PREMISSAS'!W33 -> 0 | AF33: ='08_PREMISSAS'!X33 -> 18000 | AG33: ='12_MODELO'!AG32+'12_MODELO'!AE33-'12_MODELO'!AF33 -> 656000 | AH33: ='08_PREMISSAS'!Y33 -> 0 | AI33: ='12_MODELO'!AI32 -> 3900000 | AJ33: ='12_MODELO'!AJ32+'12_MODELO'!T33-'12_MODELO'!AH33 -> 638014.99 | AK33: ='12_MODELO'!U32+'12_MODELO'!C33-'12_MODELO'!U33 -> 1013800 | AL33: ='12_MODELO'!X32+'12_MODELO'!W33-'12_MODELO'!X33 -> 754404.84 | AM33: ='12_MODELO'!M33+'12_MODELO'!Y32-'12_MODELO'!Y33 -> 209271 | AN33: ='12_MODELO'!Z32+'12_MODELO'!D33-'12_MODELO'!Z33 -> 88689 | AO33: ='12_MODELO'!AA32+'12_MODELO'!S33-'12_MODELO'!AA33 -> 15383.844 | AP33: ='12_MODELO'!AK33-'12_MODELO'!AL33-'12_MODELO'!AM33-'12_MODELO'!AN33-'12_MODELO'!Q33-'12_MODELO'!AO33 -> -62036.684 | AQ33: ='12_MODELO'!T33+'12_MODELO'!O33-('12_MODELO'!U33-'12_MODELO'!U32)-('12_MODELO'!V33-'12_MODELO'!V32)+('12_MODELO'!X33-'12_MODELO'!X32)+('12_MODELO'!Y33-'12_MODELO'!Y32)+('12_MODELO'!Z33-'12_MODELO'!Z32)+('12_MODELO'!AA33-'12_MODELO'!AA32) -> -62036.684 | AR33: =-'12_MODELO'!AB33 -> -18000 | AS33: ='12_MODELO'!AE33-'12_MODELO'!AF33-'12_MODELO'!AH33 -> -18000 | AT33: ='12_MODELO'!AQ33+'12_MODELO'!AR33+'12_MODELO'!AS33 -> -98036.684 | AU33: ='12_MODELO'!AV32 -> 2340356.2 | AV33: ='12_MODELO'!AU33+'12_MODELO'!AT33 -> 2242319.5 | AW33: ='12_MODELO'!AV33+'12_MODELO'!U33+'12_MODELO'!V33+'12_MODELO'!AC33-'12_MODELO'!AD33 -> 6215432.8 | AX33: ='12_MODELO'!X33+'12_MODELO'!Y33+'12_MODELO'!Z33+'12_MODELO'!AA33+'12_MODELO'!AG33 -> 1677417.9 | AY33: ='12_MODELO'!AI33+'12_MODELO'!AJ33 -> 4538015 | AZ33: ='12_MODELO'!AW33-'12_MODELO'!AX33-'12_MODELO'!AY33 -> 0 | BA33: ='12_MODELO'!AP33-'12_MODELO'!AQ33 -> 4.3655746e-10 | BB33: ='08_PREMISSAS'!O33 -> 40 | BC33: ='08_PREMISSAS'!P33 -> 45 | BD33: ='08_PREMISSAS'!Q33 -> 36 | BE33: ='08_PREMISSAS'!R33 -> 0.085 | BF33: ='08_PREMISSAS'!S33 -> 0.34 | BG33: ='08_PREMISSAS'!T33 -> 0.012 | BH33: ='08_PREMISSAS'!U33 -> 0.01 | BI33: =IFERROR('12_MODELO'!N33/'12_MODELO'!E33,0) -> 0.086518341 | BJ33: =IFERROR('12_MODELO'!T33/'12_MODELO'!E33,0) -> 0.04067287 | BK33: ='12_MODELO'!AQ33+'12_MODELO'!AR33 -> -80036.684 | BL33: ='12_MODELO'!U33+'12_MODELO'!V33-'12_MODELO'!X33-'12_MODELO'!Y33-'12_MODELO'!Z33-'12_MODELO'!AA33 -> 1593775.4 | BM33: ='12_MODELO'!AG33-'12_MODELO'!AV33 -> -1586319.5 | BN33: =0 -> 0 | BO33: ='12_MODELO'!AV33+'12_MODELO'!U33+'12_MODELO'!V33 -> 4857512.8 | BP33: ='12_MODELO'!AC33-'12_MODELO'!AD33 -> 1357920 | BQ33: =MIN('12_MODELO'!AG33,'12_MODELO'!AF33*12) -> 216000 | BR33: ='12_MODELO'!AG33-'12_MODELO'!BQ33 -> 440000 | BS33: ='12_MODELO'!AX33-'12_MODELO'!BR33 -> 1237417.9 | BT33: ='12_MODELO'!BR33 -> 440000 | BU33: =IFERROR('12_MODELO'!BO33/'12_MODELO'!BS33,0) -> 3.9255235
A34: 45536 | B34: Orçamento | C34: ='08_PREMISSAS'!C34*'08_PREMISSAS'!D34 -> 1176600 | D34: ='12_MODELO'!C34*'12_MODELO'!BE34 -> 100011 | E34: ='12_MODELO'!C34-'12_MODELO'!D34 -> 1076589 | F34: ='12_MODELO'!C34*'08_PREMISSAS'!E34 -> 765966.6 | G34: ='12_MODELO'!E34-'12_MODELO'!F34 -> 310622.4 | H34: ='08_PREMISSAS'!J34 -> 95000 | I34: ='12_MODELO'!C34*'08_PREMISSAS'!F34 -> 40004.4 | J34: ='08_PREMISSAS'!L34 -> 33000 | K34: ='08_PREMISSAS'!M34 -> 19000 | L34: ='12_MODELO'!C34*'08_PREMISSAS'!G34 -> 24708.6 | M34: =SUM('12_MODELO'!H34:'12_MODELO'!L34) -> 211713 | N34: ='12_MODELO'!G34-'12_MODELO'!M34 -> 98909.4 | O34: =MIN('12_MODELO'!AC33*'12_MODELO'!BH34,'12_MODELO'!AC33-'12_MODELO'!AD33+'12_MODELO'!AB34) -> 17880 | P34: ='12_MODELO'!N34-'12_MODELO'!O34 -> 81029.4 | Q34: ='12_MODELO'!AG33*'12_MODELO'!BG34 -> 7872 | R34: ='12_MODELO'!P34-'12_MODELO'!Q34 -> 73157.4 | S34: =MAX(0,'12_MODELO'!R34)*'12_MODELO'!BF34 -> 24873.516 | T34: ='12_MODELO'!R34-'12_MODELO'!S34 -> 48283.884 | U34: ='12_MODELO'!C34*'12_MODELO'!BB34/30 -> 1568800 | V34: ='12_MODELO'!F34*'12_MODELO'!BC34/30 -> 1148949.9 | W34: ='12_MODELO'!F34+'12_MODELO'!V34-'12_MODELO'!V33 -> 809323.2 | X34: ='12_MODELO'!F34*'12_MODELO'!BD34/30 -> 919159.92 | Y34: ='12_MODELO'!H34*20% -> 19000 | Z34: ='12_MODELO'!D34 -> 100011 | AA34: ='12_MODELO'!S34 -> 24873.516 | AB34: ='08_PREMISSAS'!V34 -> 90000 | AC34: ='12_MODELO'!AC33+'12_MODELO'!AB34 -> 1878000 | AD34: ='12_MODELO'!AD33+'12_MODELO'!O34 -> 447960 | AE34: ='08_PREMISSAS'!W34 -> 0 | AF34: ='08_PREMISSAS'!X34 -> 18000 | AG34: ='12_MODELO'!AG33+'12_MODELO'!AE34-'12_MODELO'!AF34 -> 638000 | AH34: ='08_PREMISSAS'!Y34 -> 0 | AI34: ='12_MODELO'!AI33 -> 3900000 | AJ34: ='12_MODELO'!AJ33+'12_MODELO'!T34-'12_MODELO'!AH34 -> 686298.87 | AK34: ='12_MODELO'!U33+'12_MODELO'!C34-'12_MODELO'!U34 -> 1117400 | AL34: ='12_MODELO'!X33+'12_MODELO'!W34-'12_MODELO'!X34 -> 774637.92 | AM34: ='12_MODELO'!M34+'12_MODELO'!Y33-'12_MODELO'!Y34 -> 211713 | AN34: ='12_MODELO'!Z33+'12_MODELO'!D34-'12_MODELO'!Z34 -> 96237 | AO34: ='12_MODELO'!AA33+'12_MODELO'!S34-'12_MODELO'!AA34 -> 21706.212 | AP34: ='12_MODELO'!AK34-'12_MODELO'!AL34-'12_MODELO'!AM34-'12_MODELO'!AN34-'12_MODELO'!Q34-'12_MODELO'!AO34 -> 5233.868 | AQ34: ='12_MODELO'!T34+'12_MODELO'!O34-('12_MODELO'!U34-'12_MODELO'!U33)-('12_MODELO'!V34-'12_MODELO'!V33)+('12_MODELO'!X34-'12_MODELO'!X33)+('12_MODELO'!Y34-'12_MODELO'!Y33)+('12_MODELO'!Z34-'12_MODELO'!Z33)+('12_MODELO'!AA34-'12_MODELO'!AA33) -> 5233.868 | AR34: =-'12_MODELO'!AB34 -> -90000 | AS34: ='12_MODELO'!AE34-'12_MODELO'!AF34-'12_MODELO'!AH34 -> -18000 | AT34: ='12_MODELO'!AQ34+'12_MODELO'!AR34+'12_MODELO'!AS34 -> -102766.13 | AU34: ='12_MODELO'!AV33 -> 2242319.5 | AV34: ='12_MODELO'!AU34+'12_MODELO'!AT34 -> 2139553.4 | AW34: ='12_MODELO'!AV34+'12_MODELO'!U34+'12_MODELO'!V34+'12_MODELO'!AC34-'12_MODELO'!AD34 -> 6287343.3 | AX34: ='12_MODELO'!X34+'12_MODELO'!Y34+'12_MODELO'!Z34+'12_MODELO'!AA34+'12_MODELO'!AG34 -> 1701044.4 | AY34: ='12_MODELO'!AI34+'12_MODELO'!AJ34 -> 4586298.9 | AZ34: ='12_MODELO'!AW34-'12_MODELO'!AX34-'12_MODELO'!AY34 -> 0 | BA34: ='12_MODELO'!AP34-'12_MODELO'!AQ34 -> -1.2369128e-10 | BB34: ='08_PREMISSAS'!O34 -> 40 | BC34: ='08_PREMISSAS'!P34 -> 45 | BD34: ='08_PREMISSAS'!Q34 -> 36 | BE34: ='08_PREMISSAS'!R34 -> 0.085 | BF34: ='08_PREMISSAS'!S34 -> 0.34 | BG34: ='08_PREMISSAS'!T34 -> 0.012 | BH34: ='08_PREMISSAS'!U34 -> 0.01 | BI34: =IFERROR('12_MODELO'!N34/'12_MODELO'!E34,0) -> 0.091872943 | BJ34: =IFERROR('12_MODELO'!T34/'12_MODELO'!E34,0) -> 0.044848948 | BK34: ='12_MODELO'!AQ34+'12_MODELO'!AR34 -> -84766.132 | BL34: ='12_MODELO'!U34+'12_MODELO'!V34-'12_MODELO'!X34-'12_MODELO'!Y34-'12_MODELO'!Z34-'12_MODELO'!AA34 -> 1654705.5 | BM34: ='12_MODELO'!AG34-'12_MODELO'!AV34 -> -1501553.4 | BN34: =0 -> 0 | BO34: ='12_MODELO'!AV34+'12_MODELO'!U34+'12_MODELO'!V34 -> 4857303.3 | BP34: ='12_MODELO'!AC34-'12_MODELO'!AD34 -> 1430040 | BQ34: =MIN('12_MODELO'!AG34,'12_MODELO'!AF34*12) -> 216000 | BR34: ='12_MODELO'!AG34-'12_MODELO'!BQ34 -> 422000 | BS34: ='12_MODELO'!AX34-'12_MODELO'!BR34 -> 1279044.4 | BT34: ='12_MODELO'!BR34 -> 422000 | BU34: =IFERROR('12_MODELO'!BO34/'12_MODELO'!BS34,0) -> 3.7976033
A35: 45566 | B35: Orçamento | C35: ='08_PREMISSAS'!C35*'08_PREMISSAS'!D35 -> 1243200 | D35: ='12_MODELO'!C35*'12_MODELO'!BE35 -> 105672 | E35: ='12_MODELO'!C35-'12_MODELO'!D35 -> 1137528 | F35: ='12_MODELO'!C35*'08_PREMISSAS'!E35 -> 809323.2 | G35: ='12_MODELO'!E35-'12_MODELO'!F35 -> 328204.8 | H35: ='08_PREMISSAS'!J35 -> 95000 | I35: ='12_MODELO'!C35*'08_PREMISSAS'!F35 -> 42268.8 | J35: ='08_PREMISSAS'!L35 -> 33000 | K35: ='08_PREMISSAS'!M35 -> 19000 | L35: ='12_MODELO'!C35*'08_PREMISSAS'!G35 -> 26107.2 | M35: =SUM('12_MODELO'!H35:'12_MODELO'!L35) -> 215376 | N35: ='12_MODELO'!G35-'12_MODELO'!M35 -> 112828.8 | O35: =MIN('12_MODELO'!AC34*'12_MODELO'!BH35,'12_MODELO'!AC34-'12_MODELO'!AD34+'12_MODELO'!AB35) -> 18780 | P35: ='12_MODELO'!N35-'12_MODELO'!O35 -> 94048.8 | Q35: ='12_MODELO'!AG34*'12_MODELO'!BG35 -> 7656 | R35: ='12_MODELO'!P35-'12_MODELO'!Q35 -> 86392.8 | S35: =MAX(0,'12_MODELO'!R35)*'12_MODELO'!BF35 -> 29373.552 | T35: ='12_MODELO'!R35-'12_MODELO'!S35 -> 57019.248 | U35: ='12_MODELO'!C35*'12_MODELO'!BB35/30 -> 1657600 | V35: ='12_MODELO'!F35*'12_MODELO'!BC35/30 -> 1213984.8 | W35: ='12_MODELO'!F35+'12_MODELO'!V35-'12_MODELO'!V34 -> 874358.1 | X35: ='12_MODELO'!F35*'12_MODELO'!BD35/30 -> 971187.84 | Y35: ='12_MODELO'!H35*20% -> 19000 | Z35: ='12_MODELO'!D35 -> 105672 | AA35: ='12_MODELO'!S35 -> 29373.552 | AB35: ='08_PREMISSAS'!V35 -> 18000 | AC35: ='12_MODELO'!AC34+'12_MODELO'!AB35 -> 1896000 | AD35: ='12_MODELO'!AD34+'12_MODELO'!O35 -> 466740 | AE35: ='08_PREMISSAS'!W35 -> 0 | AF35: ='08_PREMISSAS'!X35 -> 18000 | AG35: ='12_MODELO'!AG34+'12_MODELO'!AE35-'12_MODELO'!AF35 -> 620000 | AH35: ='08_PREMISSAS'!Y35 -> 0 | AI35: ='12_MODELO'!AI34 -> 3900000 | AJ35: ='12_MODELO'!AJ34+'12_MODELO'!T35-'12_MODELO'!AH35 -> 743318.12 | AK35: ='12_MODELO'!U34+'12_MODELO'!C35-'12_MODELO'!U35 -> 1154400 | AL35: ='12_MODELO'!X34+'12_MODELO'!W35-'12_MODELO'!X35 -> 822330.18 | AM35: ='12_MODELO'!M35+'12_MODELO'!Y34-'12_MODELO'!Y35 -> 215376 | AN35: ='12_MODELO'!Z34+'12_MODELO'!D35-'12_MODELO'!Z35 -> 100011 | AO35: ='12_MODELO'!AA34+'12_MODELO'!S35-'12_MODELO'!AA35 -> 24873.516 | AP35: ='12_MODELO'!AK35-'12_MODELO'!AL35-'12_MODELO'!AM35-'12_MODELO'!AN35-'12_MODELO'!Q35-'12_MODELO'!AO35 -> -15846.696 | AQ35: ='12_MODELO'!T35+'12_MODELO'!O35-('12_MODELO'!U35-'12_MODELO'!U34)-('12_MODELO'!V35-'12_MODELO'!V34)+('12_MODELO'!X35-'12_MODELO'!X34)+('12_MODELO'!Y35-'12_MODELO'!Y34)+('12_MODELO'!Z35-'12_MODELO'!Z34)+('12_MODELO'!AA35-'12_MODELO'!AA34) -> -15846.696 | AR35: =-'12_MODELO'!AB35 -> -18000 | AS35: ='12_MODELO'!AE35-'12_MODELO'!AF35-'12_MODELO'!AH35 -> -18000 | AT35: ='12_MODELO'!AQ35+'12_MODELO'!AR35+'12_MODELO'!AS35 -> -51846.696 | AU35: ='12_MODELO'!AV34 -> 2139553.4 | AV35: ='12_MODELO'!AU35+'12_MODELO'!AT35 -> 2087706.7 | AW35: ='12_MODELO'!AV35+'12_MODELO'!U35+'12_MODELO'!V35+'12_MODELO'!AC35-'12_MODELO'!AD35 -> 6388551.5 | AX35: ='12_MODELO'!X35+'12_MODELO'!Y35+'12_MODELO'!Z35+'12_MODELO'!AA35+'12_MODELO'!AG35 -> 1745233.4 | AY35: ='12_MODELO'!AI35+'12_MODELO'!AJ35 -> 4643318.1 | AZ35: ='12_MODELO'!AW35-'12_MODELO'!AX35-'12_MODELO'!AY35 -> 0 | BA35: ='12_MODELO'!AP35-'12_MODELO'!AQ35 -> -2.5102054e-10 | BB35: ='08_PREMISSAS'!O35 -> 40 | BC35: ='08_PREMISSAS'!P35 -> 45 | BD35: ='08_PREMISSAS'!Q35 -> 36 | BE35: ='08_PREMISSAS'!R35 -> 0.085 | BF35: ='08_PREMISSAS'!S35 -> 0.34 | BG35: ='08_PREMISSAS'!T35 -> 0.012 | BH35: ='08_PREMISSAS'!U35 -> 0.01 | BI35: =IFERROR('12_MODELO'!N35/'12_MODELO'!E35,0) -> 0.099187712 | BJ35: =IFERROR('12_MODELO'!T35/'12_MODELO'!E35,0) -> 0.050125578 | BK35: ='12_MODELO'!AQ35+'12_MODELO'!AR35 -> -33846.696 | BL35: ='12_MODELO'!U35+'12_MODELO'!V35-'12_MODELO'!X35-'12_MODELO'!Y35-'12_MODELO'!Z35-'12_MODELO'!AA35 -> 1746351.4 | BM35: ='12_MODELO'!AG35-'12_MODELO'!AV35 -> -1467706.7 | BN35: =0 -> 0 | BO35: ='12_MODELO'!AV35+'12_MODELO'!U35+'12_MODELO'!V35 -> 4959291.5 | BP35: ='12_MODELO'!AC35-'12_MODELO'!AD35 -> 1429260 | BQ35: =MIN('12_MODELO'!AG35,'12_MODELO'!AF35*12) -> 216000 | BR35: ='12_MODELO'!AG35-'12_MODELO'!BQ35 -> 404000 | BS35: ='12_MODELO'!AX35-'12_MODELO'!BR35 -> 1341233.4 | BT35: ='12_MODELO'!BR35 -> 404000 | BU35: =IFERROR('12_MODELO'!BO35/'12_MODELO'!BS35,0) -> 3.6975604
A36: 45597 | B36: Orçamento | C36: ='08_PREMISSAS'!C36*'08_PREMISSAS'!D36 -> 1431900 | D36: ='12_MODELO'!C36*'12_MODELO'!BE36 -> 121711.5 | E36: ='12_MODELO'!C36-'12_MODELO'!D36 -> 1310188.5 | F36: ='12_MODELO'!C36*'08_PREMISSAS'!E36 -> 932166.9 | G36: ='12_MODELO'!E36-'12_MODELO'!F36 -> 378021.6 | H36: ='08_PREMISSAS'!J36 -> 95000 | I36: ='12_MODELO'!C36*'08_PREMISSAS'!F36 -> 48684.6 | J36: ='08_PREMISSAS'!L36 -> 33000 | K36: ='08_PREMISSAS'!M36 -> 19000 | L36: ='12_MODELO'!C36*'08_PREMISSAS'!G36 -> 30069.9 | M36: =SUM('12_MODELO'!H36:'12_MODELO'!L36) -> 225754.5 | N36: ='12_MODELO'!G36-'12_MODELO'!M36 -> 152267.1 | O36: =MIN('12_MODELO'!AC35*'12_MODELO'!BH36,'12_MODELO'!AC35-'12_MODELO'!AD35+'12_MODELO'!AB36) -> 18960 | P36: ='12_MODELO'!N36-'12_MODELO'!O36 -> 133307.1 | Q36: ='12_MODELO'!AG35*'12_MODELO'!BG36 -> 7440 | R36: ='12_MODELO'!P36-'12_MODELO'!Q36 -> 125867.1 | S36: =MAX(0,'12_MODELO'!R36)*'12_MODELO'!BF36 -> 42794.814 | T36: ='12_MODELO'!R36-'12_MODELO'!S36 -> 83072.286 | U36: ='12_MODELO'!C36*'12_MODELO'!BB36/30 -> 1909200 | V36: ='12_MODELO'!F36*'12_MODELO'!BC36/30 -> 1398250.4 | W36: ='12_MODELO'!F36+'12_MODELO'!V36-'12_MODELO'!V35 -> 1116432.4 | X36: ='12_MODELO'!F36*'12_MODELO'!BD36/30 -> 1118600.3 | Y36: ='12_MODELO'!H36*20% -> 19000 | Z36: ='12_MODELO'!D36 -> 121711.5 | AA36: ='12_MODELO'!S36 -> 42794.814 | AB36: ='08_PREMISSAS'!V36 -> 18000 | AC36: ='12_MODELO'!AC35+'12_MODELO'!AB36 -> 1914000 | AD36: ='12_MODELO'!AD35+'12_MODELO'!O36 -> 485700 | AE36: ='08_PREMISSAS'!W36 -> 0 | AF36: ='08_PREMISSAS'!X36 -> 18000 | AG36: ='12_MODELO'!AG35+'12_MODELO'!AE36-'12_MODELO'!AF36 -> 602000 | AH36: ='08_PREMISSAS'!Y36 -> 0 | AI36: ='12_MODELO'!AI35 -> 3900000 | AJ36: ='12_MODELO'!AJ35+'12_MODELO'!T36-'12_MODELO'!AH36 -> 826390.41 | AK36: ='12_MODELO'!U35+'12_MODELO'!C36-'12_MODELO'!U36 -> 1180300 | AL36: ='12_MODELO'!X35+'12_MODELO'!W36-'12_MODELO'!X36 -> 969020.01 | AM36: ='12_MODELO'!M36+'12_MODELO'!Y35-'12_MODELO'!Y36 -> 225754.5 | AN36: ='12_MODELO'!Z35+'12_MODELO'!D36-'12_MODELO'!Z36 -> 105672 | AO36: ='12_MODELO'!AA35+'12_MODELO'!S36-'12_MODELO'!AA36 -> 29373.552 | AP36: ='12_MODELO'!AK36-'12_MODELO'!AL36-'12_MODELO'!AM36-'12_MODELO'!AN36-'12_MODELO'!Q36-'12_MODELO'!AO36 -> -156960.06 | AQ36: ='12_MODELO'!T36+'12_MODELO'!O36-('12_MODELO'!U36-'12_MODELO'!U35)-('12_MODELO'!V36-'12_MODELO'!V35)+('12_MODELO'!X36-'12_MODELO'!X35)+('12_MODELO'!Y36-'12_MODELO'!Y35)+('12_MODELO'!Z36-'12_MODELO'!Z35)+('12_MODELO'!AA36-'12_MODELO'!AA35) -> -156960.06 | AR36: =-'12_MODELO'!AB36 -> -18000 | AS36: ='12_MODELO'!AE36-'12_MODELO'!AF36-'12_MODELO'!AH36 -> -18000 | AT36: ='12_MODELO'!AQ36+'12_MODELO'!AR36+'12_MODELO'!AS36 -> -192960.06 | AU36: ='12_MODELO'!AV35 -> 2087706.7 | AV36: ='12_MODELO'!AU36+'12_MODELO'!AT36 -> 1894746.6 | AW36: ='12_MODELO'!AV36+'12_MODELO'!U36+'12_MODELO'!V36+'12_MODELO'!AC36-'12_MODELO'!AD36 -> 6630497 | AX36: ='12_MODELO'!X36+'12_MODELO'!Y36+'12_MODELO'!Z36+'12_MODELO'!AA36+'12_MODELO'!AG36 -> 1904106.6 | AY36: ='12_MODELO'!AI36+'12_MODELO'!AJ36 -> 4726390.4 | AZ36: ='12_MODELO'!AW36-'12_MODELO'!AX36-'12_MODELO'!AY36 -> 0 | BA36: ='12_MODELO'!AP36-'12_MODELO'!AQ36 -> -2.6193447e-10 | BB36: ='08_PREMISSAS'!O36 -> 40 | BC36: ='08_PREMISSAS'!P36 -> 45 | BD36: ='08_PREMISSAS'!Q36 -> 36 | BE36: ='08_PREMISSAS'!R36 -> 0.085 | BF36: ='08_PREMISSAS'!S36 -> 0.34 | BG36: ='08_PREMISSAS'!T36 -> 0.012 | BH36: ='08_PREMISSAS'!U36 -> 0.01 | BI36: =IFERROR('12_MODELO'!N36/'12_MODELO'!E36,0) -> 0.1162177 | BJ36: =IFERROR('12_MODELO'!T36/'12_MODELO'!E36,0) -> 0.063404835 | BK36: ='12_MODELO'!AQ36+'12_MODELO'!AR36 -> -174960.06 | BL36: ='12_MODELO'!U36+'12_MODELO'!V36-'12_MODELO'!X36-'12_MODELO'!Y36-'12_MODELO'!Z36-'12_MODELO'!AA36 -> 2005343.8 | BM36: ='12_MODELO'!AG36-'12_MODELO'!AV36 -> -1292746.6 | BN36: =0 -> 0 | BO36: ='12_MODELO'!AV36+'12_MODELO'!U36+'12_MODELO'!V36 -> 5202197 | BP36: ='12_MODELO'!AC36-'12_MODELO'!AD36 -> 1428300 | BQ36: =MIN('12_MODELO'!AG36,'12_MODELO'!AF36*12) -> 216000 | BR36: ='12_MODELO'!AG36-'12_MODELO'!BQ36 -> 386000 | BS36: ='12_MODELO'!AX36-'12_MODELO'!BR36 -> 1518106.6 | BT36: ='12_MODELO'!BR36 -> 386000 | BU36: =IFERROR('12_MODELO'!BO36/'12_MODELO'!BS36,0) -> 3.4267666
A37: 45627 | B37: Orçamento | C37: ='08_PREMISSAS'!C37*'08_PREMISSAS'!D37 -> 1309800 | D37: ='12_MODELO'!C37*'12_MODELO'!BE37 -> 111333 | E37: ='12_MODELO'!C37-'12_MODELO'!D37 -> 1198467 | F37: ='12_MODELO'!C37*'08_PREMISSAS'!E37 -> 852679.8 | G37: ='12_MODELO'!E37-'12_MODELO'!F37 -> 345787.2 | H37: ='08_PREMISSAS'!J37 -> 95000 | I37: ='12_MODELO'!C37*'08_PREMISSAS'!F37 -> 44533.2 | J37: ='08_PREMISSAS'!L37 -> 33000 | K37: ='08_PREMISSAS'!M37 -> 19000 | L37: ='12_MODELO'!C37*'08_PREMISSAS'!G37 -> 27505.8 | M37: =SUM('12_MODELO'!H37:'12_MODELO'!L37) -> 219039 | N37: ='12_MODELO'!G37-'12_MODELO'!M37 -> 126748.2 | O37: =MIN('12_MODELO'!AC36*'12_MODELO'!BH37,'12_MODELO'!AC36-'12_MODELO'!AD36+'12_MODELO'!AB37) -> 19140 | P37: ='12_MODELO'!N37-'12_MODELO'!O37 -> 107608.2 | Q37: ='12_MODELO'!AG36*'12_MODELO'!BG37 -> 7224 | R37: ='12_MODELO'!P37-'12_MODELO'!Q37 -> 100384.2 | S37: =MAX(0,'12_MODELO'!R37)*'12_MODELO'!BF37 -> 34130.628 | T37: ='12_MODELO'!R37-'12_MODELO'!S37 -> 66253.572 | U37: ='12_MODELO'!C37*'12_MODELO'!BB37/30 -> 1746400 | V37: ='12_MODELO'!F37*'12_MODELO'!BC37/30 -> 1279019.7 | W37: ='12_MODELO'!F37+'12_MODELO'!V37-'12_MODELO'!V36 -> 733449.15 | X37: ='12_MODELO'!F37*'12_MODELO'!BD37/30 -> 1023215.8 | Y37: ='12_MODELO'!H37*20% -> 19000 | Z37: ='12_MODELO'!D37 -> 111333 | AA37: ='12_MODELO'!S37 -> 34130.628 | AB37: ='08_PREMISSAS'!V37 -> 90000 | AC37: ='12_MODELO'!AC36+'12_MODELO'!AB37 -> 2004000 | AD37: ='12_MODELO'!AD36+'12_MODELO'!O37 -> 504840 | AE37: ='08_PREMISSAS'!W37 -> 0 | AF37: ='08_PREMISSAS'!X37 -> 18000 | AG37: ='12_MODELO'!AG36+'12_MODELO'!AE37-'12_MODELO'!AF37 -> 584000 | AH37: ='08_PREMISSAS'!Y37 -> 0 | AI37: ='12_MODELO'!AI36 -> 3900000 | AJ37: ='12_MODELO'!AJ36+'12_MODELO'!T37-'12_MODELO'!AH37 -> 892643.98 | AK37: ='12_MODELO'!U36+'12_MODELO'!C37-'12_MODELO'!U37 -> 1472600 | AL37: ='12_MODELO'!X36+'12_MODELO'!W37-'12_MODELO'!X37 -> 828833.67 | AM37: ='12_MODELO'!M37+'12_MODELO'!Y36-'12_MODELO'!Y37 -> 219039 | AN37: ='12_MODELO'!Z36+'12_MODELO'!D37-'12_MODELO'!Z37 -> 121711.5 | AO37: ='12_MODELO'!AA36+'12_MODELO'!S37-'12_MODELO'!AA37 -> 42794.814 | AP37: ='12_MODELO'!AK37-'12_MODELO'!AL37-'12_MODELO'!AM37-'12_MODELO'!AN37-'12_MODELO'!Q37-'12_MODELO'!AO37 -> 252997.02 | AQ37: ='12_MODELO'!T37+'12_MODELO'!O37-('12_MODELO'!U37-'12_MODELO'!U36)-('12_MODELO'!V37-'12_MODELO'!V36)+('12_MODELO'!X37-'12_MODELO'!X36)+('12_MODELO'!Y37-'12_MODELO'!Y36)+('12_MODELO'!Z37-'12_MODELO'!Z36)+('12_MODELO'!AA37-'12_MODELO'!AA36) -> 252997.02 | AR37: =-'12_MODELO'!AB37 -> -90000 | AS37: ='12_MODELO'!AE37-'12_MODELO'!AF37-'12_MODELO'!AH37 -> -18000 | AT37: ='12_MODELO'!AQ37+'12_MODELO'!AR37+'12_MODELO'!AS37 -> 144997.02 | AU37: ='12_MODELO'!AV36 -> 1894746.6 | AV37: ='12_MODELO'!AU37+'12_MODELO'!AT37 -> 2039743.7 | AW37: ='12_MODELO'!AV37+'12_MODELO'!U37+'12_MODELO'!V37+'12_MODELO'!AC37-'12_MODELO'!AD37 -> 6564323.4 | AX37: ='12_MODELO'!X37+'12_MODELO'!Y37+'12_MODELO'!Z37+'12_MODELO'!AA37+'12_MODELO'!AG37 -> 1771679.4 | AY37: ='12_MODELO'!AI37+'12_MODELO'!AJ37 -> 4792644 | AZ37: ='12_MODELO'!AW37-'12_MODELO'!AX37-'12_MODELO'!AY37 -> -9.3132257e-10 | BA37: ='12_MODELO'!AP37-'12_MODELO'!AQ37 -> 5.8207661e-11 | BB37: ='08_PREMISSAS'!O37 -> 40 | BC37: ='08_PREMISSAS'!P37 -> 45 | BD37: ='08_PREMISSAS'!Q37 -> 36 | BE37: ='08_PREMISSAS'!R37 -> 0.085 | BF37: ='08_PREMISSAS'!S37 -> 0.34 | BG37: ='08_PREMISSAS'!T37 -> 0.012 | BH37: ='08_PREMISSAS'!U37 -> 0.01 | BI37: =IFERROR('12_MODELO'!N37/'12_MODELO'!E37,0) -> 0.10575861 | BJ37: =IFERROR('12_MODELO'!T37/'12_MODELO'!E37,0) -> 0.055281933 | BK37: ='12_MODELO'!AQ37+'12_MODELO'!AR37 -> 162997.02 | BL37: ='12_MODELO'!U37+'12_MODELO'!V37-'12_MODELO'!X37-'12_MODELO'!Y37-'12_MODELO'!Z37-'12_MODELO'!AA37 -> 1837740.3 | BM37: ='12_MODELO'!AG37-'12_MODELO'!AV37 -> -1455743.7 | BN37: =0 -> 0 | BO37: ='12_MODELO'!AV37+'12_MODELO'!U37+'12_MODELO'!V37 -> 5065163.4 | BP37: ='12_MODELO'!AC37-'12_MODELO'!AD37 -> 1499160 | BQ37: =MIN('12_MODELO'!AG37,'12_MODELO'!AF37*12) -> 216000 | BR37: ='12_MODELO'!AG37-'12_MODELO'!BQ37 -> 368000 | BS37: ='12_MODELO'!AX37-'12_MODELO'!BR37 -> 1403679.4 | BT37: ='12_MODELO'!BR37 -> 368000 | BU37: =IFERROR('12_MODELO'!BO37/'12_MODELO'!BS37,0) -> 3.6084902
A38: 45658 | B38: Orçamento | C38: ='08_PREMISSAS'!C38*'08_PREMISSAS'!D38 -> 1047840 | D38: ='12_MODELO'!C38*'12_MODELO'!BE38 -> 89066.4 | E38: ='12_MODELO'!C38-'12_MODELO'!D38 -> 958773.6 | F38: ='12_MODELO'!C38*'08_PREMISSAS'!E38 -> 682143.84 | G38: ='12_MODELO'!E38-'12_MODELO'!F38 -> 276629.76 | H38: ='08_PREMISSAS'!J38 -> 102600 | I38: ='12_MODELO'!C38*'08_PREMISSAS'!F38 -> 35626.56 | J38: ='08_PREMISSAS'!L38 -> 33000 | K38: ='08_PREMISSAS'!M38 -> 19000 | L38: ='12_MODELO'!C38*'08_PREMISSAS'!G38 -> 22004.64 | M38: =SUM('12_MODELO'!H38:'12_MODELO'!L38) -> 212231.2 | N38: ='12_MODELO'!G38-'12_MODELO'!M38 -> 64398.56 | O38: =MIN('12_MODELO'!AC37*'12_MODELO'!BH38,'12_MODELO'!AC37-'12_MODELO'!AD37+'12_MODELO'!AB38) -> 20040 | P38: ='12_MODELO'!N38-'12_MODELO'!O38 -> 44358.56 | Q38: ='12_MODELO'!AG37*'12_MODELO'!BG38 -> 7008 | R38: ='12_MODELO'!P38-'12_MODELO'!Q38 -> 37350.56 | S38: =MAX(0,'12_MODELO'!R38)*'12_MODELO'!BF38 -> 12699.19 | T38: ='12_MODELO'!R38-'12_MODELO'!S38 -> 24651.37 | U38: ='12_MODELO'!C38*'12_MODELO'!BB38/30 -> 1397120 | V38: ='12_MODELO'!F38*'12_MODELO'!BC38/30 -> 1023215.8 | W38: ='12_MODELO'!F38+'12_MODELO'!V38-'12_MODELO'!V37 -> 426339.9 | X38: ='12_MODELO'!F38*'12_MODELO'!BD38/30 -> 818572.61 | Y38: ='12_MODELO'!H38*20% -> 20520 | Z38: ='12_MODELO'!D38 -> 89066.4 | AA38: ='12_MODELO'!S38 -> 12699.19 | AB38: ='08_PREMISSAS'!V38 -> 18000 | AC38: ='12_MODELO'!AC37+'12_MODELO'!AB38 -> 2022000 | AD38: ='12_MODELO'!AD37+'12_MODELO'!O38 -> 524880 | AE38: ='08_PREMISSAS'!W38 -> 0 | AF38: ='08_PREMISSAS'!X38 -> 18000 | AG38: ='12_MODELO'!AG37+'12_MODELO'!AE38-'12_MODELO'!AF38 -> 566000 | AH38: ='08_PREMISSAS'!Y38 -> 0 | AI38: ='12_MODELO'!AI37 -> 3900000 | AJ38: ='12_MODELO'!AJ37+'12_MODELO'!T38-'12_MODELO'!AH38 -> 917295.35 | AK38: ='12_MODELO'!U37+'12_MODELO'!C38-'12_MODELO'!U38 -> 1397120 | AL38: ='12_MODELO'!X37+'12_MODELO'!W38-'12_MODELO'!X38 -> 630983.05 | AM38: ='12_MODELO'!M38+'12_MODELO'!Y37-'12_MODELO'!Y38 -> 210711.2 | AN38: ='12_MODELO'!Z37+'12_MODELO'!D38-'12_MODELO'!Z38 -> 111333 | AO38: ='12_MODELO'!AA37+'12_MODELO'!S38-'12_MODELO'!AA38 -> 34130.628 | AP38: ='12_MODELO'!AK38-'12_MODELO'!AL38-'12_MODELO'!AM38-'12_MODELO'!AN38-'12_MODELO'!Q38-'12_MODELO'!AO38 -> 402954.12 | AQ38: ='12_MODELO'!T38+'12_MODELO'!O38-('12_MODELO'!U38-'12_MODELO'!U37)-('12_MODELO'!V38-'12_MODELO'!V37)+('12_MODELO'!X38-'12_MODELO'!X37)+('12_MODELO'!Y38-'12_MODELO'!Y37)+('12_MODELO'!Z38-'12_MODELO'!Z37)+('12_MODELO'!AA38-'12_MODELO'!AA37) -> 402954.12 | AR38: =-'12_MODELO'!AB38 -> -18000 | AS38: ='12_MODELO'!AE38-'12_MODELO'!AF38-'12_MODELO'!AH38 -> -18000 | AT38: ='12_MODELO'!AQ38+'12_MODELO'!AR38+'12_MODELO'!AS38 -> 366954.12 | AU38: ='12_MODELO'!AV37 -> 2039743.7 | AV38: ='12_MODELO'!AU38+'12_MODELO'!AT38 -> 2406697.8 | AW38: ='12_MODELO'!AV38+'12_MODELO'!U38+'12_MODELO'!V38+'12_MODELO'!AC38-'12_MODELO'!AD38 -> 6324153.5 | AX38: ='12_MODELO'!X38+'12_MODELO'!Y38+'12_MODELO'!Z38+'12_MODELO'!AA38+'12_MODELO'!AG38 -> 1506858.2 | AY38: ='12_MODELO'!AI38+'12_MODELO'!AJ38 -> 4817295.3 | AZ38: ='12_MODELO'!AW38-'12_MODELO'!AX38-'12_MODELO'!AY38 -> -9.3132257e-10 | BA38: ='12_MODELO'!AP38-'12_MODELO'!AQ38 -> 0 | BB38: ='08_PREMISSAS'!O38 -> 40 | BC38: ='08_PREMISSAS'!P38 -> 45 | BD38: ='08_PREMISSAS'!Q38 -> 36 | BE38: ='08_PREMISSAS'!R38 -> 0.085 | BF38: ='08_PREMISSAS'!S38 -> 0.34 | BG38: ='08_PREMISSAS'!T38 -> 0.012 | BH38: ='08_PREMISSAS'!U38 -> 0.01 | BI38: =IFERROR('12_MODELO'!N38/'12_MODELO'!E38,0) -> 0.06716764 | BJ38: =IFERROR('12_MODELO'!T38/'12_MODELO'!E38,0) -> 0.025711356 | BK38: ='12_MODELO'!AQ38+'12_MODELO'!AR38 -> 384954.12 | BL38: ='12_MODELO'!U38+'12_MODELO'!V38-'12_MODELO'!X38-'12_MODELO'!Y38-'12_MODELO'!Z38-'12_MODELO'!AA38 -> 1479477.6 | BM38: ='12_MODELO'!AG38-'12_MODELO'!AV38 -> -1840697.8 | BN38: =0 -> 0 | BO38: ='12_MODELO'!AV38+'12_MODELO'!U38+'12_MODELO'!V38 -> 4827033.5 | BP38: ='12_MODELO'!AC38-'12_MODELO'!AD38 -> 1497120 | BQ38: =MIN('12_MODELO'!AG38,'12_MODELO'!AF38*12) -> 216000 | BR38: ='12_MODELO'!AG38-'12_MODELO'!BQ38 -> 350000 | BS38: ='12_MODELO'!AX38-'12_MODELO'!BR38 -> 1156858.2 | BT38: ='12_MODELO'!BR38 -> 350000 | BU38: =IFERROR('12_MODELO'!BO38/'12_MODELO'!BS38,0) -> 4.1725369
... A49: 45992 | B49: Orçamento | C49: ='08_PREMISSAS'!C49*'08_PREMISSAS'!D49 -> 1545564 | D49: ='12_MODELO'!C49*'12_MODELO'!BE49 -> 131372.94 | E49: ='12_MODELO'!C49-'12_MODELO'!D49 -> 1414191.1 | F49: ='12_MODELO'!C49*'08_PREMISSAS'!E49 -> 1006162.2 | G49: ='12_MODELO'!E49-'12_MODELO'!F49 -> 408028.9 | H49: ='08_PREMISSAS'!J49 -> 102600 | I49: ='12_MODELO'!C49*'08_PREMISSAS'!F49 -> 52549.176 | J49: ='08_PREMISSAS'!L49 -> 33000 | K49: ='08_PREMISSAS'!M49 -> 19000 | L49: ='12_MODELO'!C49*'08_PREMISSAS'!G49 -> 32456.844 | M49: =SUM('12_MODELO'!H49:'12_MODELO'!L49) -> 239606.02 | N49: ='12_MODELO'!G49-'12_MODELO'!M49 -> 168422.88 | O49: =MIN('12_MODELO'!AC48*'12_MODELO'!BH49,'12_MODELO'!AC48-'12_MODELO'!AD48+'12_MODELO'!AB49) -> 24180 | P49: ='12_MODELO'!N49-'12_MODELO'!O49 -> 144242.88 | Q49: ='12_MODELO'!AG48*'12_MODELO'!BG49 -> 8832 | R49: ='12_MODELO'!P49-'12_MODELO'!Q49 -> 135410.88 | S49: =MAX(0,'12_MODELO'!R49)*'12_MODELO'!BF49 -> 46039.698 | T49: ='12_MODELO'!R49-'12_MODELO'!S49 -> 89371.178 | U49: ='12_MODELO'!C49*'12_MODELO'!BB49/30 -> 2060752 | V49: ='12_MODELO'!F49*'12_MODELO'!BC49/30 -> 1509243.2 | W49: ='12_MODELO'!F49+'12_MODELO'!V49-'12_MODELO'!V48 -> 865470 | X49: ='12_MODELO'!F49*'12_MODELO'!BD49/30 -> 1207394.6 | Y49: ='12_MODELO'!H49*20% -> 20520 | Z49: ='12_MODELO'!D49 -> 131372.94 | AA49: ='12_MODELO'!S49 -> 46039.698 | AB49: ='08_PREMISSAS'!V49 -> 90000 | AC49: ='12_MODELO'!AC48+'12_MODELO'!AB49 -> 2508000 | AD49: ='12_MODELO'!AD48+'12_MODELO'!O49 -> 770160 | AE49: ='08_PREMISSAS'!W49 -> 0 | AF49: ='08_PREMISSAS'!X49 -> 18000 | AG49: ='12_MODELO'!AG48+'12_MODELO'!AE49-'12_MODELO'!AF49 -> 718000 | AH49: ='08_PREMISSAS'!Y49 -> 0 | AI49: ='12_MODELO'!AI48 -> 3900000 | AJ49: ='12_MODELO'!AJ48+'12_MODELO'!T49-'12_MODELO'!AH49 -> 1641698.1 | AK49: ='12_MODELO'!U48+'12_MODELO'!C49-'12_MODELO'!U49 -> 1737668 | AL49: ='12_MODELO'!X48+'12_MODELO'!W49-'12_MODELO'!X49 -> 978023.73 | AM49: ='12_MODELO'!M49+'12_MODELO'!Y48-'12_MODELO'!Y49 -> 239606.02 | AN49: ='12_MODELO'!Z48+'12_MODELO'!D49-'12_MODELO'!Z49 -> 143619.57 | AO49: ='12_MODELO'!AA48+'12_MODELO'!S49-'12_MODELO'!AA49 -> 56265.641 | AP49: ='12_MODELO'!AK49-'12_MODELO'!AL49-'12_MODELO'!AM49-'12_MODELO'!AN49-'12_MODELO'!Q49-'12_MODELO'!AO49 -> 311321.04 | AQ49: ='12_MODELO'!T49+'12_MODELO'!O49-('12_MODELO'!U49-'12_MODELO'!U48)-('12_MODELO'!V49-'12_MODELO'!V48)+('12_MODELO'!X49-'12_MODELO'!X48)+('12_MODELO'!Y49-'12_MODELO'!Y48)+('12_MODELO'!Z49-'12_MODELO'!Z48)+('12_MODELO'!AA49-'12_MODELO'!AA48) -> 311321.04 | AR49: =-'12_MODELO'!AB49 -> -90000 | AS49: ='12_MODELO'!AE49-'12_MODELO'!AF49-'12_MODELO'!AH49 -> -18000 | AT49: ='12_MODELO'!AQ49+'12_MODELO'!AR49+'12_MODELO'!AS49 -> 203321.04 | AU49: ='12_MODELO'!AV48 -> 2153869 | AV49: ='12_MODELO'!AU49+'12_MODELO'!AT49 -> 2357190 | AW49: ='12_MODELO'!AV49+'12_MODELO'!U49+'12_MODELO'!V49+'12_MODELO'!AC49-'12_MODELO'!AD49 -> 7665025.3 | AX49: ='12_MODELO'!X49+'12_MODELO'!Y49+'12_MODELO'!Z49+'12_MODELO'!AA49+'12_MODELO'!AG49 -> 2123327.2 | AY49: ='12_MODELO'!AI49+'12_MODELO'!AJ49 -> 5541698.1 | AZ49: ='12_MODELO'!AW49-'12_MODELO'!AX49-'12_MODELO'!AY49 -> -9.3132257e-10 | BA49: ='12_MODELO'!AP49-'12_MODELO'!AQ49 -> -1.1641532e-10 | BB49: ='08_PREMISSAS'!O49 -> 40 | BC49: ='08_PREMISSAS'!P49 -> 45 | BD49: ='08_PREMISSAS'!Q49 -> 36 | BE49: ='08_PREMISSAS'!R49 -> 0.085 | BF49: ='08_PREMISSAS'!S49 -> 0.34 | BG49: ='08_PREMISSAS'!T49 -> 0.012 | BH49: ='08_PREMISSAS'!U49 -> 0.01 | BI49: =IFERROR('12_MODELO'!N49/'12_MODELO'!E49,0) -> 0.11909485 | BJ49: =IFERROR('12_MODELO'!T49/'12_MODELO'!E49,0) -> 0.063195972 | BK49: ='12_MODELO'!AQ49+'12_MODELO'!AR49 -> 221321.04 | BL49: ='12_MODELO'!U49+'12_MODELO'!V49-'12_MODELO'!X49-'12_MODELO'!Y49-'12_MODELO'!Z49-'12_MODELO'!AA49 -> 2164668 | BM49: ='12_MODELO'!AG49-'12_MODELO'!AV49 -> -1639190 | BN49: =0 -> 0 | BO49: ='12_MODELO'!AV49+'12_MODELO'!U49+'12_MODELO'!V49 -> 5927185.3 | BP49: ='12_MODELO'!AC49-'12_MODELO'!AD49 -> 1737840 | BQ49: =MIN('12_MODELO'!AG49,'12_MODELO'!AF49*12) -> 216000 | BR49: ='12_MODELO'!AG49-'12_MODELO'!BQ49 -> 502000 | BS49: ='12_MODELO'!AX49-'12_MODELO'!BR49 -> 1621327.2 | BT49: ='12_MODELO'!BR49 -> 502000 | BU49: =IFERROR('12_MODELO'!BO49/'12_MODELO'!BS49,0) -> 3.6557613
A50: 45658 | B50: Forecast 6+6 | C50: ='12_MODELO'!C14 -> 1151091.5 | D50: ='12_MODELO'!D14 -> 97842.777 | E50: ='12_MODELO'!E14 -> 1053248.7 | F50: ='12_MODELO'!F14 -> 786981.58 | G50: ='12_MODELO'!G14 -> 266267.13 | H50: ='12_MODELO'!H14 -> 105925 | I50: ='12_MODELO'!I14 -> 41439.29 | J50: ='12_MODELO'!J14 -> 33920 | ... BM50: ='12_MODELO'!BM14 -> -1141637.3 | BN50: =0 -> 0 | BO50: ='12_MODELO'!BO14 -> 4875115.4 | BP50: ='12_MODELO'!BP14 -> 1497120 | BQ50: ='12_MODELO'!BQ14 -> 216000 | BR50: ='12_MODELO'!BR14 -> 350000 | BS50: ='12_MODELO'!BS14 -> 1257406.2 | BT50: ='12_MODELO'!BT14 -> 350000 | BU50: ='12_MODELO'!BU14 -> 3.8771204
A51: 45689 | B51: Forecast 6+6 | C51: ='12_MODELO'!C15 -> 1176731.8 | D51: ='12_MODELO'!D15 -> 100022.2 | E51: ='12_MODELO'!E15 -> 1076709.6 | F51: ='12_MODELO'!F15 -> 805807.26 | G51: ='12_MODELO'!G15 -> 270902.3 | H51: ='12_MODELO'!H15 -> 105925 | I51: ='12_MODELO'!I15 -> 42362.34 | J51: ='12_MODELO'!J15 -> 33920 | ... BM51: ='12_MODELO'!BM15 -> -1106600.6 | BN51: =0 -> 0 | BO51: ='12_MODELO'!BO15 -> 4894879.7 | BP51: ='12_MODELO'!BP15 -> 1494900 | BQ51: ='12_MODELO'!BQ15 -> 216000 | BR51: ='12_MODELO'!BR15 -> 332000 | BS51: ='12_MODELO'!BS15 -> 1282631.5 | BT51: ='12_MODELO'!BT15 -> 332000 | BU51: ='12_MODELO'!BU15 -> 3.8162789
A52: 45717 | B52: Forecast 6+6 | C52: ='12_MODELO'!C16 -> 1389953.1 | D52: ='12_MODELO'!D16 -> 118146.01 | E52: ='12_MODELO'!E16 -> 1271807.1 | F52: ='12_MODELO'!F16 -> 952291.92 | G52: ='12_MODELO'!G16 -> 319515.15 | H52: ='12_MODELO'!H16 -> 105925 | I52: ='12_MODELO'!I16 -> 50038.31 | J52: ='12_MODELO'!J16 -> 33920 | ... BM52: ='12_MODELO'!BM16 -> -684670.77 | BN52: =0 -> 0 | BO52: ='12_MODELO'!BO16 -> 5042903.3 | BP52: ='12_MODELO'!BP16 -> 1564500 | BQ52: ='12_MODELO'!BQ16 -> 216000 | BR52: ='12_MODELO'!BR16 -> 314000 | BS52: ='12_MODELO'!BS16 -> 1483990 | BT52: ='12_MODELO'!BT16 -> 314000 | BU52: ='12_MODELO'!BU16 -> 3.3982057
A53: 45748 | B53: Forecast 6+6 | C53: ='12_MODELO'!C17 -> 1384297.2 | D53: ='12_MODELO'!D17 -> 117665.26 | E53: ='12_MODELO'!E17 -> 1266632 | F53: ='12_MODELO'!F17 -> 950090.68 | G53: ='12_MODELO'!G17 -> 316541.28 | H53: ='12_MODELO'!H17 -> 105925 | I53: ='12_MODELO'!I17 -> 49834.7 | J53: ='12_MODELO'!J17 -> 33920 | ... BM53: ='12_MODELO'!BM17 -> -700533.54 | BN53: =0 -> 0 | BO53: ='12_MODELO'!BO17 -> 5378089.7 | BP53: ='12_MODELO'!BP17 -> 1561200 | BQ53: ='12_MODELO'!BQ17 -> 216000 | BR53: ='12_MODELO'!BR17 -> 646000 | BS53: ='12_MODELO'!BS17 -> 1470289 | BT53: ='12_MODELO'!BT17 -> 646000 | BU53: ='12_MODELO'!BU17 -> 3.6578453
A54: 45778 | B54: Forecast 6+6 | C54: ='12_MODELO'!C18 -> 1449678.5 | D54: ='12_MODELO'!D18 -> 123222.68 | E54: ='12_MODELO'!E18 -> 1326455.9 | F54: ='12_MODELO'!F18 -> 991818.4 | G54: ='12_MODELO'!G18 -> 334637.45 | H54: ='12_MODELO'!H18 -> 105925 | I54: ='12_MODELO'!I18 -> 52188.43 | J54: ='12_MODELO'!J18 -> 33920 | ... BM54: ='12_MODELO'!BM18 -> -607222.02 | BN54: =0 -> 0 | BO54: ='12_MODELO'!BO18 -> 5441536.9 | BP54: ='12_MODELO'!BP18 -> 1557720 | BQ54: ='12_MODELO'!BQ18 -> 216000 | BR54: ='12_MODELO'!BR18 -> 628000 | BS54: ='12_MODELO'!BS18 -> 1527976.4 | BT54: ='12_MODELO'!BT18 -> 628000 | BU54: ='12_MODELO'!BU18 -> 3.5612704
A55: 45809 | B55: Forecast 6+6 | C55: ='12_MODELO'!C19 -> 1471161 | D55: ='12_MODELO'!D19 -> 125048.68 | E55: ='12_MODELO'!E19 -> 1346112.3 | F55: ='12_MODELO'!F19 -> 1007209.9 | G55: ='12_MODELO'!G19 -> 338902.35 | H55: ='12_MODELO'!H19 -> 105925 | I55: ='12_MODELO'!I19 -> 52961.79 | J55: ='12_MODELO'!J19 -> 33920 | ... BM55: ='12_MODELO'!BM19 -> -549665.14 | BN55: =0 -> 0 | BO55: ='12_MODELO'!BO19 -> 5426314.6 | BP55: ='12_MODELO'!BP19 -> 1626060 | BQ55: ='12_MODELO'!BQ19 -> 216000 | BR55: ='12_MODELO'!BR19 -> 610000 | BS55: ='12_MODELO'!BS19 -> 1558317.8 | BT55: ='12_MODELO'!BT19 -> 610000 | BU55: ='12_MODELO'!BU19 -> 3.4821616
A56: 45839 | B56: Forecast 6+6 | C56: ='08_PREMISSAS'!C56*'08_PREMISSAS'!D56 -> 1147740 | D56: ='12_MODELO'!C56*'12_MODELO'!BE56 -> 97557.9 | E56: ='12_MODELO'!C56-'12_MODELO'!D56 -> 1050182.1 | F56: ='12_MODELO'!C56*'08_PREMISSAS'!E56 -> 771281.28 | G56: ='12_MODELO'!E56-'12_MODELO'!F56 -> 278900.82 | H56: ='08_PREMISSAS'!J56 -> 112000 | I56: ='12_MODELO'!C56*'08_PREMISSAS'!F56 -> 41318.64 | J56: ='08_PREMISSAS'!L56 -> 33920 | K56: ='08_PREMISSAS'!M56 -> 20160 | L56: ='12_MODELO'!C56*'08_PREMISSAS'!G56 -> 26398.02 | M56: =SUM('12_MODELO'!H56:'12_MODELO'!L56) -> 233796.66 | N56: ='12_MODELO'!G56-'12_MODELO'!M56 -> 45104.16 | O56: =MIN('12_MODELO'!AC55*'12_MODELO'!BH56,'12_MODELO'!AC55-'12_MODELO'!AD55+'12_MODELO'!AB56) -> 22560 | P56: ='12_MODELO'!N56-'12_MODELO'!O56 -> 22544.16 | Q56: ='12_MODELO'!AG55*'12_MODELO'!BG56 -> 9912 | R56: ='12_MODELO'!P56-'12_MODELO'!Q56 -> 12632.16 | S56: =MAX(0,'12_MODELO'!R56)*'12_MODELO'!BF56 -> 4294.9344 | T56: ='12_MODELO'!R56-'12_MODELO'!S56 -> 8337.2256 | U56: ='12_MODELO'!C56*'12_MODELO'!BB56/30 -> 1912900 | V56: ='12_MODELO'!F56*'12_MODELO'!BC56/30 -> 1414015.7 | W56: ='12_MODELO'!F56+'12_MODELO'!V56-'12_MODELO'!V55 -> 439466.4 | X56: ='12_MODELO'!F56*'12_MODELO'!BD56/30 -> 899828.16 | Y56: ='12_MODELO'!H56*20% -> 22400 | Z56: ='12_MODELO'!D56 -> 97557.9 | AA56: ='12_MODELO'!S56 -> 4294.9344 | AB56: ='08_PREMISSAS'!V56 -> 18000 | AC56: ='12_MODELO'!AC55+'12_MODELO'!AB56 -> 2274000 | AD56: ='12_MODELO'!AD55+'12_MODELO'!O56 -> 652500 | AE56: ='08_PREMISSAS'!W56 -> 0 | AF56: ='08_PREMISSAS'!X56 -> 18000 | AG56: ='12_MODELO'!AG55+'12_MODELO'!AE56-'12_MODELO'!AF56 -> 808000 | AH56: ='08_PREMISSAS'!Y56 -> 0 | AI56: ='12_MODELO'!AI55 -> 3900000 | AJ56: ='12_MODELO'!AJ55+'12_MODELO'!T56-'12_MODELO'!AH56 -> 992393.95 | AK56: ='12_MODELO'!U55+'12_MODELO'!C56-'12_MODELO'!U56 -> 1539658.9 | AL56: ='12_MODELO'!X55+'12_MODELO'!W56-'12_MODELO'!X56 -> 714716.5 | AM56: ='12_MODELO'!M56+'12_MODELO'!Y55-'12_MODELO'!Y56 -> 232581.66 | AN56: ='12_MODELO'!Z55+'12_MODELO'!D56-'12_MODELO'!Z56 -> 125048.68 | AO56: ='12_MODELO'!AA55+'12_MODELO'!S56-'12_MODELO'!AA56 -> 21005.886 | AP56: ='12_MODELO'!AK56-'12_MODELO'!AL56-'12_MODELO'!AM56-'12_MODELO'!AN56-'12_MODELO'!Q56-'12_MODELO'!AO56 -> 436394.12 | AQ56: ='12_MODELO'!T56+'12_MODELO'!O56-('12_MODELO'!U56-'12_MODELO'!U55)-('12_MODELO'!V56-'12_MODELO'!V55)+('12_MODELO'!X56-'12_MODELO'!X55)+('12_MODELO'!Y56-'12_MODELO'!Y55)+('12_MODELO'!Z56-'12_MODELO'!Z55)+('12_MODELO'!AA56-'12_MODELO'!AA55) -> 436394.12 | AR56: =-'12_MODELO'!AB56 -> -18000 | AS56: ='12_MODELO'!AE56-'12_MODELO'!AF56-'12_MODELO'!AH56 -> -18000 | AT56: ='12_MODELO'!AQ56+'12_MODELO'!AR56+'12_MODELO'!AS56 -> 400394.12 | AU56: ='12_MODELO'!AV55 -> 1375665.1 | AV56: ='12_MODELO'!AU56+'12_MODELO'!AT56 -> 1776059.3 | AW56: ='12_MODELO'!AV56+'12_MODELO'!U56+'12_MODELO'!V56+'12_MODELO'!AC56-'12_MODELO'!AD56 -> 6724474.9 | AX56: ='12_MODELO'!X56+'12_MODELO'!Y56+'12_MODELO'!Z56+'12_MODELO'!AA56+'12_MODELO'!AG56 -> 1832081 | AY56: ='12_MODELO'!AI56+'12_MODELO'!AJ56 -> 4892394 | AZ56: ='12_MODELO'!AW56-'12_MODELO'!AX56-'12_MODELO'!AY56 -> -9.3132257e-10 | BA56: ='12_MODELO'!AP56-'12_MODELO'!AQ56 -> -1.1641532e-10 | BB56: ='08_PREMISSAS'!O56 -> 50 | BC56: ='08_PREMISSAS'!P56 -> 55 | BD56: ='08_PREMISSAS'!Q56 -> 35 | BE56: ='08_PREMISSAS'!R56 -> 0.085 | BF56: ='08_PREMISSAS'!S56 -> 0.34 | BG56: ='08_PREMISSAS'!T56 -> 0.012 | BH56: ='08_PREMISSAS'!U56 -> 0.01 | BI56: =IFERROR('12_MODELO'!N56/'12_MODELO'!E56,0) -> 0.042948894 | BJ56: =IFERROR('12_MODELO'!T56/'12_MODELO'!E56,0) -> 0.007938838 | BK56: ='12_MODELO'!AQ56+'12_MODELO'!AR56 -> 418394.12 | BL56: ='12_MODELO'!U56+'12_MODELO'!V56-'12_MODELO'!X56-'12_MODELO'!Y56-'12_MODELO'!Z56-'12_MODELO'!AA56 -> 2302834.7 | BM56: ='12_MODELO'!AG56-'12_MODELO'!AV56 -> -968059.27 | BN56: =0 -> 0 | BO56: ='12_MODELO'!AV56+'12_MODELO'!U56+'12_MODELO'!V56 -> 5102974.9 | BP56: ='12_MODELO'!AC56-'12_MODELO'!AD56 -> 1621500 | BQ56: =MIN('12_MODELO'!AG56,'12_MODELO'!AF56*12) -> 216000 | BR56: ='12_MODELO'!AG56-'12_MODELO'!BQ56 -> 592000 | BS56: ='12_MODELO'!AX56-'12_MODELO'!BR56 -> 1240081 | BT56: ='12_MODELO'!BR56 -> 592000 | BU56: =IFERROR('12_MODELO'!BO56/'12_MODELO'!BS56,0) -> 4.1150336
